Workbook

Sheet DropdownLIST
A1: HEADS
A2: MCGS | B2: IMO Manager
A3: BPB | B3: Operations & Maintenance SectionHead
A4: LFCP | B4: Engineering Section Head
A5: VEP | B5: Finance Section Head
A6: VMM | B6: Senior Accounting Processor A
A7: MME | B7: Administrative Section Head
A10: SECTION | G10: ENG'G | H10: OMS | I10: ADMIN | J10: FINANCE | K10: BAC | L10: CATNES | M10: IMO
A11: ENG'G | G11: BILLING | H11: CERTIFICATIONS | I11: APPLICANTS | J11: CERTIFICATIONS | K11: CERTIFICATIONS | L11: BILLING | M11: CERTIFICATIONS
A12: OMS | G12: CERTIFICATIONS | H12: COMMUNICATION LETTER | I12: AUTHORITY TO RENDER OVERTIME SERVICES | J12: CHEQUES/JEV | K12: COMMUNICATION LETTER | L12: CERTIFICATIONS | M12: COMMUNICATION LETTER
A13: ADMIN | G13: COMMUNICATION LETTER | H13: GATE PASS, RIS, TRIP TICKET, TRANSPO REQ | I13: CERTIFICATIONS | J13: COMMUNICATION LETTER | K13: LOCATOR SLIP | L13: COMMUNICATION LETTER | M13: LOCATOR SLIP
A14: FINANCE | G14: CONTRACT TIME ADJUSTMENT | H14: INSPECTION REPORT | I14: COMMUNICATION LETTER | J14: LOCATOR SLIP | K14: MINUTES | L14: CONTRACT TIME ADJUSTMENT | M14: MINUTES
A15: BAC | G15: FIVC/FINAL INSPECTION REPORT | H15: LOCATOR SLIP | I15: LOCATOR SLIP | J15: MINUTES | K15: RESOLUTION | L15: FIVC/FINAL INSPECTION REPORT | M15: RESOLUTION
A16: CATNES | G16: FSDE | H16: MINUTES | I16: MINUTES | J16: PAYROLL | K16: TRANSMITTAL | L16: FSDE | M16: TRANSMITTAL
A17: IMO | G17: INSPECTION REPORT | H17: PROJECT PROPOSAL | I17: PAYROLL | J17: RESOLUTION | K17: TRAVEL ORDER/ITINERARY | L17: INSPECTION REPORT | M17: TRAVEL ORDER/ITINERARY
G18: LOCATOR SLIP | H18: RESOLUTION | I18: PURCHASE ORDER | J18: TRANSMITTAL | K18: POST QUALIFICATION EVALUATION | L18: LOCATOR SLIP
G19: MINUTES | H19: TRANSMITTAL | I19: RESOLUTION | J19: TRAVEL ORDER/ITINERARY | K19: VERIFICATION OF PERFORMANCE/TRACK RECORD | L19: MINUTES
G20: PLANS | H20: TRAVEL ORDER/ITINERARY | I20: TRANSMITTAL | L20: PLANS
G21: PROGRAM OF WORKS | I21: TRAVEL ORDER/ITINERARY | L21: PROGRAM OF WORKS
G22: RESOLUTION | I22: OTHER ADMIN CONCERNS | L22: RESOLUTION
G23: TRANSMITTAL | L23: TRANSMITTAL
G24: TRAVEL ORDER/ITINERARY | L24: TRAVEL ORDER/ITINERARY
G25: VARIATION ORDERS | L25: VARIATION ORDERS

Sheet 0102
A1: INCOMING DOCUMENTS TO THE OFFICE OF THE IMO MANAGER
A2: 45659
A3: =TEXT(A2,"DDDD") -> Thursday
A4: NOTE: | B4: IMO on leave, OIC: BPB until 11:30AM, OIC after 11:30 : LFCP
A5: NO. | C5: DOCUMENT | E5: SECTION | F5: TO | G5: REMARKS
A6: =A2 -> 45659 | B6: 1 | C6: ITINERARY: OMS-TO001 | E6: OMS | F6: BPB | G6: FOR SIGNATURE
A7: =A6 -> 45659 | B7: =B6+1 -> 2 | C7: 8th Supplemental (APP FY 2024) | E7: BAC | F7: MCGS | G7: FOR SIGNATURE
A8: =A7 -> 45659 | B8: =B7+1 -> 3 | C8: Personnel Locator Slip: 01/02/2025, NB Nash, Official, 10:00AM | E8: ENG'G | F8: BPB | G8: FOR SIGNATURE
A9: =A8 -> 45659 | B9: =B8+1 -> 4 | C9: TRAVEL ORDER: ENG-TO002 | E9: ENG'G | F9: LFCP | G9: FOR SIGNATURE
A10: =A9 -> 45659 | B10: =B9+1 -> 5 | C10: ITINERARY: OMS-TO002 | E10: OMS | F10: LFCP | G10: FOR SIGNATURE
A11: =A10 -> 45659 | B11: =B10+1 -> 6 | C11: FIVC & FINAL INSPECTION REPORT: (FOR SIGNATURE) Tagoytoy CIS (ALCARP-REPCIS-015-24INF) | E11: ENG'G | F11: MCGS | G11: FOR SIGNATURE
A12: =A11 -> 45659 | B12: =B11+1 -> 7 | C12: FINAL INSPECTION REPORT: (with Punchlist) ALIBUAG CIS (CAT-REPCIS-003-24INF) | E12: CATNES | F12: MME | G12: (Original Copy) Forwarded to Admin to be sent to Cat'nes
A13: =A12 -> 45659 | B13: =B12+1 -> 8 | C13: Currents Volume 57, No. 2 2023 (21 pcs) Gearing Up to Build Better More Irrigation Infrastructures | E13: IMO | F13: MCGS
A14: =A13 -> 45659 | B14: =B13+1 -> 9 | C14: Approved Feasibility Study Report: AROYAO PIP, CAGDARAO SIP, MACULIW CIP | E14: ENG'G | F14: LFCP | G14: Forwarded to Eng'g
A15: =A14 -> 45659 | B15: =B14+1 -> 10 | C15: Comments on the Submitted FSDE for the Modernization of Cabilogan-San Juan RIS | E15: ENG'G | F15: LFCP | G15: Forwarded to Eng'g
A16: =A15 -> 45659 | B16: =B15+1 -> 11 | C16: Transmittal to Region: SUBMISSION OF AUDIT COMPLIANCE PROGRESS REPORT (ACPR) RE: OPERATIONS PERFORMANCE AUDIT | E16: ENG'G | F16: LFCP | G16: FOR SIGNATURE
A17: =A16 -> 45659 | B17: =B16+1 -> 12 | C17: TRAVEL ORDER: OMS-TO006 | E17: OMS | F17: LFCP | G17: FOR SIGNATURE
A18: ***NOTHING FOLLOWS***
A20: Received, Recorded & Forwarded: | D20: Tracked Disseminated & Filed:
D22: (not yet recalled) | F22: (not yet recalled)
A23: COLEEN M. RASTRULLO | D23: ELLA N. RINGAD | F23: JESSICA V. PEÑAFLOR
A24: Engineering Assistant A | D24: Clerk Processor A | F24: Information Officer C

Sheet 0103
A1: INCOMING DOCUMENTS TO THE OFFICE OF THE IMO MANAGER
A2: 45660
A3: =TEXT(A2,"DDDD") -> Friday
A4: NOTE:
A5: NO. | C5: DOCUMENT | E5: SECTION | F5: TO | G5: REMARKS
A6: =A2 -> 45660 | B6: 1 | C6: Travel Order: ENG-TO003 | E6: ENG'G | F6: MCGS | G6: For Signature
A7: =A6 -> 45660 | B7: =B6+1 -> 2 | C7: Travel Order: ENG-TO004 | E7: ENG'G | F7: MCGS | G7: For Signature
A8: =A7 -> 45660 | B8: =B7+1 -> 3 | C8: Transmittal to Region: SIGNED FIVC & FINAL INSPECTION REPORT BY IMO MANAGER FOR TAGOYTOY CIS CONTRACT NO: ALCARP-REPCIS-015-24INF | E8: ENG'G | F8: MCGS | G8: For Signature
A9: =A8 -> 45660 | B9: =B8+1 -> 4 | C9: NOTICE OF MEETING INVITATION Sunwest Inc., 01/09/2025 (Thursday) at NIA ROV | E9: ENG'G | F9: MCGS | G9: For Signature
A10: =A9 -> 45660 | B10: =B9+1 -> 5 | C10: Office Memo: ADM001 s.2025: Various Directives and Reminders | E10: ADMIN | F10: MCGS | G10: For Signature
A11: =A10 -> 45660 | B11: =B10+1 -> 6 | C11: Transmittal to Region: Request for Extension/Creation of job Order Positions for the 1st Semester CY 2025 | E11: ADMIN | F11: MCGS | G11: For Signature
A12: =A11 -> 45660 | B12: =B11+1 -> 7 | C12: To Catanduanes: File Copy of 2nd & Final Billing of Alibuag CIS CAT-REPCIS-002-23 | E12: CATNES | F12: MCGS | G12: For Signature
A13: =A12 -> 45660 | B13: =B12+1 -> 8 | C13: Oas Community College Internship Program of BS inOffice Admin on February 17, 2025 | E13: ADMIN | F13: MCGS
A14: =A13 -> 45660 | B14: =B13+1 -> 9 | C14: APPLICANTS: Guadalupe, Ulyssis (Gate Keeper) Franco Satuid (Dam Operator) | E14: ADMIN | F14: MCGS
A15: =A14 -> 45660 | B15: =B14+1 -> 10 | C15: REQUEST FOR INSPECTION OF COA: Buhi CIS (CAT-REPCIS-001-23) Alibuag CIS (CAT-REPCIS-002-23) Quinartilan CIS (ALCARP-REPCIS-013-24INF) Bagong Abre CIS (AL-REPCIS-004-24INF) Cabilogan San Juan RIS (AL-RESNIS-009-24INF) MNOH Mahaba RIS (TAPSSIA) (AL-REPNIS-011-24INF) | E15: ENG'G | F15: MCGS | G15: For Signature
A16: =A15 -> 45660 | B16: =B15+1 -> 11 | C16: RIS: 001-2025 | E16: OMS | F16: MCGS | G16: For Signature
A17: ***NOTHING FOLLOWS***
A19: Received, Recorded & Forwarded: | D19: Tracked Disseminated & Filed:
D21: (not yet recalled) | F21: (not yet recalled)
A22: COLEEN M. RASTRULLO | D22: ELLA N. RINGAD | F22: JESSICA V. PEÑAFLOR
A23: Engineering Assistant A | D23: Clerk Processor A | F23: Information Officer C

Sheet 0106
A1: INCOMING DOCUMENTS TO THE OFFICE OF THE IMO MANAGER
A2: 45663
A3: =TEXT(A2,"DDDD") -> Monday
A4: NOTE:
A5: NO. | C5: DOCUMENT | D5: SECTION | E5: TO | F5: REMARKS
A6: =A2 -> 45663 | B6: 1 | C6: Personnel Locator Slip 01/06/2025, NBN, 9:00AM, Official | D6: ENG'G | E6: MCGS | F6: For signature
A7: =A6 -> 45663 | B7: =B6+1 -> 2 | C7: Wages (Oct. 1-15, 2024) MP Laynesa | D7: FINANCE | E7: MCGS | F7: For signature
A8: =A7 -> 45663 | B8: =B7+1 -> 3 | C8: Wages(Oct. 16-29, 2024) A. Guarin & 1 | D8: FINANCE | E8: MCGS | F8: For signature
A9: =A8 -> 45663 | B9: =B8+1 -> 4 | C9: Wages(Nov. 1-15, 2024) R.S Nacario | D9: FINANCE | E9: MCGS | F9: For signature
A10: =A9 -> 45663 | B10: =B9+1 -> 5 | C10: Wages(Nov. 16-30, 2024) R.R Warde | D10: FINANCE | E10: MCGS | F10: For signature
A11: =A10 -> 45663 | B11: =B10+1 -> 6 | C11: DRAFT Office Memo: ADM002 : 1st Written Warning ADM003 : Reiteration of the Office Memorandum AD010s.2024 ADM004: Use of Equipment Shed as Hangout Spot, Lounge and/of Kitchen Area | D11: ADMIN | E11: MCGS | F11: For signature
A12: =A11 -> 45663 | B12: =B11+1 -> 7 | C12: Travel Order: ENG-TO005, 006,007,008,009,010 | D12: ENG'G | E12: MCGS | F12: For signature
A13: =A12 -> 45663 | B13: =B12+1 -> 8 | C13: Trvale Order: OMS-TO009 | D13: OMS | E13: MCGS | F13: For signature
A14: =A13 -> 45663 | B14: =B13+1 -> 9 | C14: Personnel Locator Slip 01/06/2025, MAP POLIDARIO, 11:30AM, Official | D14: OMS | E14: MCGS | F14: For signature
A15: =A14 -> 45663 | B15: =B14+1 -> 10 | C15: ITINERARY: OMS-TO007 | D15: OMS | E15: MCGS | F15: For signature
A16: =A15 -> 45663 | B16: =B15+1 -> 11 | C16: ITINERARY: OMS-TO10 | D16: OMS | E16: MCGS | F16: For signature
A17: =A16 -> 45663 | B17: =B16+1 -> 12 | C17: INSPECTION REPORT: Inspection Report (Fallen Tree along MC of Cabilogan-San Juan RIS) (01/06/2025) | D17: OMS | E17: MCGS | F17: For signature
A18: =A17 -> 45663 | B18: =B17+1 -> 13 | C18: Competency Assessment Form of LFCP | D18: ENG'G | E18: MCGS | F18: For signature
... A24: =A23 -> 45663 | B24: =B23+1 -> 19 | C24: To Region: CY 2023 Project Cost Variances of Catanduanes 1. Libjo CIS (2.5M) 2. Dororian CIS (1.5M) 3. Cabuyoan CIS (2M) | D24: ENG'G | E24: MCGS | F24: For signature
A25: =A24 -> 45663 | B25: =B24+1 -> 20 | C25: GSIS: Delayed Remittances Payment for the month of November 2024 | D25: FINANCE | E25: MCGS
A26: =A25 -> 45663 | B26: =B25+1 -> 21 | C26: Notice of Resumption: October 22, 2023 Tilod CIS & Nagbarorong CIS CAT-RREIS-007-23INF | D26: CATNES | E26: MCGS
A27: =A26 -> 45663 | B27: =B26+1 -> 22 | C27: PCR: Repar/Rehab of Marambong CIS RREIS-CT-020-12 | D27: CATNES | E27: MCGS
A28: =A27 -> 45663 | B28: =B27+1 -> 23 | C28: TRAVEL ORDER: ENG-TO012 ITINERARY: ENG-TO013,014,015,016 | D28: ENG'G | E28: MCGS | F28: For signature
A29: =A28 -> 45663 | B29: =B28+1 -> 24 | C29: Office Memo: ADM002 : 1st Written Warning ADM003 : Reiteration of the Office Memorandum AD010s.2024 ADM004: Use of Equipment Shed as Hangout Spot, Lounge and/of Kitchen Area | D29: ADMIN | E29: MCGS | F29: For signature
A30: =A29 -> 45663 | B30: =B29+1 -> 25 | C30: Plantilla of Casual Appointments (JG 8 below) | D30: ADMIN | E30: MCGS | F30: For signature
A31: =A30 -> 45663 | B31: =B30+1 -> 26 | C31: ITINERARY: ENG-TO017,018 OMS-TO011,012,013,014 | D31: ENG'G | E31: MCGS | F31: For signature
A32: =A31 -> 45663 | B32: =B31+1 -> 27 | C32: Personnel Locator Slip 01/06/2025, MAP POLIDARIO, no time, Official | D32: OMS | E32: MCGS | F32: For signature
A33: =A32 -> 45663 | B33: =B32+1 -> 28 | C33: Gate Pass: 005,004,003,009,010,011-2025 RIS: 006,007,005,002,004-2025 Transpo Req: 001,003,004,005,002-2025 Trip Ticket: 001,002,003,004,005,006,007,008-2025 | D33: OMS | E33: MCGS | F33: For signature
A34: =A33 -> 45663 | B34: =B33+1 -> 29 | C34: Turn-Over Documents San Francisco RIS (Repair CIS CY 2022) 20M | D34: ENG'G | E34: MCGS | F34: For signature
A35: =A34 -> 45663 | B35: =B34+1 -> 30 | C35: Application for Leave V. Manlangit, AJ Delgado | D35: FINANCE | E35: MCGS | F35: For signature
A36: =A35 -> 45663 | B36: =B35+1 -> 31 | C36: Transmittal To COA *with attachments: Bank Reconcialiation Statement Fund 501 LFP & CARP-IC for November 2024 | D36: FINANCE | E36: MCGS | F36: For signature
A37: =A36 -> 45663 | B37: =B36+1 -> 32 | C37: Travel Order FIN-TO007 s.2024 | D37: FINANCE | E37: MCGS | F37: For signature
A38: =A37 -> 45663 | B38: =B37+1 -> 33 | C38: Reimbursement of MCG So for May-June 2024 | D38: FINANCE | E38: MCGS | F38: For signature
A39: =A38 -> 45663 | B39: =B38+1 -> 34 | C39: PAG-IBIG Calamity Loan Application Form AB Calpe | D39: ADMIN | E39: MCGS | F39: For signature
... A70: =A69 -> 45663 | B70: =B69+1 -> 65 | C70: RIS: 008-2025 | D70: OMS | E70: MCGS | F70: For signature
A71: ***NOTHING FOLLOWS***
A73: Received, Recorded & Forwarded: | D73: Tracked Disseminated & Filed:
A76: COLEEN M. RASTRULLO | D76: ELLA N. RINGAD | F76: JESSICA V. PEÑAFLOR
A77: Engineering Assistant A | D77: Clerk Processor A | F77: Information Officer C

Sheet 0107
A1: INCOMING DOCUMENTS TO THE OFFICE OF THE IMO MANAGER
A2: 45664
A3: =TEXT(A2,"DDDD") -> Tuesday
A4: NOTE:
A5: NO. | C5: DOCUMENT | F5: TO | G5: REMARKS
C6: SECTION | D6: TYPE
A7: =A2 -> 45664 | B7: 1 | C7: OMS | E7: Gate Pass: 019-2025 RIS: 009,010-2025 Trip Ticket: 010-2025 | F7: MCGS | G7: For Signature
A8: =A7 -> 45664 | B8: =B7+1 -> 2 | C8: OMS | E8: RIS: 011-2025 | F8: MCGS | G8: For Signature
A9: =A8 -> 45664 | B9: =B8+1 -> 3 | C9: OMS | E9: Letters to: Hon. Alfredo Garbin Jr. Hon. Jaime C. Villanueva re: Final Pre-Con on 01/10/2025 at Cagbacong Brgy. Session Hall, 9:30AM | F9: MCGS | G9: For Signature
A10: =A9 -> 45664 | B10: =B9+1 -> 4 | C10: OMS | E10: Itinerary: OMS-TO008 | F10: MCGS | G10: For Signature
A11: =A10 -> 45664 | B11: =B10+1 -> 5 | C11: OMS | E11: To Region: Turn-Over Documents 1. Ogsong RIS (REPNIS 2023) | F11: MCGS | G11: For Signature
A12: =A11 -> 45664 | B12: =B11+1 -> 6 | C12: OMS | E12: TRAVEL ORDER: OMS-TO016, 017,018 | F12: MCGS | G12: For Signature
A13: =A12 -> 45664 | B13: =B12+1 -> 7 | C13: OMS | E13: Personnel Locator Slip: 01/07/2025, 10:00AM, A Lopez, Official | F13: MCGS | G13: For Signature
A14: =A13 -> 45664 | B14: =B13+1 -> 8 | C14: OMS | E14: Travel Order: OMS-TO021 | F14: MCGS | G14: For Signature
A15: =A14 -> 45664 | B15: =B14+1 -> 9 | C15: OMS | E15: Gate Pass: 021-2025 Transpo Req: 011-2025 Travel Order: OMS-TO022 | F15: MCGS | G15: For Signature
A16: =A15 -> 45664 | B16: =B15+1 -> 10 | C16: FINANCE | E16: Cheques & JEV: NIA F-501 LFP - Php 3,587.19 Vilma M. Manlangit - Php 4,582.00 NIA F-501LFP - Php 52,362.02 Senen A. Balondo - Php 2,700.00 Jojo O. Paje - Php 3,150.00 Gratuity Pay: John Kenneth Paje & 2 | F16: MCGS | G16: For Signature
A17: =A16 -> 45664 | B17: =B16+1 -> 11 | E17: TRAVEL ORDER: ENG-TO026 ITINERARY OF TRAVEL: OMS-TO20 & OMS-TO19 | F17: MCGS | G17: For Signature
A18: =A17 -> 45664 | B18: =B17+1 -> 12 | C18: OMS | E18: Gate Pass: January 7, 2025 Karl Daniel Asanza, PE of Sunwest Inc. : 2 sets Mounting Structure & 2 other items thru Howo Boom Truck NFF-8761 | F18: MCGS | G18: For Signature
A19: =A18 -> 45664 | B19: =B18+1 -> 13 | C19: OMS | E19: IDS REGULAR MEETING (JAN. 06, 2024)-4 COPIES | F19: MCGS | G19: For Signature
A20: =A19 -> 45664 | B20: =B19+1 -> 14 | C20: OMS | E20: ITINERARY: OMS-TO024 | F20: MCGS | G20: For Signature
A21: =A20 -> 45664 | B21: =B20+1 -> 15 | C21: IMO | E21: Personnel Locator Slip: 01/07/2025, 1:30PM,EN Ringad, Personal | F21: MCGS | G21: For Signature
A22: =A21 -> 45664 | B22: =B21+1 -> 16 | C22: ENG'G | E22: LGU MALINAO (MAENRO) Letter Request for the Continuation of Irrigation Services Between Bariw and Balading | F22: MCGS
A23: =A22 -> 45664 | B23: =B22+1 -> 17 | C23: BAC | E23: NIA ROV: POST QUALIFICATION EVALUATION CISCO KVF Const & 8 Others | F23: MCGS
A24: =A23 -> 45664 | B24: =B23+1 -> 18 | C24: ADMIN | E24: OM No. 003 s.2025 Readoptation of MC No. 102 s.2024 in all Official Letters and Specific Reports/Forms Regionwide | F24: MCGS
A25: =A24 -> 45664 | B25: =B24+1 -> 19 | C25: BAC | E25: DPWH: VERIFICATION OF PERFORMANCE/TRACK RECORD Dated December 16,17,18,24, 2024 | F25: MCGS
A26: =A25 -> 45664 | B26: =B25+1 -> 20 | C26: BAC | E26: DPWH: VERIFICATION OF PERFORMANCE/TRACK RECORD Dated December 9 & 10, 2024 | F26: MCGS
A27: =A26 -> 45664 | B27: =B26+1 -> 21 | C27: OMS | E27: Gate Pass: 023,022-2025 Travel Order: ADM-TO001 | F27: MCGS | G27: For Signature
A28: =A27 -> 45664 | B28: =B27+1 -> 22 | C28: OMS | E28: Personnel Locator Slip: 01/07/2025, 2:00PM, Official, CL Lontac | F28: MCGS | G28: For Signature
A29: =A28 -> 45664 | B29: =B28+1 -> 23 | C29: OMS | E29: ITINERARY: OMS-TO025 | F29: MCGS | G29: For Signature
A30: =A29 -> 45664 | B30: =B29+1 -> 24 | C30: FINANCE | E30: Cheques w/ Attachments: Albay Electric Cooperative Inc. - Php 803.69 PLDT, Inc - Php 2,061.56 FICELCO - Php 6,394.25 NCIP Region V - Php 20,930.00 | F30: MCGS | G30: For Signature
A31: =A30 -> 45664 | B31: =B30+1 -> 25 | C31: FINANCE | E31: Cheques w/ Attachments: Carlito C. Pongpong - Php 2,000.00 Carlito C. Pongpong - Php 2,000.00 Carlito C. Pongpong - Php 2,000.00 Carlito C. Pongpong - Php 2,000.00 Elizabeth J. Jacob - Php 1,966.00 Jevielyn A. Dolz - Php 3,150.00 Marilou A. Robledo - Php 730.00 Bernardita P. Balingasa - Php 4,4370.00 | F31: MCGS | G31: For Signature
A32: =A31 -> 45664 | B32: =B31+1 -> 26 | C32: ENG'G | E32: 15% Mobilization Santicon SPIP (AL-EGPIPSOL-010-24INF) Grelips Construction and Development | F32: MCGS | G32: For Signature
A33: =A32 -> 45664 | B33: =B32+1 -> 27 | C33: ENG'G | E33: TRAVEL ORDER: ENG-TO027 | F33: MCGS | G33: For Signature
A34: =A33 -> 45664 | B34: =B33+1 -> 28 | C34: OMS | E34: ITINERARY: OMS-TO023, 026 | F34: MCGS | G34: For Signature
A35: =A34 -> 45664 | B35: =B34+1 -> 29 | C35: ENG'G | E35: Request for ICC: 1. Leo P. Carase, Lot No. 310 | F35: MCGS | G35: For Signature
A36: =A35 -> 45664 | B36: =B35+1 -> 30 | C36: ENG'G | E36: Request for ICC: 1. Graciano P. Dafta Sr., Lot No. 1221 2. Graciano P. Dagta Sr., Lot No. 1217 | F36: MCGS | G36: For Signature
A37: =A36 -> 45664 | B37: =B36+1 -> 31 | C37: OMS | E37: Travel Order: OMS-TO027 | F37: MCGS | G37: For Signature
A38: =A37 -> 45664 | B38: =B37+1 -> 32 | C38: ENG'G | E38: Travel Order: ENG-TO028 | F38: MCGS | G38: For Signature
... A45: =A44 -> 45664 | B45: =B44+1 -> 39 | C45: ENG'G | E45: Request for ICC: 1.Glicerio Colle Dolom m/ to Elene R. Dolom | F45: MCGS | G45: For Signature
A46: ***NOTHING FOLLOWS***
A48: Received, Recorded, Tracked, Disseminated & Filed:
A51: COLEEN M. RASTRULLO | E51: ELLA N. RINGAD | G51: JESSICA V. PEÑAFLOR
A52: Engineering Assistant A | E52: Clerk Processor A | G52: Information Officer C

Sheet 0108
A1: INCOMING DOCUMENTS TO THE OFFICE OF THE IMO MANAGER
A2: 45665
A3: =TEXT(A2,"DDDD") -> Wednesday
A4: NOTE: | B4: Half-day work suspension due to intense rain
A5: NO. | C5: DOCUMENT | F5: TO | G5: REMARKS
C6: DOCUMENT | D6: SECTION | E6: TYPE
A7: =A2 -> 45665 | B7: 1 | C7: To Region: Plantilla of Casual Appointments for the Period of January 1, 2025 to December 31, 2025 Summary and Accomplished Competency Assessment Form CY 2024 | D7: ADMIN | F7: MCGS | G7: For Signature
A8: =A7 -> 45665 | B8: =B7+1 -> 2 | C8: Travel Order: ENG-TO032 | D8: ENG'G | F8: MCGS | G8: For Signature
A9: =A8 -> 45665 | B9: =B8+1 -> 3 | C9: Stronghold Insurance Company Inc. (Closed Envelope) for MCGS | D9: IMO | F9: MCGS
A10: =A9 -> 45665 | B10: =B9+1 -> 4 | C10: JEV & attachments: 1. NIA Region V Naga City COB for Bid Documents Income for 4th Quarter of CY 2024 2. 2nd & Final Billing of Mahaba RIS (MAZOIA) (AL-ISRNIS-007-24INF) | D10: FINANCE | F10: MCGS | G10: For Signature
A11: =A10 -> 45665 | B11: =B10+1 -> 5 | C11: 15% Mobilization LIBJO CIS (AL-EGPIPSOL-012-24INF) Kratos Development Corporation | D11: ENG'G | F11: MCGS | G11: For Signature
A12: =A11 -> 45665 | B12: =B11+1 -> 6 | C12: To COA: Bank Reconciliation Statement of Fund 501LFP & CARP-IC for October 2024 | D12: FINANCE | F12: MCGS | G12: For Signature
A13: =A12 -> 45665 | B13: =B12+1 -> 7 | C13: DTR & Attachments: VE Pitallano (11/1-15, 16-30/2024), (12/1-15/2024) | D13: ADMIN | F13: MCGS | G13: For Signature
A14: =A13 -> 45665 | B14: =B13+1 -> 8 | C14: Travel Order: ENG-TO033, 034 | D14: ENG'G | F14: MCGS | G14: For Signature
A15: =A14 -> 45665 | B15: =B14+1 -> 9 | C15: Gate Pass: 028,029-2025 RIS: 013,014-2025 Transpo Req: 017,018-2025 | D15: OMS | F15: MCGS | G15: For Signature
A16: =A15 -> 45665 | B16: =B15+1 -> 10 | C16: To COA: Summary Report of Actual Maintenance & Other Operating Expenses (MOOE) & Capital Outlay (CO) for Semester ended December 31, 2024 Report of Accountability for Accountable Forms for the month of October 2024 | D16: FINANCE | F16: MCGS | G16: For Signature
A17: =A16 -> 45665 | B17: =B16+1 -> 11 | C17: Check & attachments: Vilma M. Manlangit - Php 133,981.00 | D17: FINANCE | F17: MCGS | G17: For Signature
A18: =A17 -> 45665 | B18: =B17+1 -> 12 | C18: Check & attachments: Vilma M. Manlangit - Php 84,272.54 | D18: FINANCE | F18: MCGS | G18: For Signature
A19: =A18 -> 45665 | B19: =B18+1 -> 13 | C19: Travel Order: OMS-TO029,030 | D19: OMS | F19: MCGS | G19: For Signature
A20: =A19 -> 45665 | B20: =B19+1 -> 14 | C20: Letters to: Hon. Gerry Raphael Z. Jaucian Jr. Hon. Roy Marco re: Pre-Con for Alobo Gapo Inarado CIS EGPIP Fund on 01/10/2025 ,9:00AM at Inarado Brgy Hall, Daraga, albay | D20: OMS | F20: MCGS | G20: For Signature
A21: =A20 -> 45665 | B21: =B20+1 -> 15 | C21: To COA: Quarterly Financial Reports as of December 31, 2024 for Fund 501-LFP (2 separate documents w/ different attachments) | D21: FINANCE | F21: MCGS | G21: For Signature
... A31: =A30 -> 45665 | B31: =B30+1 -> 25 | C31: Gate pass: 032, 033, 031, 030-2025 RIS : 015-2025 Transpo Req. : 020, 026, 021, 022-2025 | D31: OMS | F31: MCGS | G31: For Signature
A32: ***NOTHING FOLLOWS***
A34: Received, Recorded, Tracked, Disseminated & Filed:
A37: COLEEN M. RASTRULLO | D37: ELLA N. RINGAD | G37: JESSICA V. PEÑAFLOR
A38: Engineering Assistant A | D38: Clerk Processor A | G38: Information Officer C

Sheet 0109
A1: INCOMING DOCUMENTS TO THE OFFICE OF THE IMO MANAGER
A2: 45666
A3: =TEXT(A2,"DDDD") -> Thursday
A4: NOTE: | B4: IMO at Regional Office. OIC: BPB
A5: NO. | C5: DOCUMENT | F5: TO | G5: REMARKS
C6: DOCUMENT | D6: SECTION | E6: TYPE
A7: =A2 -> 45666 | B7: 1 | C7: Travel Order: ENG-TO042,043 | D7: ENG'G | F7: BPB | G7: For Signature
A8: =A7 -> 45666 | B8: =B7+1 -> 2 | C8: Travel Order: ENG-TO044 | D8: ENG'G | F8: BPB | G8: For Signature
A9: =A8 -> 45666 | B9: =B8+1 -> 3 | C9: Gate Pass: 034-2025 RIS: 016-2025 Personnel Locator Slip: 01/09/25,8:30, Official, CL Lontac Travel Order: OMS-TO027, ENG-TO045 | D9: OMS | F9: BPB | G9: For Signature
A10: =A9 -> 45666 | B10: =B9+1 -> 4 | C10: Project Completion Report San Francisco RIS CY 2022 | D10: ENG'G | F10: MCGS | G10: For Signature
A11: =A10 -> 45666 | B11: =B10+1 -> 5 | C11: Travel Order: ENG-TO046 Gate Pass: 035-2025 RIS: 017-2025 | F11: BPB | G11: For Signature
A12: =A11 -> 45666 | B12: =B11+1 -> 6 | C12: Post Qualification Evaluation 1. Philworks Const. & Supply & 10 others | D12: BAC | F12: MCGS
A13: =A12 -> 45666 | B13: =B12+1 -> 7 | C13: ACIMO-5-501-2024-465-PS for CNA Php 1,515,000.00 & 3 others | D13: FINANCE | F13: MCGS
A14: =A13 -> 45666 | B14: =B13+1 -> 8 | C14: Travel Order: ENG-TO047, 048 | D14: ENG'G | F14: BPB | G14: For Signature
A15: =A14 -> 45666 | B15: =B14+1 -> 9 | C15: ITINERARY: OMS-TO031 | D15: OMS | F15: BPB | G15: For Signature
A16: =A15 -> 45666 | B16: =B15+1 -> 10 | C16: Project Completion Report Baniaga CIS, Bato, Catanduanes CY 2017 (RREIS-CT-025-17) | D16: ENG'G | F16: MCGS | G16: For Signature
A17: =A16 -> 45666 | B17: =B16+1 -> 11 | C17: Project Completion Report Marambong CIS, Pandan, Catanduanes CY 2012 (RREIS-CT-020-12) | D17: ENG'G | F17: MCGS | G17: For Signature
A18: =A17 -> 45666 | B18: =B17+1 -> 12 | C18: TEVS of: Jevielyn A Dolz - 3,150.00 Marilou A Robledo - 730.00 Cash Advance: Bernardita P. Balingasa - 29,760.00 Excess CA of JBC: NIA F-501LFP- 4,548.00 | D18: FINANCE | F18: MCGS | G18: For Signature
A19: =A18 -> 45666 | B19: =B18+1 -> 13 | C19: Wages (08/01/2024-12/31/2024) JK Paje & 1 AR Madrideo & 2 Wages: (11/16-30/2024) F. Dagumboy | D19: FINANCE | F19: MCGS | G19: For Signature
A20: =A19 -> 45666 | B20: =B19+1 -> 14 | C20: Cheque & Attachments: 2nd & Final Billing BUHI CIS (CAT-REPCIS-001-23) Hi-Tone Construction & Devt Corp. Php 520,040.85 | D20: ENG'G | F20: MCGS | G20: For Signature
A21: =A20 -> 45666 | B21: =B20+1 -> 15 | C21: Personnel Locator Slip: 01/09/2025, 2:00PM, Official, JA Amados | D21: OMS | F21: BPB | G21: For Signature
A22: =A21 -> 45666 | B22: =B21+1 -> 16 | C22: Personnel Locator Slip: 01/09/2025, 1:15PM, Official, A Lopez | D22: OMS | F22: BPB | G22: For Signature
A23: =A22 -> 45666 | B23: =B22+1 -> 17 | C23: Gate Pass: 036,,037,038,039-2025 RIS: 018,019,020-2025 Transpo Req: 024,023,025-2025 | D23: OMS | F23: BPB | G23: For Signature
A24: =A23 -> 45666 | B24: =B23+1 -> 18 | C24: Gate Pass: January 9, 2025 Karl Daniel Asanza, PE of Sunwest Inc. : 50pcs of 5 in Double Flange Steel Pipes & 1 other item thru Howo Boom Truck NFF-8761 | D24: OMS | F24: BPB | G24: For Signature
A25: =A24 -> 45666 | B25: =B24+1 -> 19 | C25: Gate Pass: January 9, 2025 Karl Daniel Asanza, PE of Sunwest Inc. : 30pcs of 5 in Double Flange Steel Pipes & 3 other items thru Howo Boom Truck NFF-8761 | D25: OMS | F25: BPB | G25: For Signature
... A35: =A34 -> 45666 | B35: =B34+1 -> 29 | C35: Travel Order: OMS-TO034,035 | D35: OMS | F35: BPB | G35: For Signature
A36: =A35 -> 45666 | B36: =B35+1 -> 30 | C36: Request to re-schedule conduct of Strategic Planning and Policy Formulation Training/Workshop in Banquerohan CIS from 12/12-13/2024 to 01/21-22/2025 | D36: OMS | F36: MCGS
A37: =A36 -> 45666 | B37: =B36+1 -> 31 | C37: SSS Remittance of K. Almiñana & 1 and A Calpe & 11 for November 2024 | D37: FINANCE | F37: MCGS | G37: For Signature
A38: =A37 -> 45666 | B38: =B37+1 -> 32 | C38: Payment to PLDT Inc for November & December 2024 (Albay) | D38: FINANCE | F38: MCGS | G38: For Signature
A39: =A38 -> 45666 | B39: =B38+1 -> 33 | C39: Fund Transfer Fund 501 CARP to F501-COB for VIG Disallowance for April-November 2024 | D39: FINANCE | F39: MCGS | G39: For Signature
A40: =A39 -> 45666 | B40: =B39+1 -> 34 | C40: Payment to Bureau of Treasury for Remittance of LD for December 2024 | D40: FINANCE | F40: MCGS | G40: For Signature
A41: =A40 -> 45666 | B41: =B40+1 -> 35 | C41: 10% Retention Quinartilan CIS (AL-REPCIS-003-24INF) JCM Construction & Supply Php 233,340.87 | D41: FINANCE | F41: MCGS | G41: For Signature
A42: =A41 -> 45666 | B42: =B41+1 -> 36 | C42: Wages(10/30-31/2024) AMD Balingasa & 2 | D42: FINANCE | F42: MCGS | G42: For Signature
A43: =A42 -> 45666 | B43: =B42+1 -> 37 | C43: To Region: List of Irrigated and Planted (LIPA) Wet Season 2024 CSJ, SQRIS,OSMCIA,MAZOIA,TAPSIA,Bahamas IA,ORISIA,HRISIA | D43: OMS | F43: MCGS | G43: For Signature
A44: =A43 -> 45666 | B44: =B43+1 -> 38 | C44: Hard Copies of NIS & CIS NWRB Statement of Account (SOA)
A45: =A44 -> 45666 | B45: =B44+1 -> 39 | C45: Submission of Status of Funds GAA2024 as of November 2024 LFP, GAA 2023, 2022, 2021 & 2020
A46: =A45 -> 45666 | B46: =B45+1 -> 40 | C46: Water Permit Application for Posting V-ALB-2024-11-008 Philippine Geothermal Production Comp. Inc
A47: =A46 -> 45666 | B47: =B46+1 -> 41 | C47: Re: Follow-up Signed Deeds of Usufruct and Permit-to-Enter for EGPIPSolar Projects
A48: ***NOTHING FOLLOWS***
A50: Received, Recorded, Tracked, Disseminated & Filed:
D52: (absent)
A53: COLEEN M. RASTRULLO | D53: ELLA N. RINGAD | G53: JESSICA V. PEÑAFLOR
A54: Engineering Assistant A | D54: Clerk Processor A | G54: Information Officer C

Sheet 0110
A1: INCOMING DOCUMENTS TO THE OFFICE OF THE IMO MANAGER
A2: 45667
A3: =TEXT(A2,"DDDD") -> Friday
A4: NOTE: | B4: MCGS on Official Business 3:30PM, OIC after: BPB
A5: NO. | C5: DOCUMENT | F5: TO | G5: REMARKS
C6: DOCUMENT | D6: SECTION | E6: TYPE
A7: =A2 -> 45667 | B7: 1 | C7: Travel Order: ENG-TO052 | D7: ENG'G | F7: MCGS | G7: For Signature
A8: =A7 -> 45667 | B8: =B7+1 -> 2 | C8: Travel Order: ENG-TO050 | D8: ENG'G | F8: MCGS | G8: For Signature
A9: =A8 -> 45667 | B9: =B8+1 -> 3 | C9: Personnel Locator Slip: 01/10/2025, 9:00AM, Official, A Lopez | D9: OMS | F9: MCGS | G9: For Signature
A10: =A9 -> 45667 | B10: =B9+1 -> 4 | C10: Travel Order: ENG-TO053 | D10: ENG'G | F10: MCGS | G10: For Signature
A11: =A10 -> 45667 | B11: =B10+1 -> 5 | C11: Gate Pass: 041-2025 | D11: OMS | F11: MCGS | G11: For Signature
A12: =A11 -> 45667 | B12: =B11+1 -> 6 | C12: Gate Pass: 042-2025 | D12: OMS | F12: MCGS | G12: For Signature (Void)
A13: =A12 -> 45667 | B13: =B12+1 -> 7 | C13: Travel Order: OMS-TO036 | D13: OMS | F13: MCGS | G13: For Signature
A14: =A13 -> 45667 | B14: =B13+1 -> 8 | C14: Authority to Render Overtime Services: JAR Sarion & 2 (01/08/2025) JAR Sarion (01/07/2025) | D14: ENG'G | F14: MCGS | G14: For Signature
A15: =A14 -> 45667 | B15: =B14+1 -> 9 | C15: Report of ETPs for October 2024 (501-CARP, 501-LFP) Report of ETPs for November 2024 (501-CARP) | D15: FINANCE | F15: MCGS | G15: For Signature
A16: =A15 -> 45667 | B16: =B15+1 -> 10 | C16: Check w/ Attachments: Glory's Diner - 16,167.36 Meal & Snacks for1 day Modernization NIS Coordination Meeting last 09/27/2024 | D16: FINANCE | F16: MCGS | G16: For Signature
A17: =A16 -> 45667 | B17: =B16+1 -> 11 | C17: Request for ICC: 1. Eunice M. Rellores | D17: ENG'G | F17: MCGS | G17: For Signature | J17: •
A18: =A17 -> 45667 | B18: =B17+1 -> 12 | C18: Approved Sand & Gravel Quarry Permit Applications: 1. Santos Padilla 2. Maggie B. Zafe | D18: ENG'G | F18: MCGS | G18: For Signature
A19: =A18 -> 45667 | B19: =B18+1 -> 13 | C19: Gate Pass : 043-2025 RIS : 021-2025 Daily Trip Ticket : 011,012,013,014,015,016,017,018,019, 020-2025 Travel Order : ENG-TO 054 | D19: ENG'G | F19: MCGS | G19: For signature
A20: =A19 -> 45667 | B20: =B19+1 -> 14 | C20: Equipment Program of Works | D20: OMS | F20: MCGS | G20: For signature
A21: =A20 -> 45667 | B21: =B20+1 -> 15 | C21: Authority to Render Overtime Services: NS REODIQUE & 3 (01/11/2025) TRAVEL ORDER: OMS-TO037 | D21: OMS | F21: MCGS | G21: For signature
A22: =A21 -> 45667 | B22: =B21+1 -> 16 | C22: Check w/ Attachments: Vilma M. Manlangit - 4,000.00 CA of Gratuity Pay of MC Alvarez | D22: FINANCE | F22: MCGS | G22: For signature
A23: =A22 -> 45667 | B23: =B22+1 -> 17 | C23: DCTV Payment for 12/30/2024-01/29/2025 of Albay Ligao Water District 11/06/2024-12/03/2024 GSIS Remittance for November 2024 (COB) GSIS Remittance for November 2024 (CARP to COB) TEV of DZ Manlangit 06/12/2024-06/15/2024 Virac Water District 11/29/2024-12/16/2024 Bureau of Treasure for Fidelity Bond of AV Marquez 2023-2024 | D23: FINANCE | F23: MCGS | G23: For signature
A24: =A23 -> 45667 | B24: =B23+1 -> 18 | C24: 10% Retention Pandan Bongalon CIS (AL-REPCIS-001-24INF) JCM Costruction & Supply, Inc. Php 281,493.98 | D24: FINANCE | F24: MCGS | G24: For signature
A25: =A24 -> 45667 | B25: =B24+1 -> 19 | C25: Gate Pass: 044-2025 | D25: OMS | F25: MCGS | G25: For signature
A26: =A25 -> 45667 | B26: =B25+1 -> 20 | C26: Travel Order : ENG-TO 055 Travel Order : FIN-TO 001 | D26: ENG'G | F26: MCGS | G26: For signature
A27: =A26 -> 45667 | B27: =B26+1 -> 21 | C27: 3rd & Final Progress Billing Gogon CIS (AL-REPCIS-002-24INF) 3RB Construction & Supply | D27: ENG'G | F27: MCGS | G27: For signature
A28: =A27 -> 45667 | B28: =B27+1 -> 22 | C28: Authority To Render Overtime Services: EMS Abila & 8 (12/30/2024) | D28: ADMIN | F28: MCGS | G28: For signature
A29: =A28 -> 45667 | B29: =B28+1 -> 23 | C29: INSPECTION REPORT: Response to Corrective Action Request Regarding Canal Construction and Flooding in Barangay Bariw, Malinao, Albay | D29: ENG'G | F29: MCGS | G29: For signature COMPLAINT
... A40: =A39 -> 45667 | B40: =B39+1 -> 34 | C40: ITINERARY: ENG-TO058 | D40: ENG'G | F40: BPB | G40: For signature
A41: ***NOTHING FOLLOWS***
A43: Received, Recorded, Tracked, Disseminated & Filed:
A46: COLEEN M. RASTRULLO | D46: ELLA N. RINGAD | G46: JESSICA V. PEÑAFLOR
A47: Engineering Assistant A | D47: Clerk Processor A | G47: Information Officer C

Sheet 0113
A1: INCOMING DOCUMENTS TO THE OFFICE OF THE IMO MANAGER
A2: 45670
A3: =TEXT(A2,"DDDD") -> Monday
A4: NOTE:
A5: NO. | C5: DOCUMENT | F5: TO | G5: REMARKS
C6: DOCUMENT | D6: SECTION | E6: TYPE
A7: =A2 -> 45670 | B7: 1 | C7: Personnel Locator Slip: 01/13/2024, 8:20, LTO, CL Lontac 01/13/2024, 8:20, LTO, JL Agripa | D7: OMS | F7: MCGS | G7: For Signature
A8: =A7 -> 45670 | B8: =B7+1 -> 2 | C8: Travel Order: OMS-TO040 | D8: OMS | F8: MCGS | G8: For Signature
A9: =A8 -> 45670 | B9: =B8+1 -> 3 | C9: Personnel Locator Slip: 01/13/2024, 8:35 am, LBP, JP Pante, Personal | D9: OMS | F9: MCGS | G9: For Signature
A10: =A9 -> 45670 | B10: =B9+1 -> 4 | C10: Itinerary: OMS-TO 045, 041, 043, 044,042 | D10: OMS | F10: MCGS | G10: For Signature
A11: =A10 -> 45670 | B11: =B10+1 -> 5 | C11: Gate Pass: 046,047,048,049,050,051-2025 RIS: 024,025,026-2025 Transpo Req: 033,034,030,036,037-2025 Trip Ticket: 025,024,023-2025 | D11: OMS | F11: MCGS | G11: For Signature
A12: =A11 -> 45670 | B12: =B11+1 -> 6 | C12: Personnel Locator Slip: 01/13/2024, 9:00, LTO, JA Amados | D12: OMS | F12: MCGS | G12: For Signature
A13: =A12 -> 45670 | B13: =B12+1 -> 7 | C13: Itinerary: ENG-TO059,060,061,062,063,064,065,066,079 | D13: ENG'G | F13: MCGS | G13: For Signature
A14: =A13 -> 45670 | B14: =B13+1 -> 8 | C14: Itinerary: OMS-TO047 | D14: OMS | F14: MCGS | G14: For Signature
A15: =A14 -> 45670 | B15: =B14+1 -> 9 | C15: To Catanduanes: Approved Copy of 2nd & Final Billing Buhi CIS (CAT-REPCIS-001-23) | D15: CATNES | F15: MCGS | G15: For Signature
A16: =A15 -> 45670 | B16: =B15+1 -> 10 | C16: 2nd & Final Billing Cawayan CIS (AL-REPCIS-003-23) Roca Blanca Construction | D16: ENG'G | F16: MCGS | G16: For Signature | I16: •
A17: =A16 -> 45670 | B17: =B16+1 -> 11 | C17: 15% Mobilization South Quinale RIS (AL-EGPIPSOL-014-24INF) Roca Blanca Construction | D17: ENG'G | F17: MCGS | G17: For Signature
A18: =A17 -> 45670 | B18: =B17+1 -> 12 | C18: Cheque & Attachments: Vilma Manlangit - Php 49,090.80 for CA of wages of A.Arao & 9 (11/16-30/2024) | D18: FINANCE | F18: MCGS | G18: For Signature
A19: =A18 -> 45670 | B19: =B18+1 -> 13 | C19: Cheque & Attachments: Vilma Manlangit - Php 49,090.80 for CA of wages of A.Arao & 9 (12/1-15/2024) | D19: FINANCE | F19: MCGS | G19: For Signature
A20: =A19 -> 45670 | B20: =B19+1 -> 14 | C20: Reimbursement of MCGS for Rizal Day Flower Stand last December 30, 2024 | D20: FINANCE | F20: MCGS | G20: For Signature
A21: =A20 -> 45670 | B21: =B20+1 -> 15 | C21: 1. Adjust understated Tax payment for May 2021 2. Adjust Understatement of Check #1014363 3. Record Funding Check for November 2024 4. Record Funding Check for October 2024 5. Socorro's Lakeside Restaurant & Grill due to overpayment for Check #1124038 dated 1/12/24 6. Fund Transfer of CARP settlement of PHIC Remittances for July-August 2024 7. Record Funding Check for October 2024 8. Fund Transfer of CARP & COB settlement of PHIC Remittances for May-June 2024 9. Fund Transfer of CARP & COB settlement of BIR Remittances for May 2024 10. Fund Transfer of CARP & COB settlement of BIR Remittances for June-July 2024 | D21: FINANCE | F21: MCGS | G21: For Signature
A22: =A21 -> 45670 | B22: =B21+1 -> 16 | C22: To Region: Operations and Maintenance Monthly Report of Albay-Catanduanes IMO for December 2024 | D22: OMS | F22: MCGS | G22: For Signature
A23: =A22 -> 45670 | B23: =B22+1 -> 17 | C23: Itinerary: OMS-TO049 | D23: OMS | F23: MCGS | G23: For Signature
A24: =A23 -> 45670 | B24: =B23+1 -> 18 | C24: Itinerary: OMS-TO048,046 | D24: OMS | F24: MCGS | G24: For Signature
A25: =A24 -> 45670 | B25: =B24+1 -> 19 | C25: Gate Pass: 052-2025 Travel Order: OMS-TO050 | D25: OMS | F25: MCGS | G25: For Signature
A26: =A25 -> 45670 | B26: =B25+1 -> 20 | C26: ITINERARY: ENG-TO080,081 | F26: MCGS | G26: For Signature
A27: =A26 -> 45670 | B27: =B26+1 -> 21 | C27: Letters to: 1. Hon. Wilfredo V. Maronilla 2. Linao Brgy. Captain re Final Pre-Con on January 17, 2025, 9:00AM at SQIA Office | F27: MCGS | G27: For Signature
A28: =A27 -> 45670 | B28: =B27+1 -> 22 | C28: PIC Weekly Accomplishment Report & Project Status South Quinale RIS as of 01/10/2025 South Quinale RIS as of 01/10/2025 | F28: MCGS | G28: For Signature
A29: =A28 -> 45670 | B29: =B28+1 -> 23 | C29: ITINERARY: ENG-TO082 | F29: MCGS | G29: For Signature
A30: =A29 -> 45670 | B30: =B29+1 -> 24 | C30: Personnel Locator Slip: 01/13/2025, 1:30PM, Official, J Amados | F30: MCGS | G30: For Signature
A31: =A30 -> 45670 | B31: =B30+1 -> 25 | C31: Letter to DPWH 1st District: Response to Complaint Regarding Flooding Allegedly Caused by our Irrigation Canals | F31: MCGS | G31: For Signature
A32: =A31 -> 45670 | B32: =B31+1 -> 26 | C32: Audit Compliance Progress Report (ACPR) of Operations Audit in NIA Region 5 | D32: ENG'G | F32: MCGS
A33: =A32 -> 45670 | B33: =B32+1 -> 27 | C33: Authority to Render Overtime Services: MD Orogo (01/12/2025) RP Bonapos (01/10/2025) CL Lontac & 3 (01/11/2025) KAL Almiñana & 1 (01/09/2025) DRP Pagal (01/07-08/2025) DMC Mayor & 3 (01/11-12/2025) | D33: ADMIN | F33: MCGS | G33: For Signature
A34: =A33 -> 45670 | B34: =B33+1 -> 28 | C34: Itinerary: OMS-TO051 | D34: OMS | F34: MCGS | G34: For Signature
A35: =A34 -> 45670 | B35: =B34+1 -> 29 | C35: Posting of Invitation to Apply for Vacant Positions: 1. Sr. IDO - Magarao, Camsur 2. Principal Enginer C - ROV Naga City 3. SWRFT - Magarao, Camsur | F35: MCGS
A36: =A35 -> 45670 | B36: =B35+1 -> 30 | C36: MC No. 133 s. 2024 Juman Resource Promotion and Selection Board (HRMPSB) Resolution No. 1-2024 | F36: MCGS
A37: =A36 -> 45670 | B37: =B36+1 -> 31 | C37: MC No. 01 s. 2025 NIA Board of Directors Performance Evaluation Guidelines | F37: MCGS
A38: =A37 -> 45670 | B38: =B37+1 -> 32 | C38: MC No. 02 s. 2025 NIA Ushering 2025 Activity | F38: MCGS
A39: =A38 -> 45670 | B39: =B38+1 -> 33 | C39: MC No. 132 s. 2024 Amendment to NIA MC No. 126 s.2023 "NIA Drug-Free Workplace Program Policy" | F39: MCGS
A40: =A39 -> 45670 | B40: =B39+1 -> 34 | C40: OM No. 007 s. 2025 Submission of Scheduling of Forced Leave (SFL) and Statement of Assets, Liabilities, and Net Worth (SALN) | F40: MCGS
A41: =A40 -> 45670 | B41: =B40+1 -> 35 | C41: Memorandum: IA Success Stories | F41: MCGS
A42: =A41 -> 45670 | B42: =B41+1 -> 36 | C42: Response to Request for Salinity Test Equipment and Technical Assistance | F42: MCGS
A43: =A42 -> 45670 | B43: =B42+1 -> 37 | C43: Projects without Turn-Over Documents | F43: MCGS
A44: =A43 -> 45670 | B44: =B43+1 -> 38 | C44: Travel Order: ENG-TO083,084 Itinerary: ENG-TO085 | D44: ENG'G | F44: MCGS | G44: For Signature
A45: =A44 -> 45670 | B45: =B44+1 -> 39 | C45: Wages: November 16-30, 2024 JB Dayupay & 10 | D45: ADMIN | F45: MCGS | G45: For Signature
A46: =A45 -> 45670 | B46: =B45+1 -> 40 | C46: Wages: AN Banga & 12 (October 30-31,2024) AJ Delgado (10/16-30/2024) K Almiñana & 2 (10/16-29/2024) M. Azutea & 6 (10/16-29/2024) | D46: ADMIN | F46: MCGS | G46: For Signature
A47: =A46 -> 45670 | B47: =B46+1 -> 41 | C47: Travel Order: AD-TO072 s. 2024 | D47: ADMIN | F47: MCGS | G47: For Signature
A48: =A47 -> 45670 | B48: =B47+1 -> 42 | C48: Itinerary: OMS-TO052 | D48: OMS | F48: MCGS | G48: For Signature
A49: =A48 -> 45670 | B49: =B48+1 -> 43 | C49: Travel Order: OMS-TO053 | D49: OMS | F49: MCGS | G49: For Signature
A50: =A49 -> 45670 | B50: =B49+1 -> 44 | C50: Travel Order: OMS-TO054 | D50: OMS | F50: MCGS | G50: For Signature
A51: =A50 -> 45670 | B51: =B50+1 -> 45 | C51: Gate Pass: 057,056,055,054,053-2025 RIS: 023-2025 Transpo Req: 044,038,039,040,041,042,043-2025 | D51: OMS | F51: MCGS | G51: For Signature
A52: =A51 -> 45670 | B52: =B51+1 -> 46 | C52: Narrative Report: NIA Staff 2024 Year-End Assessment December 9, 2024 | D52: OMS | F52: MCGS | G52: For Signature
A53: =A52 -> 45670 | B53: =B52+1 -> 47 | C53: Office Memo: ADM005 s.2025: Meeting on PS Requirements for CY 2025 | D53: ADMIN | F53: MCGS | G53: For Signature
A54: =A53 -> 45670 | B54: =B53+1 -> 48 | C54: Travel Order: OMS-TO055 | D54: OMS | F54: MCGS | G54: For Signature
A55: =A54 -> 45670 | B55: =B54+1 -> 49 | C55: To Vozcer Construction & Supply: Approved Copy of Plans for Badian-Catburawan CIS AL-REPCIS-019-24INF | D55: ENG'G | F55: MCGS | G55: For Signature
A56: ***NOTHING FOLLOWS***
A58: Received, Recorded, Tracked, Disseminated & Filed:
A61: COLEEN M. RASTRULLO | D61: ELLA N. RINGAD | G61: JESSICA V. PEÑAFLOR
A62: Engineering Assistant A | D62: Clerk Processor A | G62: Information Officer C

Sheet 0114
A1: INCOMING DOCUMENTS TO THE OFFICE OF THE IMO MANAGER
A2: 45671
A3: =TEXT(A2,"DDDD") -> Tuesday
A4: NOTE:
A5: NO. | C5: DOCUMENT | F5: TO | G5: REMARKS
C6: DOCUMENT | D6: SECTION | E6: TYPE
A7: =A2 -> 45671 | B7: 1 | C7: GATE PASS: 058, 059, 060-2025 RIS: 027, 028-2024 | F7: MCGS | G7: For Signature
A8: =A7 -> 45671 | B8: =B7+1 -> 2 | C8: Travel Order: ENG-TO067,068 | F8: MCGS | G8: For Signature
A9: =A8 -> 45671 | B9: =B8+1 -> 3 | C9: ITINERARY OF TRAVEL: OMS-TO056 | F9: MCGS | G9: For Signature
A10: =A9 -> 45671 | B10: =B9+1 -> 4 | C10: ITINERARY OF TRAVEL: ENG-TO069, 070 | F10: MCGS | G10: For Signature
A11: =A10 -> 45671 | B11: =B10+1 -> 5 | C11: Gate Pass: January 11, 2025 Nover Springael, foreman of Sunwest Inc. : solar Module Panels 6 pallets thru Howo Boom Truck NFF-8761 Gate Pass: January 14, 2025 Arnel Bodlong, Foreman of Sunwest Inc. : submersible pump and 1 other thru Toyota Hilux ZNN 460 Nover Springael, foreman of Sunwest Inc. : SOLAR MOUNTING KITS and 2 others thru Howo Boom Truck NFF-8761 | F11: MCGS | G11: For Signature
A12: =A11 -> 45671 | B12: =B11+1 -> 6 | C12: ITINERARY OF TRAVEL: ENG-TO071, 072,073 | F12: MCGS | G12: For Signature
A13: =A12 -> 45671 | B13: =B12+1 -> 7 | C13: To Region: Turnover Documents 1. San Francisco RIS, CY 2022, 20M | F13: MCGS | G13: For Signature
A14: =A13 -> 45671 | B14: =B13+1 -> 8 | C14: To Catanduanes: Project Completion Reports 1. Soboc CIS CY 2018 2. Burgos San Jose CIS CY 2018 3. Alibuag CIS CY 2017 4. Manambrag CIS CY 2019 5. Siay CIP CY 2020 6. Tarba CIS CY 2016 7. Hicming CIP Cy 2020 8. Carangag CIS CY 2015 9. Sta. Isabel CIP CY 2019 10. Tinago CIS CY 2018 11. Sicmil CIS CY 2015 12. Panganiban CIS CY 2015 13. Oco CIS CY 2016 | F14: MCGS | G14: For Signature
A15: =A14 -> 45671 | B15: =B14+1 -> 9 | C15: Itinerary: OMS-TO056 | F15: MCGS | G15: For Signature
A16: =A15 -> 45671 | B16: =B15+1 -> 10 | C16: Follow-up Letter from St. Claire Trading re 10% Retention of Contract No. CO18-AL-002-19: Supply & Delivery of Construction Materials for the Improvement of NIA ACIMO Building | F16: MCGS | I16: •
A17: =A16 -> 45671 | B17: =B16+1 -> 11 | C17: Stronghold Insurance Company Inc. Certification from Insurance Commission for Advance Payment Bond for Libjo CIS (AL-EGPIPSOL-012-24INF) | F17: MCGS
A18: =A17 -> 45671 | B18: =B17+1 -> 12 | C18: Personnel Locator Slip: 01/14/2025, 1:00PM, Official, JA Amados 01/14/2025, 1:00PM, Official, Cl Lontac | F18: MCGS | G18: For Signature
A19: =A18 -> 45671 | B19: =B18+1 -> 13 | C19: To Regional Office: Condonation of Writing Off of Loans of Unpaid ISF Back Account Balance Per RA 10969 SQRIS - Anso Recato & 12 CSJRIS - Armando Llarena & 10 | F19: MCGS | G19: For Signature
A20: =A19 -> 45671 | B20: =B19+1 -> 14 | C20: Stronghold Insurance Company Inc. Statement of Accounts as of January 8, 2025 JCM Const./Hi-Tone Const./ CPR Const./ Kratos Devt./Sisbro Const./ Apex Builders | F20: MCGS
A21: =A20 -> 45671 | B21: =B20+1 -> 15 | C21: Transmittal to COA: JEV for FUND 501-LFP (October 1-15, 2024) JEV for FUND 501-LFP (September 16-30, 2024) | F21: MCGS | G21: For Signature
A22: =A21 -> 45671 | B22: =B21+1 -> 16 | C22: Claire's Resto & Catering Meals/Snacks for NIA Capability Building 10/01/2024 | F22: MCGS | G22: For Signature
A23: =A22 -> 45671 | B23: =B22+1 -> 17 | C23: Personnel Locator Slip: 01/14/2025, 3:15PM, Official, MD Orogo 01/14/2025, 3:15PM, Official, JV Peñaflor 01/14/2025, 3:15PM, Official, EN Ringad | F23: MCGS | G23: For Signature
A24: =A23 -> 45671 | B24: =B23+1 -> 18 | C24: Gate Pass: 061,062,063,064,065,066-2025 Transpo Req: 045,046,047,048,049-2025 | F24: MCGS | G24: For Signature
A25: =A24 -> 45671 | B25: =B24+1 -> 19 | C25: To CamSur IMO: Record of Leaves of Absence (Leave Card) of Albino, Arroyo & Cabiles | F25: MCGS | G25: For Signature
A26: =A25 -> 45671 | B26: =B25+1 -> 20 | C26: To Region: Record of Leaves of Absence (Leave Card) of Chazzie L. Rañola | F26: MCGS | G26: For Signature
A27: =A26 -> 45671 | B27: =B26+1 -> 21 | C27: To Region: Procurement Monitoring Report (PMR) Annexes A & B as of December 31, 2024 | F27: MCGS | G27: For Signature
A28: ***NOTHING FOLLOWS***
A30: Received, Recorded, Tracked, Disseminated & Filed:
A33: COLEEN M. RASTRULLO | D33: ELLA N. RINGAD | G33: JESSICA V. PEÑAFLOR
A34: Engineering Assistant A | D34: Clerk Processor A | G34: Information Officer C

Sheet 0115
A1: INCOMING DOCUMENTS TO THE OFFICE OF THE IMO MANAGER
A2: 45672
A3: =TEXT(A2,"DDDD") -> Wednesday
A4: NOTE:
A5: NO. | C5: DOCUMENTS | F5: TO | G5: REMARKS
C6: DOCUMENT | D6: SECTION | E6: TYPE
A7: =A2 -> 45672 | B7: 1 | C7: TRAVEL ORDER: ADM-TO002 | F7: MCGS | G7: FOR SIGNATURE
A8: =A7 -> 45672 | B8: =B7+1 -> 2 | C8: ITINERARY: ENG-TO078,077,076,075 TRAVEL ORDER: ENG-TO086 | F8: MCGS | G8: FOR SIGNATURE
A9: =A8 -> 45672 | B9: =B8+1 -> 3 | C9: MEMORANDUM OF AGREEMENT NIA & KINA BALANGIBANG CARISAC IA (KBCIA), INC. | F9: MCGS | G9: FOR SIGNATURE
A10: =A9 -> 45672 | B10: =B9+1 -> 4 | C10: ITINERARY: OMS-TO058 | F10: MCGS | G10: FOR SIGNATURE
A11: =A10 -> 45672 | B11: =B10+1 -> 5 | C11: Gate Pass: 067,068-2025 RIS: 029,030,031-2025 | F11: MCGS | G11: FOR SIGNATURE
A12: =A11 -> 45672 | B12: =B11+1 -> 6 | C12: Travel Order: ENG-TO092, OMS-TO059 | F12: MCGS | G12: FOR SIGNATURE
A13: =A12 -> 45672 | B13: =B12+1 -> 7 | C13: Gate Pass Matls: 001-2025 RIS: 032-2025 | F13: MCGS | G13: FOR SIGNATURE
A14: =A13 -> 45672 | B14: =B13+1 -> 8 | C14: Travel Order: OMS-TO060 | F14: MCGS | G14: FOR SIGNATURE
A15: =A14 -> 45672 | B15: =B14+1 -> 9 | C15: To Region: Response to Corrective Action Form No. 202501:001 Complair Re Flooding Allegedly Casued by Our Irrigation Canals in Barangay Bariw, Malinao, Albay | F15: MCGS | G15: FOR SIGNATURE
A16: =A15 -> 45672 | B16: =B15+1 -> 10 | C16: Typo Error on the Date of Letter for Post-Qualification 1. 3RB Const. & 5 others | F16: MCGS | I16: •
A17: =A16 -> 45672 | B17: =B16+1 -> 11 | C17: No verification form attachment in email received Re: Request for Accomplishment of Verification Form 1. 3RB Const & Supply | F17: MCGS
A18: =A17 -> 45672 | B18: =B17+1 -> 12 | C18: Approved Casual Appointment of NIA ACIMO | F18: MCGS
A19: =A18 -> 45672 | B19: =B18+1 -> 13 | C19: Cheque w/ Attachments: Jane Amy Sarion - 3,300.00 TEV November 2024 FICELCO - 6,356.09 Electric Consumption of NIA Cat. 11/23/2024-12/23/2024 | F19: MCGS | G19: FOR SIGNATURE
A20: =A19 -> 45672 | B20: =B19+1 -> 14 | C20: Cheque w/ Attachments: Vilma M. Manlangit - 68,318.03 CA for FAW payrolls of OGSONG & TAPSSIA | F20: MCGS | G20: FOR SIGNATURE
A21: =A20 -> 45672 | B21: =B20+1 -> 15 | C21: Project Completion Report Magsaysay-Begonia CIS (RREIS-CT-021-13) | F21: MCGS
A22: =A21 -> 45672 | B22: =B21+1 -> 16 | C22: Response Report on Follow-Up Rectification Works of Mabato-Siay CIP (CAT-SIP-2021-01-021INF & CAT-SIP-2021-04INF) | F22: MCGS
A23: =A22 -> 45672 | B23: =B22+1 -> 17 | C23: Resubmission of Variation Order of BUGAO & OBO-MOSBOS CIS CAT-RREIS-006-23INF | F23: MCGS
A24: =A23 -> 45672 | B24: =B23+1 -> 18 | C24: Resubmission of Variation Order of AGBAN CIS CAT-RREIS-010-23INF | F24: MCGS
A25: =A24 -> 45672 | B25: =B24+1 -> 19 | C25: Resubmission of Variation Order of PANGANIBAN CIS CAT-REPCIS-008-24INF | F25: MCGS
A26: =A25 -> 45672 | B26: =B25+1 -> 20 | C26: Original Copy of Final Inspection Report of Cabuyoan CIS CAT-RREIS-005-23INF | F26: MCGS
A27: =A26 -> 45672 | B27: =B26+1 -> 21 | C27: Salary Adjustment AV Marquez (10/1-31/2024) Balondo (Apr.- Aug 2024) | F27: MCGS | G27: FOR SIGNATURE
A28: =A27 -> 45672 | B28: =B27+1 -> 22 | C28: Payroll (12/16-31/2024) V. Manlangit | F28: MCGS | G28: FOR SIGNATURE
A29: =A28 -> 45672 | B29: =B28+1 -> 23 | C29: SRI Payroll H. Gorgonia & 48 Reyes & 1 | F29: MCGS | G29: FOR SIGNATURE
A30: =A29 -> 45672 | B30: =B29+1 -> 24 | C30: CAN CY 2024 Gorgonia & 50 | F30: MCGS | G30: FOR SIGNATURE
A31: =A30 -> 45672 | B31: =B30+1 -> 25 | C31: Payroll & attachments Almiñana (10/30-31/2024) Balingasa(10/30-31/2024) Alnas (11/16-30/2024) Llave (11/16-30/2024) Azutea (11/16-30/2024) Almiñana (11/1-15/2024) Warde (11/1-15/2024) | F31: MCGS | G31: FOR SIGNATURE
A32: =A31 -> 45672 | B32: =B31+1 -> 26 | C32: Cheque & attachments: Ligao City Water District - 5,546.88 Water Consumption 12/03/2024-01/06/2025 | F32: MCGS | G32: FOR SIGNATURE
A33: =A32 -> 45672 | B33: =B32+1 -> 27 | C33: Cheque & attachments: Claire's Resto & Catering - 32,300.00 NIA capability Building 10/01/2024 | F33: MCGS | G33: FOR SIGNATURE
A34: =A33 -> 45672 | B34: =B33+1 -> 28 | C34: Cheque & attachments: Kairo's Food & Allied Services Corporation - 46,406.25 1 Day Stakeholders Forum 12/13/2024 | F34: MCGS | G34: FOR SIGNATURE
A35: =A34 -> 45672 | B35: =B34+1 -> 29 | C35: To COA: Copy of emailed scanned copies of PR, NOA, PO and IAR dated January 15, 2025 | F35: MCGS | G35: FOR SIGNATURE
A36: =A35 -> 45672 | B36: =B35+1 -> 30 | C36: Office Memo: ADM006s.2025 : NIA Ushering 2025: Crafting Horizons | F36: MCGS | G36: FOR SIGNATURE
A37: =A36 -> 45672 | B37: =B36+1 -> 31 | C37: Authority to render Overtime Services: RO Clariño & 12 others (01/11-12/2025) DRP Pagal (01/13-14/2025) RP Bonapos & 1 (01/15/2025) | F37: MCGS | G37: FOR SIGNATURE
A38: =A37 -> 45672 | B38: =B37+1 -> 32 | C38: Travel Order: OMS-TO061 ENG-TO087,088 | F38: MCGS | G38: FOR SIGNATURE
... A41: =A40 -> 45672 | B41: =B40+1 -> 35 | C41: Travel Order: ENG-TO 089,090 OMS-TO062 | F41: MCGS | G41: FOR SIGNATURE
A42: =A41 -> 45672 | B42: =B41+1 -> 36 | C42: Submission of CY 2024 Harvest Report and Estimated Cost of Production | F42: MCGS
A43: =A42 -> 45672 | B43: =B42+1 -> 37 | C43: ASA # ACIMO 5-501-2024-209 Capital Outlay 133,817 & 2 others | F43: MCGS
A44: =A43 -> 45672 | B44: =B43+1 -> 38 | C44: Travel Order: ENG-TO093 | F44: MCGS | G44: FOR SIGNATURE
A45: =A44 -> 45672 | B45: =B44+1 -> 39 | C45: Gate Pass Mtls: 002-2025 | F45: MCGS | G45: FOR SIGNATURE
A46: ***NOTHING FOLLOWS***
A48: Received, Recorded, Tracked, Disseminated & Filed:
A51: COLEEN M. RASTRULLO | D51: ELLA N. RINGAD | G51: JESSICA V. PEÑAFLOR
A52: Engineering Assistant A | D52: Clerk Processor A | G52: Information Officer C

Sheet 0116
A1: INCOMING DOCUMENTS TO THE OFFICE OF THE IMO MANAGER
A2: 45673
A3: =TEXT(A2,"DDDD") -> Thursday
A4: NOTE:
A5: NO. | C5: DOCUMENTS | F5: TO | G5: REMARKS
C6: DOCUMENT | D6: SECTION | E6: TYPE
A7: =A2 -> 45673 | B7: 1 | C7: Travel Order : ENG-TO 094, 095 | F7: MCGS | G7: For signature
A8: =A7 -> 45673 | B8: =B7+1 -> 2 | C8: Gate Pass: January 16, 2025-003 Edcel Arao, 50 bags of cement thru Hino Dump Truck SCN-294 travel order: OMS-TO063 | F8: MCGS | G8: For signature
A9: =A8 -> 45673 | B9: =B8+1 -> 3 | C9: Personnel Locator Slip: JP. Papa, 01/16/25, 9:00 am, OFFICIAL | F9: MCGS | G9: For signature
A10: =A9 -> 45673 | B10: =B9+1 -> 4 | C10: Gate Pass: 075-2025 RIS: 035-2025 TRIP TICKET: 026-2025 | F10: MCGS | G10: For signature
A11: =A10 -> 45673 | B11: =B10+1 -> 5 | C11: Authority to Render Overtime Services: Jan. 11, 2025 RG. Aycardo & 1 Jan. 15, 2025 JA. Siguenza | F11: MCGS | G11: For signature
A12: =A11 -> 45673 | B12: =B11+1 -> 6 | C12: Travel Order: ENG-TO096,097 | F12: MCGS | G12: For signature
A13: =A12 -> 45673 | B13: =B12+1 -> 7 | C13: CORRECTIVE ACTION REQUEST FORM: 202501:003 Zhai Carillo-Pineda Purok 1, Sitio Taguntong, Mahaba Ligao City | F13: MCGS
A14: =A13 -> 45673 | B14: =B13+1 -> 8 | C14: Gate Pass Vcls: 076-2025 RIS: 036-2025 | F14: MCGS | G14: For signature
A15: =A14 -> 45673 | B15: =B14+1 -> 9 | C15: Cheque & Attachments : 15% Mobilization Tagoytoy CIS (AL-EGPIPSOL-009-24INF) Dalebo Construction & Gen. Merchandise (2,128,457.41) | F15: MCGS | G15: For signature
A16: =A15 -> 45673 | B16: =B15+1 -> 10 | C16: Notice of Meeting 01/20/2025, 9:00AM, NIA ACIMO Conference Room Finalization of Areas for Inventory of Irrigation System as of December 2024 | F16: MCGS | G16: For signature | I16: •
A17: =A16 -> 45673 | B17: =B16+1 -> 11 | C17: Memorandum of Agreement (MOA) Cabilogan San Juan RIS SPIP | F17: MCGS | G17: For signature
A18: =A17 -> 45673 | B18: =B17+1 -> 12 | C18: CSPC Letter Request to Conduct an Interview & Survey | F18: MCGS
A19: =A18 -> 45673 | B19: =B18+1 -> 13 | C19: To Region: Request for Trailer Truck on Jnauary 18, 2025 | F19: MCGS | G19: For signature
A20: =A19 -> 45673 | B20: =B19+1 -> 14 | C20: Travel Order: OMS-TO064 | F20: MCGS | G20: For signature
A21: =A20 -> 45673 | B21: =B20+1 -> 15 | C21: Letter to LGU Malinao: RESPONSE TO REQUEST FOR ADDITIONAL CANAL CONCRETING PROJECT AND VALIDATION AT BRGY BARIW, MALINAO | F21: MCGS | G21: For signature
A22: =A21 -> 45673 | B22: =B21+1 -> 16 | C22: Payroll (11/18/2024-12/31/2024) Caningag CIS FAW Romel R. Molina & 4 others | F22: MCGS | G22: For signature
A23: =A22 -> 45673 | B23: =B22+1 -> 17 | C23: Ligao Community College Request for permission of ten (10) students for OJT from 01/22/2025-04/03/2025 (400hrs) | F23: MCGS
A24: =A23 -> 45673 | B24: =B23+1 -> 18 | C24: Personnel Locator Slip: 01/16/25, 1:00PM, Official, JLM Agripa | F24: MCGS | G24: For signature
A25: =A24 -> 45673 | B25: =B24+1 -> 19 | C25: To Region: Request for Final Inspection Alobo-Gapo-Inarado CIP (SIP-AL-070-18) Mabalod-Tandarura CIP (SIP-AL-082-18) | F25: MCGS | G25: For signature
A26: =A25 -> 45673 | B26: =B25+1 -> 20 | C26: Personnel Locator Slip: 01/16/2025, 2:00PM, Official, AM Lopez | F26: MCGS | G26: For signature
A27: =A26 -> 45673 | B27: =B26+1 -> 21 | C27: (DRAFT) Revised 2nd APP-CSE CY 2024 for review | F27: MCGS
A28: =A27 -> 45673 | B28: =B27+1 -> 22 | C28: MC No. 145 s. 2022 PGU/LGU Resolution to regulate quarrying activitiers : requirrement prior the implementation of new irrigation projects & repair/rehab/restoration works for existing irrigation system | F28: MCGS
A29: =A28 -> 45673 | B29: =B28+1 -> 23 | C29: Magurang Ubaliw Basud Irrigators Association Resolution No. 2403 s.2024: A Resolution Requesting Me. Mark Cloyd G. So, Acting Division Manager, NIA, Ligao City, Albay for Appropriate Action for the Urgent Repair of Damaged Irrigation Line Canals of Dam 1 and Dam 2 | F29: MCGS
A30: =A29 -> 45673 | B30: =B29+1 -> 24 | C30: To COA: copy of emailed scanned copies of Inspection and Acceptance Report Dated January 16, 2025 | F30: MCGS | G30: For signature
A31: =A30 -> 45673 | B31: =B30+1 -> 25 | C31: Authority to Render Overtime Services: MD Orogo & 3 (01/08/2025) I Cullat (01/12/2025) | F31: MCGS | G31: For signature
A32: =A31 -> 45673 | B32: =B31+1 -> 26 | C32: Travel Order: OMS-TO065 | F32: MCGS | G32: For signature
A33: =A32 -> 45673 | B33: =B32+1 -> 27 | C33: Gate Pass Vcls: 077,078,079,080,081-2025 RIS: 037,038-2025 Transpo Req: 060,056,059,057,054-2025 | F33: MCGS | G33: For signature
A34: =A33 -> 45673 | B34: =B33+1 -> 28 | C34: Travel Order: ENG-TO098,099,100 | F34: MCGS | G34: For signature
A35: =A34 -> 45673 | B35: =B34+1 -> 29 | C35: Application For Leave: RO Clariño (12/23/2024) GS Arabaca (12/26/2024) DA Rebadajo (12/27-28/2024) RO Clariño (01/2-3/2025) AML Dela Cruz (01/02/2025) | F35: MCGS | G35: For signature
A36: ***NOTHING FOLLOWS***
A38: Received, Recorded, Tracked, Disseminated & Filed:
A41: COLEEN M. RASTRULLO | D41: ELLA N. RINGAD | G41: JESSICA V. PEÑAFLOR
A42: Engineering Assistant A | D42: Clerk Processor A | G42: Information Officer C

Sheet 0117
A1: INCOMING DOCUMENTS TO THE OFFICE OF THE IMO MANAGER
A2: 45674
A3: =TEXT(A2,"DDDD") -> Friday
A4: NOTE:
A5: NO. | C5: DOCUMENTS | F5: TO | G5: REMARKS
C6: DOCUMENT | D6: SECTION | E6: TYPE
A7: =A2 -> 45674 | B7: 1 | C7: Follow-up Inspection Report (Fallen Tree along MC of Cabilogan-San Juan RIS) | D7: OMS | F7: MCGS | G7: For Signature
A8: =A7 -> 45674 | B8: =B7+1 -> 2 | C8: Authority to Render Overtime Services: RG Aycardo & 3 (01/08/2025 | D8: ENG'G | F8: MCGS | G8: For Signature
A9: =A8 -> 45674 | B9: =B8+1 -> 3 | C9: Personnel Locator Slip: 01/17/2025, 8:20, Official, A Lopez | D9: ADMIN | F9: MCGS | G9: For Signature
A10: =A9 -> 45674 | B10: =B9+1 -> 4 | C10: GSIS Remittances September 2024 for NIA 501-COB Payroll: AJ Delgado (11/1-15/2024) AN Guarin & 2 (11/16-30/2024) AM Balingasa & 2 (11/1-15/2024) J Bombita & 3 (11/1-15/2024) JP Atanante & 1 (11/1-15/2024) | D10: FINANCE | F10: MCGS | G10: For Signature
A11: =A10 -> 45674 | B11: =B10+1 -> 5 | C11: TEV: JSM Peñafiel (04/02-25/2024) JSM Peñafiel (07/03-26/2024) JSM Peñafiel (08/01-27/2024) JSM Peñafiel (09/03-26/2024) JSM Peñafiel (03/1-18/2024) MDC Salire (August 2024) JSM Peñafiel (10/1-28/2024) CR Reyes (May 2024) | D11: FINANCE | F11: MCGS | G11: For Signature
A12: =A11 -> 45674 | B12: =B11+1 -> 6 | C12: Travel Order: OMS-TO066 | D12: OMS | F12: MCGS | G12: For Signature
A13: =A12 -> 45674 | B13: =B12+1 -> 7 | C13: Gate Pass Vcls: 082,083-2025 Gate Pass Mtls: 004-2025 | F13: MCGS | G13: For Signature
A14: =A13 -> 45674 | B14: =B13+1 -> 8 | C14: Follow-up Letter to Atty. Shella L. Abellano re Civil case No. 1944 Tracking No. 1220017 | F14: MCGS | G14: For Signature
A15: =A14 -> 45674 | B15: =B14+1 -> 9 | C15: Travel Order: OMS-TO067 | F15: MCGS | G15: For Signature
A16: =A15 -> 45674 | B16: =B15+1 -> 10 | C16: Inspection Report: Validation of the Area for Request for Comment on the Revival of Eminent Domain case Entitled "Republic of the Philippines Vs Mariano Garcia" | F16: MCGS | G16: For Signature | I16: •
A17: =A16 -> 45674 | B17: =B16+1 -> 11 | C17: Application for Leave &CTO : 1. Reyes, CR. Et. Al | F17: MCGS | G17: For Signature
A18: =A17 -> 45674 | B18: =B17+1 -> 12 | C18: Cheques & Attachments : Mobilization for Truck 1. Aphard Primecon Construction - PO-EQP-24-12-001 (45,937.50) | F18: MCGS | G18: For Signature
A19: =A18 -> 45674 | B19: =B18+1 -> 13 | C19: Cheque & Attachments : Final Billing Repair/Rehabilitation of Kamanitohan CIS (AL-REPCIS-006-24INF) Php 1,221,599.79 | F19: MCGS | G19: For Signature
A20: =A19 -> 45674 | B20: =B19+1 -> 14 | C20: NWRB-AL-2024-09-050 LGU of Malinao, Albay Ground Water : Brgy. Balading, 4512, Malinao, Albay | F20: MCGS | G20: For Signature
A21: =A20 -> 45674 | B21: =B20+1 -> 15 | C21: Personnel Locator Slip: 1/17/25, LTO Ligao, 10:30 am, JA Amados, OFFICIAL | F21: MCGS | G21: For Signature
A22: =A21 -> 45674 | B22: =B21+1 -> 16 | C22: Gate Pass Mtls: 005-2025 | F22: MCGS | G22: For Signature
A23: =A22 -> 45674 | B23: =B22+1 -> 17 | C23: Authority to Render Overtime Services: NB Oraye (01/11/2025) | F23: MCGS | G23: For Signature
A24: =A23 -> 45674 | B24: =B23+1 -> 18 | C24: DPWH Response re the Flooding Complaint from Brgy. Bariw, Malinao, Albay | F24: MCGS
A25: =A24 -> 45674 | B25: =B24+1 -> 19 | C25: Travel Order: OMS-TO071 | F25: MCGS | G25: For Signature
A26: =A25 -> 45674 | B26: =B25+1 -> 20 | C26: Travel Order: OMS-TO068,069,070 | F26: MCGS | G26: For Signature
A27: =A26 -> 45674 | B27: =B26+1 -> 21 | C27: To Region: IMT-Contract-Nagbarorong Baras IA Inc. | F27: MCGS | G27: For Signature
A28: =A27 -> 45674 | B28: =B27+1 -> 22 | C28: Gate Pass Vcls: 084,085-2025 RIS: 039-2025 Transpo Req: 027,028 | F28: MCGS | G28: For Signature
A29: =A28 -> 45674 | B29: =B28+1 -> 23 | C29: Personnel Locator Slip: 01/17/2025, 3:00PM, Official, DP Vibar | F29: MCGS | G29: For Signature
A30: =A29 -> 45674 | B30: =B29+1 -> 24 | C30: Authority to Render Overtime Services: NS Reodique & 1 (01/18/2025) NS Reodique & 1 (01/19/2025) | F30: MCGS | G30: For Signature
A31: =A30 -> 45674 | B31: =B30+1 -> 25 | C31: Travel Order: ENG-TO 101 | F31: MCGS | G31: For Signature
A32: =A31 -> 45674 | B32: =B31+1 -> 26 | C32: Payroll: ARS Madrideo & 5 (12/19-31/2024) | F32: MCGS | G32: For Signature
A33: =A32 -> 45674 | B33: =B32+1 -> 27 | C33: Payroll: DZ Manlangit & 7 (12/19-31/2024) ACS Guarin & 2 (12/19-31/2024) FB Arcilla & 6 (12/19-31/2024) | F33: MCGS | G33: For Signature
A34: =A33 -> 45674 | B34: =B33+1 -> 28 | C34: Gate Pass Vcls: 086-2025 RIS: 040-2025 Transpo Req: 061-2025 Trip Ticket: 029,030,031,032,033,034,035,036-2025 | F34: MCGS | G34: For Signature
A35: =A34 -> 45674 | B35: =B34+1 -> 29 | C35: FIVC & Final Inspection Report: Tagoytoy CIS (ALCARP-REPCIS-015-24INF) | F35: MCGS
A36: =A35 -> 45674 | B36: =B35+1 -> 30 | C36: Approved Revised CY 2024 POW MNOH MAHABA RIS (OSMCIA) P 50M | F36: MCGS
A37: =A36 -> 45674 | B37: =B36+1 -> 31 | C37: Approved CY 2025 POW MNOH MAHABA RIS (MAZOIA) P 12M | F37: MCGS
A38: =A37 -> 45674 | B38: =B37+1 -> 32 | C38: Payroll ACS Guarin & 2 (01/1-15/2025) | F38: MCGS | G38: For Signature
A39: =A38 -> 45674 | B39: =B38+1 -> 33 | C39: As-Take Plan of Mabini CIS CY 2024 EGPIP-SOLAR | F39: MCGS
A40: =A39 -> 45674 | B40: =B39+1 -> 34 | C40: Approved CY 2025 POW Lower Talisay CIS P 20M | F40: MCGS
A41: =A40 -> 45674 | B41: =B40+1 -> 35 | C41: CY 2024 Variation Orders (Catanduanes) 1. Supang Dataga CIS (CAT-REPCIS-007-24INF(1)) 2. Inagasan CIS (CAT-REPCIS-004-24-INF) 3. Tilod-Sta. Maria CIS (CAT-REPCIS-006-24INF) 4. Baniaga CIS (CAT-REPCIS-005-24INF) 5. Alibuag CIS (CAT-REPCIS-003-24INF) 6. Tinago CIS (CAT-REPCIS-001-24INF) | F41: MCGS
A42: =A41 -> 45674 | B42: =B41+1 -> 36 | C42: Approved CY 2025 POW Upper Libod CIS P 7M | F42: MCGS
A43: =A42 -> 45674 | B43: =B42+1 -> 37 | C43: Project Completion Report 1. Tinago Villa Aurora CIS CY 2019 2. Panganiban CIS CY 2016 | F43: MCGS
A44: =A43 -> 45674 | B44: =B43+1 -> 38 | C44: Project Completion Report 1. Baniaga CIP CY 2014 2. Carangag CIS CY 2017 3. San Roque CIS CY 2023 4. Pacugon CIP CY 2019 5. Ananong SIP Cy 2021 6. Hicming CIP CY 2019 7. Caramoran CIS CY 2019 8. Marambong CIS CY 2016 9. Soboc CIS Cy 2015 | F44: MCGS
A45: =A44 -> 45674 | B45: =B44+1 -> 39 | C45: Cheque & Attachments : Powerzone Petroleum Product Corporation - 47,199.72 Fuel & Oil of Cat'nes for October 2024 | F45: MCGS | G45: For Signature
A46: =A45 -> 45674 | B46: =B45+1 -> 40 | C46: Cheque & Attachments : HDMF - 27,815.18 Remittances of Abila Ela & 39 for December 2024 | F46: MCGS | G46: For Signature
A47: =A46 -> 45674 | B47: =B46+1 -> 41 | C47: Cheque & Attachments : Vilma M. Manlangit - 39,272.64 CA for FAW (December 2024) of C.Baloloy & 8 and G.Teves & 3 | F47: MCGS | G47: For Signature
A48: =A47 -> 45674 | B48: =B47+1 -> 42 | C48: Gate Pass Vcls: 087-2025 trip Ticket: 037-2025 | F48: MCGS | G48: For Signature
A49: =A48 -> 45674 | B49: =B48+1 -> 43 | C49: Travel Order: ENG-TO102 | F49: MCGS | G49: For Signature
A50: =A49 -> 45674 | B50: =B49+1 -> 44 | C50: Authority to Render Overtime Services: NB Oraye (01/18/2025) AE Rull & 4 (01/18/2025 | F50: MCGS | G50: For Signature
A51: =A50 -> 45674 | B51: =B50+1 -> 45 | C51: Authority to Render Overtime Services: VJA Peralta (01/18/2025) | F51: MCGS | G51: For Signature
A52: =A51 -> 45674 | B52: =B51+1 -> 46 | C52: Gate Pass Vcls: 088-2025 Transpo Req: 062-2025 | F52: MCGS | G52: For Signature
A53: =A52 -> 45674 | B53: =B52+1 -> 47 | C53: Office Memo: IMO002 s.2025: REGULAR MEETING EVERY MONDAY FOR EGPIP-SOLAR PROJECTS | F53: MCGS | G53: For Signature
A54: =A53 -> 45674 | B54: =B53+1 -> 48 | C54: Authority to Render Overtime Services: JAR Sarion & 5 (01/18/2025) | F54: MCGS | G54: For Signature
A55: =A54 -> 45674 | B55: =B54+1 -> 49 | C55: Post Qualification Evaluation: Request for Information re Status of On-going and/or completed Contracts of ASC Const & China First Highway Engg Co. | F55: MCGS
A56: =A55 -> 45674 | B56: =B55+1 -> 50 | C56: Post Qualification Evaluation: Verification of Office Performance Track Records - AA Pahati Const | F56: MCGS
A57: =A56 -> 45674 | B57: =B56+1 -> 51 | C57: Submission of CY 2025 Program of Works Under CARP-IC Balasbas CIS (20M) on or before January 31, 2025 | F57: MCGS
A58: =A57 -> 45674 | B58: =B57+1 -> 52 | C58: Submission for Application for Condonation | F58: MCGS
A59: =A58 -> 45674 | B59: =B58+1 -> 53 | C59: Audit Compliance Progress Report (ACPR) of Operations Audit NIA Region V | F59: MCGS
A60: =A59 -> 45674 | B60: =B59+1 -> 54 | C60: Follow-up Rectification works as per Final Inspection of Mabato & Siay CIP CY 2021 dated October 9, 2024 | F60: MCGS
A61: ***NOTHING FOLLOWS***
A63: Received, Recorded, Tracked, Disseminated & Filed:
A66: COLEEN M. RASTRULLO | D66: ELLA N. RINGAD | G66: JESSICA V. PEÑAFLOR
A67: Engineering Assistant A | D67: Clerk Processor A | G67: Information Officer C

Sheet 0120
A1: INCOMING DOCUMENTS TO THE OFFICE OF THE IMO MANAGER
A2: 45677
A3: =TEXT(A2,"DDDD") -> Monday
A4: NOTE: | B4: MCGS & BPB on Official Business until 10:45AM
A5: NO. | C5: DOCUMENTS | F5: TO | G5: REMARKS
C6: DOCUMENT | D6: SECTION | E6: TYPE
A7: =A2 -> 45677 | B7: 1 | C7: Travel Order: OMS-TO074,078 | D7: OMS | F7: LFCP | G7: For Signature
A8: =A7 -> 45677 | B8: =B7+1 -> 2 | C8: Itinerary: OMS-TO075,076 | D8: OMS | F8: LFCP | G8: For Signature
A9: =A8 -> 45677 | B9: =B8+1 -> 3 | C9: Personnel Locator Slip: 01/20/2025, 9:30, Official, AM Lopez | D9: ADMIN | F9: LFCP | G9: For Signature
A10: =A9 -> 45677 | B10: =B9+1 -> 4 | C10: Travel Order: OMS-TO079 | D10: OMS | F10: LFCP | G10: For Signature
A11: =A10 -> 45677 | B11: =B10+1 -> 5 | C11: TEV: FT Melgar( June 2024) SA Pontillas (May 2024) SA Pontillas (November 2024) VJA Peralta (October -December 2024) SA Pontillas (August 2024) SA Pontillas (October 2024) SA Pontillas (September 2024) MB Dacillo ( August 1-29, 2024) MB Dacillo (March 1-26, 2024) MB Dacillo (July 2-30, 2024) MB Dacillo ( February 1-23, 2024) MB Dacillo (January 24-July 19, 2024) | D11: FINANCE | F11: MCGS | G11: For Signature
A12: =A11 -> 45677 | B12: =B11+1 -> 6 | C12: Travel Order: ENG-TO125 | D12: ENG'G | F12: MCGS | G12: Backdated For Signature
A13: =A12 -> 45677 | B13: =B12+1 -> 7 | C13: Travel Order: OMS-TO077 Itinerary: OMS-TO080 | D13: OMS | F13: LFCP | G13: For Signature
A14: =A13 -> 45677 | B14: =B13+1 -> 8 | C14: Travel Order: ENG-TO126 | D14: ENG'G | F14: LFCP | G14: For Signature
A15: =A14 -> 45677 | B15: =B14+1 -> 9 | C15: Gate pass Vcls: 092,093,095,096,097,098,091,090-2025 RIS: 043,042,041-2025 Transpo Req: 069,063,066,064,065-2025 Trip Ticket: 040,039,038-2025 | D15: OMS | F15: LFCP | G15: For Signature
A16: =A15 -> 45677 | B16: =B15+1 -> 10 | C16: Itinerary: ENG-TO127 | D16: ENG'G | F16: LFCP | G16: For Signature | I16: •
A17: =A16 -> 45677 | B17: =B16+1 -> 11 | C17: Travel order: ENG-TO128 | D17: ENG'G | F17: LFCP | G17: For Signature
A18: =A17 -> 45677 | B18: =B17+1 -> 12 | C18: Itinerary: ENG-TO130 | D18: ENG'G | F18: LFCP | G18: For Signature
A19: =A18 -> 45677 | B19: =B18+1 -> 13 | C19: Angat Calambay Bulusan IA Inc Resolution No. 02 s. 2025 "A Resolution Requesting Assistance from the NIA ACIMO by Providing a Backhoe for the Desilting of Lined Canals Affected by Flooding due to Typhoons and Heavy Rainfall" | F19: MCGS
A20: =A19 -> 45677 | B20: =B19+1 -> 14 | C20: Gate Pass VCLS: 100-2025 RIS: 044-2025 Transpo Req: 067-2025 | F20: MCGS | G20: For Signature
A21: =A20 -> 45677 | B21: =B20+1 -> 15 | C21: Itinerary: OMS-TO083, 073 | F21: MCGS | G21: For Signature
A22: =A21 -> 45677 | B22: =B21+1 -> 16 | C22: Itinerary: ENG-TO103,104,105,106,107,108,109,110,111,112,113,114, 115, 116,117,118,119,120,121,122,123,124,129 | F22: LFCP | G22: For Signature
A23: =A22 -> 45677 | B23: =B22+1 -> 17 | C23: Itinerary: ENG-TO131 | F23: MCGS | G23: For Signature
A24: =A23 -> 45677 | B24: =B23+1 -> 18 | C24: Gate Pass Mtls: 006-2025 | F24: MCGS | G24: For Signature
A25: =A24 -> 45677 | B25: =B24+1 -> 19 | C25: Itinerary: OMS-TO081 | F25: MCGS | G25: For Signature
A26: =A25 -> 45677 | B26: =B25+1 -> 20 | C26: To CamSur IMO: Variation Order No. 2 of Cawayan CIS (AL-REPCIS-003-23) | F26: MCGS | G26: For Signature
A27: =A26 -> 45677 | B27: =B26+1 -> 21 | C27: Corrected Documents for Final Billing of Sipi CIS (CAT-RREIS-015-23INF) | F27: MCGS
A28: =A27 -> 45677 | B28: =B27+1 -> 22 | C28: Attachments for the Request of Final Inspection of Tinago CIS (CAT-REPCIS-001-24INF) | F28: MCGS
A29: =A28 -> 45677 | B29: =B28+1 -> 23 | C29: Attachments for the Request of Final Inspection of Baniaga CIS (CAT-REPCIS-005-24INF) | F29: MCGS
A30: =A29 -> 45677 | B30: =B29+1 -> 24 | C30: Project Completion Report: Macutal CIS (CAT-RREIS-001-23INF) | F30: MCGS
A31: =A30 -> 45677 | B31: =B30+1 -> 25 | C31: Project Completion Report: Baniaga CIS (CAT-RREIS-013(2)-23INF) | F31: MCGS
A32: =A31 -> 45677 | B32: =B31+1 -> 26 | C32: Authority to Render Overtime Services: JV Peñaflor (01/18-19/2025) | F32: MCGS | G32: For Signature
A33: =A32 -> 45677 | B33: =B32+1 -> 27 | C33: Response Report on Follow-Up Rectification Works of Mabato-Siay CIP (CAT-SIP-2021-01-021INF & CAT-SIP-2021-04INF) | F33: MCGS | G33: For Signature
A34: =A33 -> 45677 | B34: =B33+1 -> 28 | C34: Cheque w/ Attachments: Villa Salome Resort - Php 25,602.50 1 day training on Alteranative Wetting & Drying Tech. last 11/29/2024 | F34: MCGS | G34: For Signature
A35: =A34 -> 45677 | B35: =B34+1 -> 29 | C35: Cheque w/ Attachments: Angelo V. Marquez - Php 10,140.00 TEV for 12/05-13/2024 | F35: MCGS | G35: For Signature
A36: =A35 -> 45677 | B36: =B35+1 -> 30 | C36: Certification: IA with Good Standing for HIBIGA RIS (WMPA) IA, Inc. Issued January 20, 2025 | F36: MCGS | G36: For Signature
A37: =A36 -> 45677 | B37: =B36+1 -> 31 | C37: Notice of Meeting to Contractors: Kratos Devt. Corp (01/21/2025 at 8-10am) First OMB Const. (01/21/2025 at 10-12pm) Dalebo Const & Gen. Merch (01/21/2025 at 1-3pm) Equator Energy Corp. (01/21/2025 at 3-5pm) | F37: MCGS | G37: For Signature
A38: =A37 -> 45677 | B38: =B37+1 -> 32 | C38: Itinerary: OMS-TO084 | F38: MCGS | G38: For Signature
A39: =A38 -> 45677 | B39: =B38+1 -> 33 | C39: Notice of Meeting to Contractors: Grelips Const. & Devt. (01/23/2025 at 8-10am) Aldacu Const & Supply (01/23/2025 at 10am-12pm) Fixtructure Const & Supply (01/23/2025 at 1-3pm) Apex Builders (01/23/2025 at 3-5pm) | F39: MCGS | G39: For Signature
A40: =A39 -> 45677 | B40: =B39+1 -> 34 | C40: Notice of Meeting to Contractors: Jejan Const & Supply (01/24/2025 at 8-10am) Roca Blanca Const. (01/24/2025 at 10am-12pm) JCM Const & Supply (01/24/2025 at 1-3pm) CPR Const & Supply (01/24/2025 at 3-5pm) | F40: MCGS | G40: For Signature
A41: =A40 -> 45677 | B41: =B40+1 -> 35 | C41: Itinerary: ENG-TO132, 133 | F41: MCGS | G41: For Signature
A42: =A41 -> 45677 | B42: =B41+1 -> 36 | C42: DPWH-NIA Convergence: DPWH'S Flood Management Program for FY 2025 GAA | F42: MCGS | H42: Katubigan Form 1 and FMP Form 1 submission to Systems Management Division-Operations Department every 5th of the ensuing month
A43: =A42 -> 45677 | B43: =B42+1 -> 37 | C43: Managers Conference on FY 2024 Performnce and Implementation Planning, and Management Review of FY 2024 Quality Management System (QMS) to be Held on January 14, 25,and 16 2025 | F43: MCGS
A44: =A43 -> 45677 | B44: =B43+1 -> 38 | C44: Payroll: JL Agripa & 7 for 11/16-30/2024 | F44: MCGS | G44: For Signature
A45: =A44 -> 45677 | B45: =B44+1 -> 39 | C45: Payroll: JP Atanante & 6 for 11/16-30/2024 | F45: MCGS | G45: For Signature
A46: =A45 -> 45677 | B46: =B45+1 -> 40 | C46: Payroll: AN Banga & 13 for 11/16-30/2024 | F46: MCGS | G46: For Signature
A47: =A46 -> 45677 | B47: =B46+1 -> 41 | C47: Office Memo: IMO003 s. 2025: SUBMISSION OF CY 2025 PROGRAM OF WORKS UNDER CARP-IC | F47: MCGS | G47: For Signature
A48: =A47 -> 45677 | B48: =B47+1 -> 42 | C48: Office Memo: ADM007 s.2025 : Reiteration of TEV Rates | F48: MCGS | G48: For Signature
A49: =A48 -> 45677 | B49: =B48+1 -> 43 | C49: Itinerary: OMS-TO087 | F49: MCGS | G49: For Signature
A50: =A49 -> 45677 | B50: =B49+1 -> 44 | C50: To Region: Request for Trailer Truck on January 22, 2025 for Prisa Left Quinale CIS | F50: MCGS | G50: For Signature
A51: =A50 -> 45677 | B51: =B50+1 -> 45 | C51: Itinerary: OMS-TO085 | F51: MCGS | G51: For Signature
A52: =A51 -> 45677 | B52: =B51+1 -> 46 | C52: To Region: Request for ICC 1. Rogelio E. Cabrera Lot No. 13679 2. Rogelio E. Cabrera Lot No. 13681 | F52: MCGS | G52: For Signature
A53: =A52 -> 45677 | B53: =B52+1 -> 47 | C53: Gate Pass Vcls: 101,102,103,104-2025 RIS: 045,046-2025 Transpo Req: 070,068,072,071,074-2025 | F53: MCGS | G53: For Signature
A54: =A53 -> 45677 | B54: =B53+1 -> 48 | C54: Itinerary: OMS-TO088 | F54: MCGS | G54: For Signature
A55: ***NOTHING FOLLOWS***
A57: Received, Recorded, Tracked, Disseminated & Filed:
A60: COLEEN M. RASTRULLO | D60: ELLA N. RINGAD | G60: JESSICA V. PEÑAFLOR
A61: Engineering Assistant A | D61: Clerk Processor A | G61: Information Officer C

Sheet 0121
A1: INCOMING DOCUMENTS TO THE OFFICE OF THE IMO MANAGER
A2: 45678
A3: =TEXT(A2,"DDDD") -> Tuesday
A4: NOTE:
A5: NO. | C5: DOCUMENTS | F5: TO | G5: REMARKS
C6: DOCUMENT | D6: SECTION | E6: TYPE
A7: =A2 -> 45678 | B7: 1 | C7: Gate Pass Vcls: 105-2025 | F7: MCGS | G7: For Signature
A8: =A7 -> 45678 | B8: =B7+1 -> 2 | C8: Travel Order: ENG-TO134 | F8: MCGS | G8: For Signature
A9: =A8 -> 45678 | B9: =B8+1 -> 3 | C9: Itinerary: OMS-TO089 Travel Order:OMS-TO 090,091 | F9: MCGS | G9: For Signature
A10: =A9 -> 45678 | B10: =B9+1 -> 4 | C10: Itinerary: ENG-TO135,136 | F10: MCGS | G10: For Signature
A11: =A10 -> 45678 | B11: =B10+1 -> 5 | C11: Travel Order : OMS-TO 089 & ENG-TO 137 | F11: MCGS | G11: For Signature
A12: =A11 -> 45678 | B12: =B11+1 -> 6 | C12: To COA: Copy of emailed scanned copies of inspection and acceptance report dated January 20, 2025 | F12: MCGS | G12: For Signature
A13: =A12 -> 45678 | B13: =B12+1 -> 7 | C13: Gate Pass Vcls: 106, 107-2025 RIS : 047-2025 Transpo Req. : 075-2025 | F13: MCGS | G13: For Signature
A14: =A13 -> 45678 | B14: =B13+1 -> 8 | C14: Personnel Locator Slip : 1/21/2025, 8:50AM, CLB Lontac, Official Travel Order : ENG-TO 138 | F14: MCGS | G14: For Signature
A15: =A14 -> 45678 | B15: =B14+1 -> 9 | C15: Notice of Meeting : Assesment of Project Accomplishments & Existing Irrigation System in Preparation for Inventory Activity Dated January 21-22, 2025 | F15: MCGS
A16: =A15 -> 45678 | B16: =B15+1 -> 10 | C16: Travel Order: OMS-TO092 | F16: MCGS | G16: For Signature
A17: =A16 -> 45678 | B17: =B16+1 -> 11 | C17: DPWH ROV: Information that their road widening will affect the irrigation canals along Brgy. Centro Occidental, Polangui, Albay | F17: MCGS
A18: =A17 -> 45678 | B18: =B17+1 -> 12 | C18: Travel Order: ENG-TO139 | F18: MCGS | G18: For Signature
A19: =A18 -> 45678 | B19: =B18+1 -> 13 | C19: Itinerary: OMS-TO086 | F19: MCGS | G19: For Signature
A20: =A19 -> 45678 | B20: =B19+1 -> 14 | C20: Gate Pass Mtls: 007,008-2025 | F20: MCGS | G20: For Signature
A21: =A20 -> 45678 | B21: =B20+1 -> 15 | C21: Travel Order: OMS-TO093 | F21: MCGS | G21: For Signature
A22: =A21 -> 45678 | B22: =B21+1 -> 16 | C22: Remittance for NIAEASP loan repayment JB Nacario M Dacillo & 1 JB Nacario & 1 | F22: MCGS | G22: For Signature
A23: =A22 -> 45678 | B23: =B22+1 -> 17 | C23: Remittance to Bureau of Treasury of Liquidated Damages for December 2024 | F23: MCGS | G23: For Signature
A24: =A23 -> 45678 | B24: =B23+1 -> 18 | C24: Remittance for SSS for November & December 2024 | F24: MCGS | G24: For Signature
A25: =A24 -> 45678 | B25: =B24+1 -> 19 | C25: Personnel Locator Slip : 01/21/2025, 1:00PM, Personal, EN Ringad | F25: MCGS | G25: For Signature
A26: =A25 -> 45678 | B26: =B25+1 -> 20 | C26: To COA: Copy of emailed scanned copies of inspection and acceptance report dated January 20, 2025 | F26: MCGS | G26: For Signature
A27: =A26 -> 45678 | B27: =B26+1 -> 21 | C27: DPWH 3rd DEO: Information that their construction of farm to market road will affect the irrigation canals along Brgy. Napo-Sitio Matamis Ponso, Polangui,Albay
A28: =A27 -> 45678 | B28: =B27+1 -> 22 | C28: DPWH 3rd DEO: Meeting Invitation on January 22, 2025, 1:00PM at Brgy. Tuburan, Ligao City re: Prop. FY 2025, Construction of Left & Right Side Ogsong River Flood Control Structure, Package II
A29: =A28 -> 45678 | B29: =B28+1 -> 23 | C29: Fund Transfer to F501-LFP for the ETPs-BIR Remittances of F501-COB for September, October & November 2024 | F29: MCGS | G29: For Signature
A30: =A29 -> 45678 | B30: =B29+1 -> 24 | C30: Fund Transfer to F501-LFP for the ETPs-BIR Remittances of F501-CARP for September, October & November 2024 | F30: MCGS | G30: For Signature
A31: =A30 -> 45678 | B31: =B30+1 -> 25 | C31: Remittance for PAG-IBIG of V Manlangit & 1 for December 2024 | F31: MCGS | G31: For Signature
A32: =A31 -> 45678 | B32: =B31+1 -> 26 | C32: Remittance for PAG-IBIG of MB Dacillo & 8 for December 2024 | F32: MCGS | G32: For Signature
A33: =A32 -> 45678 | B33: =B32+1 -> 27 | C33: Remittance for medicare contri of V Manlangit & 1 for December 2024 | F33: MCGS | G33: For Signature
A34: =A33 -> 45678 | B34: =B33+1 -> 28 | C34: Itinerary: OMS-TO094 | F34: MCGS | G34: For Signature
A35: =A34 -> 45678 | B35: =B34+1 -> 29 | C35: Remittance to HDMF for December 2024 Aycardo, Raymond & 8 others
A36: =A35 -> 45678 | B36: =B35+1 -> 30 | C36: Remittance to HDMF for NOvember 2024 Almiñana Kimberly & 2
A37: =A36 -> 45678 | B37: =B36+1 -> 31 | C37: Remittance for medicare contri of Abila Ela & 39 for December 2024 PHIC Contri of MB Dacillo & 8 foe Sept-Dec 2024
A38: =A37 -> 45678 | B38: =B37+1 -> 32 | C38: Personnel Locator Slip : 01/21/2025, 2:20PM, Personal, RS. NACARIO | F38: MCGS | G38: FOR SIGNATURE
A39: =A38 -> 45678 | B39: =B38+1 -> 33 | C39: TRAVEL ORDER: ADM-TO003 & ENG-TO140 | F39: MCGS | G39: FOR SIGNATURE
A40: =A39 -> 45678 | B40: =B39+1 -> 34 | C40: FOLLOW-UP REPORT FOR DEFORMED TRASH RACK 01/20/2025 | F40: MCGS | G40: FOR SIGNATURE
A41: =A40 -> 45678 | B41: =B40+1 -> 35 | C41: To Region: Request for 3 units Water Puump for Cabilogan San Juan RIS rubber dam | F41: MCGS | G41: FOR SIGNATURE
A42: =A41 -> 45678 | B42: =B41+1 -> 36 | C42: Attested Appointment of NIA ACIMO Casual Employees | F42: MCGS
A43: =A42 -> 45678 | B43: =B42+1 -> 37 | C43: Travel Order: OMS-TO095,096,097 | F43: MCGS | G43: FOR SIGNATURE
A44: =A43 -> 45678 | B44: =B43+1 -> 38 | C44: Gate Pass Vcls: 108,109,110-2025 RIS: 049,048-2025 Transpo Req: 077,078,079,080,081,082-2025 | F44: MCGS | G44: FOR SIGNATURE
A45: =A44 -> 45678 | B45: =B44+1 -> 39 | C45: Payroll: RA Paraiso (07/1-15/2024) RA Paraiso (09/1-15/2024) | F45: MCGS | G45: FOR SIGNATURE
A46: =A45 -> 45678 | B46: =B45+1 -> 40 | C46: Payroll: JB Dayupay & 11 (12/1-18/2024) | F46: MCGS | G46: FOR SIGNATURE
A47: =A46 -> 45678 | B47: =B46+1 -> 41 | C47: Payroll: MC Azutea & 7 (12/19-31/2024) | F47: MCGS | G47: FOR SIGNATURE
A48: =A47 -> 45678 | B48: =B47+1 -> 42 | C48: Gate Pass Vcls: 111-2025 | F48: MCGS | G48: FOR SIGNATURE
A49: =A48 -> 45678 | B49: =B48+1 -> 43 | C49: Travel Order: OMS-TO072 | F49: MCGS | G49: FOR SIGNATURE
A50: ***NOTHING FOLLOWS***
A52: Received, Recorded, Tracked, Disseminated & Filed:
A55: COLEEN M. RASTRULLO | D55: ELLA N. RINGAD | G55: JESSICA V. PEÑAFLOR
A56: Engineering Assistant A | D56: Clerk Processor A | G56: Information Officer C

Sheet 0122
A1: INCOMING DOCUMENTS TO THE OFFICE OF THE IMO MANAGER
A2: 45679
A3: =TEXT(A2,"DDDD") -> Wednesday
A4: NOTE:
A5: NO. | C5: DOCUMENTS | F5: TO | G5: REMARKS
C6: DOCUMENT | D6: SECTION | E6: TYPE
A7: =A2 -> 45679 | B7: 1 | C7: Gate PassVcls : 112, 113-2025 RIS : 050, 051-2025 Daily Trip Ticket : 041-2025 | F7: MCGS | G7: For signature
A8: =A7 -> 45679 | B8: =B7+1 -> 2 | C8: Travel Order: OMS-TO098,099, 100 | F8: MCGS | G8: For signature
A9: =A8 -> 45679 | B9: =B8+1 -> 3 | C9: Certification for Funding Assistance Repair/rehab NIA/CIS Damaged by TS Kristine | F9: MCGS | G9: For signature
A10: =A9 -> 45679 | B10: =B9+1 -> 4 | C10: Project Completion Report Magsaysay-Begonia CIS RREIS-CT-021-13 | F10: MCGS | G10: For signature
A11: =A10 -> 45679 | B11: =B10+1 -> 5 | C11: Project Completion Report Panganiban CIS NDRRMF CY 2017 | F11: MCGS | G11: For signature
A12: =A11 -> 45679 | B12: =B11+1 -> 6 | C12: Travel Order: ENG-TO141 | F12: MCGS | G12: For signature
A13: =A12 -> 45679 | B13: =B12+1 -> 7 | C13: Request for ICC 1. Erwin M. Logronio Lot No. 1167-A | F13: MCGS | G13: For signature
A14: =A13 -> 45679 | B14: =B13+1 -> 8 | C14: Project Completion Report Oco CIS NDRRMF CY 2017 | F14: MCGS | G14: For signature
A15: =A14 -> 45679 | B15: =B14+1 -> 9 | C15: Gate Pass Matls: 009-2025 | F15: MCGS | G15: For signature
A16: =A15 -> 45679 | B16: =B15+1 -> 10 | C16: Authority to Render Overtime Services VE Pitallano & 7 (01/06-10/2025) VE Pitallano & 7 (01/11-12/2025) VE Pitallano & 9 (01/13-17/2025) VE Pitallano & 9 (01/18-19/2025) VE Pitallano & 8 (01/20-24/2025) VE Pitallano & 8 (01/25-26/2025) VE Pitallano & 8 (01/27-31/2025) | F16: MCGS | G16: For signature
A17: =A16 -> 45679 | B17: =B16+1 -> 11 | C17: RIS: 052-2025 | F17: MCGS | G17: For signature
A18: =A17 -> 45679 | B18: =B17+1 -> 12 | C18: Report for Deformed Trash Rack Repair 01/22/2025 | F18: MCGS | G18: For signature
A19: =A18 -> 45679 | B19: =B18+1 -> 13 | C19: Personnel Locator Slip : 1/22/2025, 1:30 pm, JA Amados, Official | F19: MCGS | G19: For signature
... A29: =A28 -> 45679 | B29: =B28+1 -> 23 | C29: Paid: (For Signature) Kairos Food & Allied Services Corporation 1-day stakeholders Forum last 12/13/2024 | F29: MCGS | G29: For signature
A30: =A29 -> 45679 | B30: =B29+1 -> 24 | C30: Envia Consultancy Letter of Invitation for 40hr Basic Pollution Control Officer (PCO) training on January 27-28 and January 30-31, 2025 at Armada Hotel Manila | F30: MCGS
A31: =A30 -> 45679 | B31: =B30+1 -> 25 | C31: Memorandum NIA Region V Review & Planning on January 29-31, 2025 at Natures Spring Resort, Irosin, Sorsogon | F31: MCGS
A32: =A31 -> 45679 | B32: =B31+1 -> 26 | C32: Post Qualification Evaluation St. Bernardine Const. & 10 others | F32: MCGS
A33: =A32 -> 45679 | B33: =B32+1 -> 27 | C33: OM No. 008 s. 2025 Reconstitution of the Regional Committee on Anti-Red Tape (RCART), Its TWG and Secretariat | F33: MCGS
A34: =A33 -> 45679 | B34: =B33+1 -> 28 | C34: Memorandum Agency's Updated Punlic Investment Program (PIP) 2023-2028 and Three-year Rolling Infrastructure Program (TRIP) 2026-2028: Priority Programs and Projects for FY 2026 Budget Preparations | F34: MCGS
A35: =A34 -> 45679 | B35: =B34+1 -> 29 | C35: Drone-Lidar Training on January 13-17, 2025 at NIA ROV | F35: MCGS
A36: =A35 -> 45679 | B36: =B35+1 -> 30 | C36: Memorandum Gathering of Data for 2025 Farm Support Services Program List of Farmer Beneficiaries to attend the program & parcellary map before 01/31/2025 Results of soil test analysis on or before February 15, 2025 | F36: MCGS
A37: =A36 -> 45679 | B37: =B36+1 -> 31 | C37: Memorandum Submission of CY 2025 Operations Plan for NIS and Detailed Program Areas for CIS on or before January 24, 2025 | F37: MCGS
A38: =A37 -> 45679 | B38: =B37+1 -> 32 | C38: Memorandum Agri-Entrepreneurship Seminar-Workshop January 24, 2025 at NIA ROV | F38: MCGS
A39: =A38 -> 45679 | B39: =B38+1 -> 33 | C39: Advance Copy: Posting of Invitation to Apply for Vacant Position 1. Admin Officer V | F39: MCGS
A40: =A39 -> 45679 | B40: =B39+1 -> 34 | C40: Ligban Farmers IA, Inc. Request for immediate action and response regarding issues caused by heavy rainfall to system | F40: MCGS
A41: =A40 -> 45679 | B41: =B40+1 -> 35 | C41: Del Rosario-carisac-San Agustin IA, Inc. Resolution No. 1 s. 2025 "A resolution requesting the NIA for immediate restoration of slope protection dike at downstream of San Agustin CIS, Libon, Albay" | F41: MCGS
... A44: =A43 -> 45679 | B44: =B43+1 -> 38 | C44: Notice of Meeting February 12-13, 2025 at NIA ROV Training on Kobo Toolbox for Monitoring of Farm Support Services Program | F44: MCGS
A45: =A44 -> 45679 | B45: =B44+1 -> 39 | C45: To COA: JEV for F501-CARP for January 2024 JEV for F501-LFP for March 2024 JEV for F501-LFP for April | F45: MCGS | G45: For signature
A46: =A45 -> 45679 | B46: =B45+1 -> 40 | C46: DTR & Attachments: SH Agripa Jr (12/16-31/2024) NS Reodique (12/16-31/2024), (12/1-15/2024),(11/1-15/2024) | F46: MCGS | G46: For signature
A47: =A46 -> 45679 | B47: =B46+1 -> 41 | C47: Gate Pass Vcls: 114,115,117-2025 RIS: 056,054-2025 Transpo Req: 083,084,085,086-2025 | F47: MCGS | G47: For signature
A48: ***NOTHING FOLLOWS***
A50: Received, Recorded, Tracked, Disseminated & Filed:
A53: COLEEN M. RASTRULLO | D53: ELLA N. RINGAD | G53: JESSICA V. PEÑAFLOR
A54: Engineering Assistant A | D54: Clerk Processor A | G54: Information Officer C

Sheet 0123
A1: INCOMING DOCUMENTS TO THE OFFICE OF THE IMO MANAGER
A2: 45680
A3: =TEXT(A2,"DDDD") -> Thursday
A4: NOTE:
A5: NO. | C5: DOCUMENTS | F5: TO | G5: REMARKS
C6: DOCUMENT | D6: SECTION | E6: TYPE
A7: =A2 -> 45680 | B7: 1 | C7: Travel Order: OMS-TO101 | F7: MCGS | G7: For Signature
A8: =A7 -> 45680 | B8: =B7+1 -> 2 | C8: Minutes of the Meeting Technical Discussion: Cabilogan-San Juan RIS FSDE under Modernization of NIS 01/16/2025 | F8: MCGS | G8: For Signature
A9: =A8 -> 45680 | B9: =B8+1 -> 3 | C9: Inspection Report for Affected Irrigation Canal to be affected by DPWH road widening | F9: MCGS | G9: For Signature
A10: =A9 -> 45680 | B10: =B9+1 -> 4 | C10: Gate Pass Mtls: 011-2025 | F10: MCGS | G10: For Signature
A11: =A10 -> 45680 | B11: =B10+1 -> 5 | C11: Cheques & Attachments: HDMF - 12,600.00 (November 2024 Contri) HDMF -12,400.00 (December 2024 Contri) HDMF - 3,900.00 (Pag-Ibig Contri MB Dacillo & 8 for Dec. 2024) HDMF - 1,800.00 (November 2024, Aycardo & 8) HDMF - 1,800.00 (December 2024, Aycardo & 8) HDMF - 800.00 (December 2024 V Manlangit & 1) HDMF - 600.00 (November 2024, Almiñana & 2) HDMF - 600.00 (December 2024, Almiñana & 2) | F11: MCGS | G11: For Signature
A12: =A11 -> 45680 | B12: =B11+1 -> 6 | C12: Cheques & Attachments: Social Security System -9,660.00 (December 2024, Almiñana & 1) Social Security System -11,320.00 (November 2024) Social Security System -10,830.00 (November-December 2024) Social Security System -10,230.00 (November-December 2024) | F12: MCGS | G12: For Signature
A13: =A12 -> 45680 | B13: =B12+1 -> 7 | C13: Cheques & Attachments: NIA F-501 LFP - 703,940.18 NIA F-501 LFP - 493,225.47 | F13: MCGS | G13: For Signature
A14: =A13 -> 45680 | B14: =B13+1 -> 8 | C14: Travel Order: OMS-TO 102 Gate Pass Matls : 012-2025 Gate Pass Vcls: 119-2025 | F14: MCGS | G14: For Signature
A15: =A14 -> 45680 | B15: =B14+1 -> 9 | C15: Cheque & Attachments: NIAEASP - 15,000.00 (loan repayment Dacillo & 1) | F15: MCGS | G15: For Signature
A16: =A15 -> 45680 | B16: =B15+1 -> 10 | C16: Cheque & Attachments: Bureau of Treasury - 4,488.42 (December 2024 LD) | F16: MCGS | G16: For Signature
A17: =A16 -> 45680 | B17: =B16+1 -> 11 | C17: Cheque & Attachments: Elizabeth J. Jacob - 1,995.00 (TEV July 2-31, 2024) | F17: MCGS | G17: For Signature
A18: =A17 -> 45680 | B18: =B17+1 -> 12 | C18: Cheque & Attachments: Sisbro Construction & Supply - 418,860.33 10% Retention Cabilogan San Juan RIS (AL-RESNIS-009-24INF) | F18: MCGS | G18: For Signature
A19: =A18 -> 45680 | B19: =B18+1 -> 13 | C19: Travel Order: OMS-TO103 | F19: MCGS | G19: For Signature
A20: =A19 -> 45680 | B20: =B19+1 -> 14 | C20: South Quinale IA, Inc. Resolution No. 1 s.2025 "A Resolution respectfully requesting Engr. Mark Cloyd G. So, Acting Division Manager ACIMO of NIA, Tuburan, Ligao City to favorably cause the immediate Construction/Concreting of upstream washed-out dike at South Quinale RIS Rubber Dam at Busac, Oas, Albay" | F20: MCGS
A21: =A20 -> 45680 | B21: =B20+1 -> 15 | C21: Submission of the CY 2025 Revised Construction Schedule and Prior Years' Catch-up Plan for Operations-Monitored Projects *** Form A & B on or before February 15, 2025 | F21: MCGS
A22: =A21 -> 45680 | B22: =B21+1 -> 16 | C22: Letters to: DPWH 1st DEO DPWH 2nd DEO DPWH 3rd DEO re: NIA-DPWH Convergence: DPWH Flood Management Program for FY 2025 GAA | F22: MCGS | G22: For Signature
A23: =A22 -> 45680 | B23: =B22+1 -> 17 | C23: To Catanduanes: Approved Project Completion Reports 1. Carangag CIS (CY 2017) 2. Ananong CIP (CY 2021) 3. Caramoran CIS (CY 2019) 4. Marambong CIS (CY 2016) 5. Soboc CIS (CY 2020) 6. Baniaga CIS (CY 2014) 7. Panganiban CIS (CY 2016) 8. Pangcayanan CIS (CY 2022) | F23: MCGS | G23: For Signature
A24: =A23 -> 45680 | B24: =B23+1 -> 18 | C24: IPCRs of Planning & Design Unit | F24: MCGS | G24: For Signature
A25: =A24 -> 45680 | B25: =B24+1 -> 19 | C25: Payroll: December 19-31, 2024 1. Jacob 2. Mariñas 3. Aycardo 4. Balingasa | F25: MCGS | G25: For Signature
A26: =A25 -> 45680 | B26: =B25+1 -> 20 | C26: Payroll: December 1-18, 2024 1. Aydalla 2. Jacob 3. Atanante | F26: MCGS | G26: For Signature
A27: =A26 -> 45680 | B27: =B26+1 -> 21 | C27: FAW Appointments & Attachments: (11/18/24-12/31/24) Dulcisino Tesorero & 11 | F27: MCGS | G27: For Signature
A28: =A27 -> 45680 | B28: =B27+1 -> 22 | C28: FAW Appointments & Attachments: (11/8/24-12/31/24) Teves, Gregorio & 3 | F28: MCGS | G28: For Signature
A29: =A28 -> 45680 | B29: =B28+1 -> 23 | C29: FAW Appointments & Attachments: (11/8/24-12/31/24) Ereemanual Turado & 7 | F29: MCGS | G29: For Signature
A30: =A29 -> 45680 | B30: =B29+1 -> 24 | C30: Letter to: LBP Ligao Re: Open payroll account for Ulysses B. Guadalupe | F30: MCGS | G30: For Signature
A31: =A30 -> 45680 | B31: =B30+1 -> 25 | C31: *Paid- For signature only* Virac Water District Water consumption of NIA-Cat for 09/30/2024-10/31/2024 | F31: MCGS | G31: For Signature
A32: =A31 -> 45680 | B32: =B31+1 -> 26 | C32: Payroll: J Amados & 1 (11/16-30/2024) | F32: MCGS | G32: For Signature
A33: =A32 -> 45680 | B33: =B32+1 -> 27 | C33: Transmittal to Camsur IMO: MOA of CY 2023 Projects 1. Agban CIS 2. Alibuag CIS 3. Baniaga CIS 4. Bugao CIS 5. Buhi CIS 6. Cabuyoan CIS 7. Gigmoto CIS 8. Nagbarorong CIS 9. Tilod CIS | F33: MCGS | G33: For Signature
A34: =A33 -> 45680 | B34: =B33+1 -> 28 | C34: Travel Order: ENG-TO142 | F34: MCGS | G34: For Signature
A35: =A34 -> 45680 | B35: =B34+1 -> 29 | C35: Prisa Left Quinale IA, Inc. Resolution No. 1 s.2025 "A Resolution the NIA CIMO to restore the dam upstream slope protection dike which was damaged by Typhoon Kristine to irrigate the 825 heactares of farmlots of Prisa Left Quinale CIS" | F35: MCGS
A36: =A35 -> 45680 | B36: =B35+1 -> 30 | C36: Gate Pass Mtls: 013, 014-2025 | F36: MCGS | G36: For Signature
A37: =A36 -> 45680 | B37: =B36+1 -> 31 | C37: To Region: Project Completion Reports 1. Oco CIS CY 2017 2. Bagong Abre CIS CY 2020 | F37: MCGS | G37: For Signature
A38: =A37 -> 45680 | B38: =B37+1 -> 32 | C38: To: Apex Builders Approved Copy of Plans for Alobo-Gapo-Inarado SPIP AL-EGPIPSOL-007-24INF | F38: MCGS | G38: For Signature
A39: =A38 -> 45680 | B39: =B38+1 -> 33 | C39: Travel Order: ENG-TO143 | F39: MCGS | G39: For Signature
A40: =A39 -> 45680 | B40: =B39+1 -> 34 | C40: Notice of Meeting Invitation 01/27/2025, 1:00-2:00PM at ACIMO Manager's Office First OMB Const & Devt Corp | F40: MCGS | G40: For Signature
A41: =A40 -> 45680 | B41: =B40+1 -> 35 | C41: Project Completion Report Baniaga CIS CAT-RREIS-013(2)-23INF | F41: MCGS | G41: For Signature
A42: =A41 -> 45680 | B42: =B41+1 -> 36 | C42: Project Completion Report Macutal CIS CAT-RREIS-001-23INF | F42: MCGS | G42: For Signature
A43: =A42 -> 45680 | B43: =B42+1 -> 37 | C43: Travel Order: ENG-TO144, 145 | F43: MCGS | G43: For Signature
A44: =A43 -> 45680 | B44: =B43+1 -> 38 | C44: Travel Order: ADM-TO004, OMS-TO104 | F44: MCGS | G44: For Signature
A45: =A44 -> 45680 | B45: =B44+1 -> 39 | C45: Authority to Render Overtime Services: VJA Peralta (01/20-22/2025) VJA Peralta (01/08/2025) | F45: MCGS | G45: For Signature
A46: =A45 -> 45680 | B46: =B45+1 -> 40 | C46: To Region: Project Completion Reports 1. Panganiban CIS (CY 2017) 2. Magsaysay Begonia CIS (CY 2013) | F46: MCGS | G46: For Signature
A47: =A46 -> 45680 | B47: =B46+1 -> 41 | C47: Letter To: OIC of Land Records Section, DENR-LMS Legazpi re: Request for Approved Subdivision plans w/ Technical Descriptions of Lot No. 5555 & 3 others | F47: MCGS | G47: For Signature
A48: =A47 -> 45680 | B48: =B47+1 -> 42 | C48: Letter to: Hon. Fernando T. Cabredo (3D Congressman) re: Request for possible funding Assistance on Typhoon Kristine Damages under NIA-DPWH Convergence Program | F48: MCGS | G48: For Signature
A49: =A48 -> 45680 | B49: =B48+1 -> 43 | C49: Posting of Invitation to Apply for Vacant Positions -Engineer A (CARP-IC) | F49: MCGS
A50: =A49 -> 45680 | B50: =B49+1 -> 44 | C50: Coordination Meeting/Inspection of Regional Office -Construction Management Section Personnel at Irrigation Management Offices (IMO's) **ACIMO scheduled February 27-28, 2025 | F50: MCGS
A51: =A50 -> 45680 | B51: =B50+1 -> 45 | C51: Cheque & Attachments: Vilma M. Manlangit - 81,818.00 FAW Payroll for November 2024 (DR Almarez & 9) | F51: MCGS | G51: For Signature
A52: =A51 -> 45680 | B52: =B51+1 -> 46 | C52: Cheque & Attachments: Kinale Balangibang Carissac Irrigators Assn Inc- 150,000.00 Livelihood Program | F52: MCGS | G52: For Signature
A53: =A52 -> 45680 | B53: =B52+1 -> 47 | C53: Cheque & Attachments: Claire's Resto & Catering - 35,482.50 1-day NIA ACIMO Strategic Review & Planning last 12/06/24 | F53: MCGS | G53: For Signature
A54: =A53 -> 45680 | B54: =B53+1 -> 48 | C54: Cheque & Attachments: Claire's Resto & Catering - 24,272.50 1-day Training on AWDT for NIA Assisted IA last 11/25/24 | F54: MCGS | G54: For Signature
A55: =A54 -> 45680 | B55: =B54+1 -> 49 | C55: Cheque & Attachments: Claire's Resto & Catering - 24,937.50 1-day Training on AWDT for NIA Assisted IA last 11/26/24 | F55: MCGS | G55: For Signature
A56: =A55 -> 45680 | B56: =B55+1 -> 50 | C56: Cheque & Attachments: Jennimel R. Dayupay - 4,570.00 TEV October-December 2024 | F56: MCGS | G56: For Signature
A57: =A56 -> 45680 | B57: =B56+1 -> 51 | C57: Cheque & Attachments: Jomer L. Beo - 1,350.00 TEV December 5-7, 2024 | F57: MCGS | G57: For Signature
A58: =A57 -> 45680 | B58: =B57+1 -> 52 | C58: Cheque & Attachments: Angelo V. Marquez - 5,688.00 TEV August 2024 | F58: MCGS | G58: For Signature
A59: =A58 -> 45680 | B59: =B58+1 -> 53 | C59: Cheque & Attachments: Jomel M. Torio -1,350.00 TEV December 5-7, 2024 | F59: MCGS | G59: For Signature
A60: =A59 -> 45680 | B60: =B59+1 -> 54 | C60: Cheque & Attachments: Angelo V. Marquez - 1,620.00 Reimbursement for Cake as token last May 17, 2024 for NIA-IA Dialogue | F60: MCGS | G60: For Signature
A61: =A60 -> 45680 | B61: =B60+1 -> 55 | C61: Cheque & Attachments: Joshua A. Lumbao - 1,154.00 TEV December 5-7, 2024 | F61: MCGS | G61: For Signature
A62: =A61 -> 45680 | B62: =B61+1 -> 56 | C62: Cheque & Attachments: Jun Shane M. Peñafiel - 1,485.00 TEV December 2-13, 2024 | F62: MCGS | G62: For Signature
... A70: =A69 -> 45680 | B70: =B69+1 -> 64 | C70: To Region: Request for Georesistivity Equipment | F70: MCGS | G70: For Signature
A71: ***NOTHING FOLLOWS***
A73: Received, Recorded, Tracked, Disseminated & Filed:
A76: COLEEN M. RASTRULLO | D76: ELLA N. RINGAD | G76: JESSICA V. PEÑAFLOR
A77: Engineering Assistant A | D77: Clerk Processor A | G77: Information Officer C

Sheet 0124
A1: INCOMING DOCUMENTS TO THE OFFICE OF THE IMO MANAGER
A2: 45681
A3: =TEXT(A2,"DDDD") -> Friday
A4: NOTE:
A5: NO. | C5: DOCUMENTS | F5: TO | G5: REMARKS
C6: DOCUMENT | D6: SECTION | E6: TYPE
A7: =A2 -> 45681 | B7: 1 | C7: Travel Order: ENG-TO146 | F7: MCGS | G7: For signature
A8: =A7 -> 45681 | B8: =B7+1 -> 2 | C8: Authority to Render Overtime Services: EN Ringad & 1 (01/23/2025) EN Ringad & 1 (01/25-26/2025) | F8: MCGS | G8: For signature
A9: =A8 -> 45681 | B9: =B8+1 -> 3 | C9: Travel Order: OMS-TO106 | F9: MCGS | G9: For signature
A10: =A9 -> 45681 | B10: =B9+1 -> 4 | C10: Project Completion Report Cawayan CIS POW#2 CY 2019 | F10: MCGS | G10: For signature
A11: =A10 -> 45681 | B11: =B10+1 -> 5 | C11: Project Completion Report Cawayan CIS POW#1 CY 2019 | F11: MCGS | G11: For signature
A12: =A11 -> 45681 | B12: =B11+1 -> 6 | C12: Travel Order: OMS-TO107 | F12: MCGS | G12: For signature
A13: =A12 -> 45681 | B13: =B12+1 -> 7 | C13: Personnel Locator Slip 01/24/2025, 9:00AM, Official, RJ Mariñas | F13: MCGS | G13: For signature
A14: =A13 -> 45681 | B14: =B13+1 -> 8 | C14: Authority to Render Overtime Services: JB Completo & 11 (01/25/2025) | F14: MCGS | G14: For signature
A15: =A14 -> 45681 | B15: =B14+1 -> 9 | C15: Gate Pass Vcls: 128,126-2025 RIS: 063,062-2025 Transpo Req: 096,095-2025 Trip Ticket: 042,043,044,045,046,047,048,049,050,051-2025 | F15: MCGS | G15: For signature
A16: =A15 -> 45681 | B16: =B15+1 -> 10 | C16: Memorandum of Agreement BUPC and NIA re Interns for CY 2025 | F16: MCGS | G16: For signature
A17: =A16 -> 45681 | B17: =B16+1 -> 11 | C17: Application for Leave: RS Nacario - 12/11-12/2024 DA San Buenaventura - 12/27/2024 AB Calpe - 12/26/2024 EMS Abila - 12/26/2024 AB Calpe - 01/10/2025 | F17: MCGS | G17: For signature
A18: =A17 -> 45681 | B18: =B17+1 -> 12 | C18: SALN of Permanent, Casual & Job Order Employees 2024 | F18: MCGS | G18: For signature
A19: =A18 -> 45681 | B19: =B18+1 -> 13 | C19: Travel Order: OMS-TO108,109,110 | F19: MCGS | G19: For signature
A20: =A19 -> 45681 | B20: =B19+1 -> 14 | C20: Authority to Render Overtime Services: AS Raposa & 5 (01/25/2025 AS Raposa & 1 (01/26/2025 | F20: MCGS | G20: For signature
A21: =A20 -> 45681 | B21: =B20+1 -> 15 | C21: Memorandum: United Architects of the Philppines 50th National Convention | F21: MCGS
A22: =A21 -> 45681 | B22: =B21+1 -> 16 | C22: Memorandum: DPWH-NIA Convergence: DPWH's Flood Management Program for CY 2025 GAA | F22: MCGS
A23: =A22 -> 45681 | B23: =B22+1 -> 17 | C23: Email: CY 2025 Public-Private Partnership (PPP) Center Capacity Building Activities | F23: MCGS
A24: =A23 -> 45681 | B24: =B23+1 -> 18 | C24: Sangguniang Bayan ng Libon Invitation as resource person for Committee of the Whole Hearing re damaged irrigation facilities in Libon ***01/28/2025, 10:30AM at Sangguniag Bayan ng Libon Session Hall, 3rd Floor, Libon Municipal Govt Bldg | F24: MCGS
A25: =A24 -> 45681 | B25: =B24+1 -> 19 | C25: Personnel Locator Slip 01/24/2025, 9:35AM, Personal, LO Dedase | F25: MCGS | G25: For signature
A26: =A25 -> 45681 | B26: =B25+1 -> 20 | C26: Gate Pass Mtls: 015-2025 | F26: MCGS | G26: For signature
A27: =A26 -> 45681 | B27: =B26+1 -> 21 | C27: To COA: Copy of emailed scanned copies of Inspection and Acceptance report dated January 24, 2025 1. IAR of AFS-24-11-007 & 4 others | F27: MCGS | G27: For signature
A28: =A27 -> 45681 | B28: =B27+1 -> 22 | C28: Gate Pass: 130-2025 Trip Ticket: 053-2025 | F28: MCGS | G28: For signature
A29: =A28 -> 45681 | B29: =B28+1 -> 23 | C29: Response to letter dated January 7, 2025 re affected irrigation canals along Brgy. Centro Occidental, Polangui, Albay | F29: MCGS | G29: For signature
A30: =A29 -> 45681 | B30: =B29+1 -> 24 | C30: Gate Pass Vcls: 129-2025 RIS : 064-2025 Transpo Req. : 097, 054, 055-2025 | F30: MCGS | G30: For signature
A31: =A30 -> 45681 | B31: =B30+1 -> 25 | C31: Personnel Locator Slip : 1/24/25 , 2:40 pm, Official, FS Gestiada | F31: MCGS | G31: For signature
A32: =A31 -> 45681 | B32: =B31+1 -> 26 | C32: Travel Order : ADM-TO 006 & 007 | F32: MCGS | G32: For signature
A33: =A32 -> 45681 | B33: =B32+1 -> 27 | C33: Travel Order : OMS-TO 111 | F33: MCGS | G33: For signature
A34: =A33 -> 45681 | B34: =B33+1 -> 28 | C34: Application for Leave: Rebadajo, DA (05/28-29/25) | F34: MCGS | G34: For signature
A35: =A34 -> 45681 | B35: =B34+1 -> 29 | C35: Travel Order : ENG-TO 169 | F35: MCGS | G35: For signature
A36: =A35 -> 45681 | B36: =B35+1 -> 30 | C36: Travel Order : OMS-TO 112 Authority to Render Overtime Services 1. VJA Peralta (1/18 & 25/2025) | F36: MCGS | G36: For signature
... A40: =A39 -> 45681 | B40: =B39+1 -> 34 | C40: Authority to Render Overtime Services: LMB Olivera & 1 (01/25/2025) | F40: MCGS | G40: For signature
A41: ***NOTHING FOLLOWS***
A43: Received, Recorded, Tracked, Disseminated & Filed:
A46: COLEEN M. RASTRULLO | D46: ELLA N. RINGAD | G46: JESSICA V. PEÑAFLOR
A47: Engineering Assistant A | D47: Engineering Assistant A | G47: Information Officer C

Sheet 0127
A1: INCOMING DOCUMENTS TO THE OFFICE OF THE IMO MANAGER
A2: 45684
A3: =TEXT(A2,"DDDD") -> Monday
A4: NOTE:
A5: NO. | C5: DOCUMENTS | F5: TO | G5: REMARKS
C6: PARTICULAR | D6: SECTION | E6: TYPE
A7: =A2 -> 45684 | B7: 1 | C7: TRAVEL ORDER: OMS-TO113 & OMS-TO116 | D7: OMS | F7: MCGS | G7: For signature
A8: =A7 -> 45684 | B8: =B7+1 -> 2 | C8: Personnel Locator Slip 01/27/2025, 9:00AM, Official, JA AMADOS | D8: OMS | F8: MCGS | G8: For signature
A9: =A8 -> 45684 | B9: =B8+1 -> 3 | C9: TRAVEL ORDER: ENG-TO171 ITINERARY OF TRAVEL: OMS-TO117 & 118 | F9: MCGS | G9: For signature
A10: =A9 -> 45684 | B10: =B9+1 -> 4 | C10: GATEPASS: 133-2025 | F10: MCGS | G10: For signature
A11: =A10 -> 45684 | B11: =B10+1 -> 5 | C11: ITINERARY OF TRAVEL: OMS-TO 115 & OMS-TO 114 | F11: MCGS | G11: For signature
A12: =A11 -> 45684 | B12: =B11+1 -> 6 | C12: ITINERARY TRAVEL : ENG-TO172 & OMS-TO 119 | F12: MCGS | G12: For signature
A13: =A12 -> 45684 | B13: =B12+1 -> 7 | C13: TRANSMITTAL OF JEV FUND 501 CORPORATE OPERATING BUDGET WITH SUPPORTING DOCUMENTS FOR SEPT. 2024 | F13: MCGS | G13: For signature
A14: =A13 -> 45684 | B14: =B13+1 -> 8 | C14: ITINERARY OF TRAVEL: ENG-TO 173 | F14: MCGS | G14: For signature
A15: =A14 -> 45684 | B15: =B14+1 -> 9 | C15: ITINERARY OF TRAVEL: OMS-TO120 & OMS-TO121 | F15: MCGS | G15: For signature
A16: =A15 -> 45684 | B16: =B15+1 -> 10 | C16: INSPECTION REPORT; DAMAGED PULLEY OF THE SLUICE GATE LIFTING MECHANISM ENGINE (CABILOGAN-SAN JUAN NIS) | F16: MCGS | G16: For signature
A17: =A16 -> 45684 | B17: =B16+1 -> 11 | C17: GATEPASS: 134, 132, 136, 135, 137-2025 RIS: 066, 070, 069, 068, 071 -2025 TRIP TICKET: 052-2025 | F17: MCGS | G17: For signature
A18: =A17 -> 45684 | B18: =B17+1 -> 12 | C18: ITINERARY OF TRAVEL: ENG-TO174, ENG-TO175 & ENG-TO176 | F18: MCGS | G18: For signature
A19: =A18 -> 45684 | B19: =B18+1 -> 13 | C19: Authority to Render Overtime Services: EN Ringad & 1 (01/29/2025) | F19: MCGS | G19: For signature
A20: =A19 -> 45684 | B20: =B19+1 -> 14 | C20: TRAVEL ORDER: ENG-TO177 | F20: MCGS | G20: For signature
... A25: =A24 -> 45684 | B25: =B24+1 -> 19 | C25: Authority to Render Overtime Services: JSM. PENAFFIEL (01/29/2025) | F25: MCGS | G25: For signature
A26: =A25 -> 45684 | B26: =B25+1 -> 20 | C26: Corrective Action Request Form: 202501-05 Raoj Nomirb: Updating of present situation of Kamanitohan ARC Irrigators association (KARCIA) in Manito, Albay | F26: MCGS
A27: =A26 -> 45684 | B27: =B26+1 -> 21 | C27: MC Nos. 136-137 s.2024 | F27: MCGS
A28: =A27 -> 45684 | B28: =B27+1 -> 22 | C28: Travel Order: EDM-TO007 | F28: MCGS | G28: For signature
A29: =A28 -> 45684 | B29: =B28+1 -> 23 | C29: To: BUPC Approval of Intern Applicants Mary Grace Z Viñas & 3 others | F29: MCGS | G29: For signature
A30: =A29 -> 45684 | B30: =B29+1 -> 24 | C30: From Region: (Request to fill needed details of submitted) MOA of CARP-IC 2024 1. Estancia-Labnig CIS 2. Bayandong CIS 3. Tagoytoy CIS | F30: MCGS
A31: =A30 -> 45684 | B31: =B30+1 -> 25 | C31: Itinerary: ENG-TO178 | F31: MCGS | G31: For signature
A32: =A31 -> 45684 | B32: =B31+1 -> 26 | C32: From Region: Submission of List of Participants for Kobo Tool Box Training on February 12-13, 2025 at NIA Regional Office V | F32: MCGS
A33: =A32 -> 45684 | B33: =B32+1 -> 27 | C33: For Approval: CSJ Gate Keeper Rubber Dam Duty Schedule for February 2025 | F33: MCGS | G33: For signature
A34: =A33 -> 45684 | B34: =B33+1 -> 28 | C34: Office Memo: IMO004 s.2025: Mandatory Approval for Distribution of Official Documents | F34: MCGS | G34: For signature
A35: =A34 -> 45684 | B35: =B34+1 -> 29 | C35: Itinerary: OMS-TO122,123,124,126,127,128,129 | F35: MCGS | G35: For signature
A36: =A35 -> 45684 | B36: =B35+1 -> 30 | C36: Travel Order: OMS-TO130,131 Authority to Render Overtime Services: JA Amados & 1 (01/29/2025) | F36: MCGS | G36: For signature
A37: =A36 -> 45684 | B37: =B36+1 -> 31 | C37: DTR & attachments: (11/1-15/2024) Reyes (11/16-30/2024) Paje, Nacario JB, Balingasa, Balonso, Marquez | F37: MCGS | G37: For signature
A38: =A37 -> 45684 | B38: =B37+1 -> 32 | C38: DTR & attachments: (10/30-31/2024) Bombita (12/19-31/2024) Almiñana, Aydalla, Dayupay, Banga | F38: MCGS | G38: For signature
A39: =A38 -> 45684 | B39: =B38+1 -> 33 | C39: Travel Order: ENG-TO179,180 | F39: MCGS | G39: For signature
A40: =A39 -> 45684 | B40: =B39+1 -> 34 | C40: Authority to Render Overtime Services: JV Peñaflor & 2 (01/25/2025) | F40: MCGS | G40: For signature
A41: =A40 -> 45684 | B41: =B40+1 -> 35 | C41: Gate Pass Vcls: 147,139,141,142,143,144,145,146-2025 RIS: 073-2025 Transpo Req: 104,105,111,112,113,115-2025 | F41: MCGS | G41: For signature
A42: =A41 -> 45684 | B42: =B41+1 -> 36 | C42: Travel Order: OMS-TO132 | F42: MCGS | G42: For signature
A43: ***NOTHING FOLLOWS***
A45: Received, Recorded, Tracked, Disseminated & Filed:
A48: COLEEN M. RASTRULLO | D48: ELLA N. RINGAD | G48: JESSICA V. PEÑAFLOR
A49: Engineering Assistant A | D49: Engineering Assistant A | G49: Information Officer C

Sheet 0128
A1: INCOMING DOCUMENTS TO THE OFFICE OF THE IMO MANAGER
A2: 45685
A3: =TEXT(A2,"DDDD") -> Tuesday
A4: NOTE: | B4: MCGS & BPB on official business. OIC: LFCP
A5: NO. | C5: DOCUMENTS | F5: TO | G5: REMARKS
C6: PARTICULAR | D6: SECTION | E6: TYPE
A7: =A2 -> 45685 | B7: 1 | C7: RIS: 074,075-2025 | F7: LFCP | G7: For Signature
A8: =A7 -> 45685 | B8: =B7+1 -> 2 | C8: To Region: Submission of Revised Accomplishment Report and Supporting Documents for Operations Inventory | F8: LFCP | G8: For Signature
A9: =A8 -> 45685 | B9: =B8+1 -> 3 | C9: To Region: (Transmittal w/ signed attachments) Variation Order No. 2 of Cawayan CIS (AL-REPCIS-003-23) | F9: LFCP | G9: For Signature
A10: =A9 -> 45685 | B10: =B9+1 -> 4 | C10: To Region: (Transmittal w/ signed attachments) Turnover Documents Ilaod CIP (RREIS CY 2018) | F10: LFCP | G10: For Signature
A11: =A10 -> 45685 | B11: =B10+1 -> 5 | C11: Travel Order: OMS-TO133 Itinerary: OMS-TO134,135,136 | F11: LFCP | G11: For Signature
A12: =A11 -> 45685 | B12: =B11+1 -> 6 | C12: To: CPR Construction & Supply Inc. Lacking Documentary Requirements for Contract Payment 1. Caningag CIS (CAT-RREIS-003-23INF) 2. Cabuyoan CIS (CAT-RREIS-005-23INF) | F12: MCGS | G12: For Signature
A13: =A12 -> 45685 | B13: =B12+1 -> 7 | C13: Travel Order: OMS-TO137 | F13: LFCP | G13: For Signature
A14: =A13 -> 45685 | B14: =B13+1 -> 8 | C14: To: QJ Construction Lacking Documentary Requirements for Contract Payment 1. Tilod Sta Maria CIS (CAT-REPCIS-006-24INF) 2. Tinago CIS (CAT-REPCIS-001-24INF) | F14: MCGS | G14: For Signature
A15: =A14 -> 45685 | B15: =B14+1 -> 9 | C15: To: JMREO Construction Services Lacking Documentary Requirements for Contract Payment 1. Gigmoto CIS (CAT-REPCIS-002-24INF) 2. Panganiban CIS (CAT-REPCIS-008-24INF) 3. Baniaga CIS (CAT-REPCIS-005-24INF) 4. Inagasan CIS (CAT-REPCIS-0045(1)-24INF) 5. Alibuag CIS (CAT-REPCIS-003-24INF) | F15: MCGS | G15: For Signature
A16: =A15 -> 45685 | B16: =B15+1 -> 10 | C16: Personnel Locator Slip: 01/28/2025,9:45AM, Official, VMM | F16: LFCP | G16: For Signature
A17: =A16 -> 45685 | B17: =B16+1 -> 11 | C17: Travel Order: OMS-TO138 | F17: LFCP | G17: For Signature
A18: =A17 -> 45685 | B18: =B17+1 -> 12 | C18: Travel Order: ENG-TO181 | F18: LFCP | G18: For Signature
A19: =A18 -> 45685 | B19: =B18+1 -> 13 | C19: From Catanduanes: Resubmission of Attachments for Variation Order No. 1 Repair/Resto of OBO-MOSBOS CIS (CAT-RREIS-006-23INF) | D19: ENG'G | G19: To JAS for evaluation
A20: =A19 -> 45685 | B20: =B19+1 -> 14 | C20: From Catanduanes: Attachments for 1st Progress Billing Panganiban CIS (CAT-REPCIS-008-24INF) | D20: ENG'G | G20: To JAS for evaluation
A21: =A20 -> 45685 | B21: =B20+1 -> 15 | C21: From Catanduanes: Resubmission of Attachments for 2nd & Final Billing Repair/Rehab of SIPI CIS (CAT-RREIS-011-23INF) | D21: ENG'G | G21: To JAS for evaluation
A22: =A21 -> 45685 | B22: =B21+1 -> 16 | C22: From Catanduanes: Project Completion Report Caramoran CIS (CAT-SIP-2020-01SVP) | D22: ENG'G | G22: To JAS for evaluation
A23: =A22 -> 45685 | B23: =B22+1 -> 17 | C23: DTR & Attachments: 10/16-31/2024 - LFC Pante, JB Peñaflor 10/1-15/2024 - DA San Buenaventura, AP Francia | F23: MCGS | G23: For Signature
A24: =A23 -> 45685 | B24: =B23+1 -> 18 | C24: Authority to Render Overtime Services: JR Dayupay (01/29/2025) FB Juarez Jr. (01/29/2025) | F24: MCGS | G24: For Signature
A25: =A24 -> 45685 | B25: =B24+1 -> 19 | C25: To Region: MOA of CY 2023 Projects 1. Agban CIS 2. Alibuag CIS 3. Baniaga CIS 4. Bugao CIS 5. Buhi CIS 6. Cabuyoan CIS 7. Gigmoto CIS 8. Nagbarorong CIS 9. Tilod CIS | F25: MCGS | G25: For Signature
A26: =A25 -> 45685 | B26: =B25+1 -> 20 | C26: Personnel Locator Slip: 01/28/2025,1:00PM, Official,JDC Berzuela | F26: LFCP | G26: For Signature
A27: =A26 -> 45685 | B27: =B26+1 -> 21 | C27: Office Memo: IMO005 s. 2025: Clarification On OM No. IMO004 S. 2025: Mandatory Approval For Distribution Of Official Documents | F27: MCGS | G27: For Signature
A28: =A27 -> 45685 | B28: =B27+1 -> 22 | C28: Gate Pass Vcls: 148,149,150-2025 RIS: 076,077,078-2025 Transpo Req: 110-2025 | F28: LFCP | G28: For Signature
A29: =A28 -> 45685 | B29: =B28+1 -> 23 | C29: To Region: Signed Documents (Transmittal Only) Sworn Statement of Assets, Liabilities and Net Worth (SALN) for CY 2024 (Additional, with JO personnel) | F29: LFCP | G29: For Signature
A30: =A29 -> 45685 | B30: =B29+1 -> 24 | C30: Authority to Render Overtime Services: Marc David O. Orogo and 1 (01/25/2025) Diana Rose P. Pagal (01/25/2025) Marc David O. Orogo and 3 (01/29/2025) | F30: MCGS | G30: For Signature
A31: =A30 -> 45685 | B31: =B30+1 -> 25 | C31: Authority to Render Overtime Services: PJ Rebeta & 17 (01/29/2025) Travel Order: ENG-TO | F31: LFCP | G31: For Signature
A32: =A31 -> 45685 | B32: =B31+1 -> 26 | C32: To Region: MOA of Kinale Balangibang Carisac IA (KBCIA Inc) for Solar Powered Pump Irrigation Project (SPIP) | F32: MCGS | G32: For Signature
A33: =A32 -> 45685 | B33: =B32+1 -> 27 | C33: Gate Pass Vcls: 151,152-2025 RIS: 079,080-2025 Transpo Req: 116-2025 | F33: LFCP | G33: For Signature
A34: =A33 -> 45685 | B34: =B33+1 -> 28 | C34: Travel Order: OMS-TO139 | F34: LFCP | G34: For Signature
... A47: =A46 -> 45685 | B47: =B46+1 -> 41 | C47: Payroll & Attachments: (12/19-31/2024) AMD Balingasa & 7 R. Aycardo & 5 R Mariñas & 1 PG Credo JL Agripa & 8 GN Jacob AR Madrideo & 3 F Dagumboy Paje & Pante | F47: MCGS | G47: For Signature
A48: ***NOTHING FOLLOWS***
A50: Received, Recorded, Tracked, Disseminated & Filed:
A53: COLEEN M. RASTRULLO | D53: ELLA N. RINGAD | G53: JESSICA V. PEÑAFLOR
A54: Engineering Assistant A | D54: Engineering Assistant A | G54: Information Officer C

Sheet 0130
A1: INCOMING DOCUMENTS TO THE OFFICE OF THE IMO MANAGER
A2: 45687
A3: =TEXT(A2,"DDDD") -> Thursday
A4: NOTE: | B4: All signatories on Official Business except VMM
A5: NO. | C5: DOCUMENTS | F5: TO | G5: REMARKS
C6: PARTICULAR | D6: SECTION | E6: TYPE
A7: =A2 -> 45687 | B7: 1 | C7: Travel Order: OMS-TO142 ENG-TO184 | F7: VMM | G7: For Signature
A8: =A7 -> 45687 | B8: =B7+1 -> 2 | C8: Gate Pass Vcls: 157,158,159,160,161,162-2025 RIS: 081-2025 Transpo Req: 118,119,120,121,123-2025 | F8: VMM | G8: For Signature
A9: =A8 -> 45687 | B9: =B8+1 -> 3 | C9: Personnel Locator Slip: 01/30/2025, 9:30AM, Personal, RA Paraiso | F9: VMM | G9: For Signature
A10: =A9 -> 45687 | B10: =B9+1 -> 4 | C10: Authority to Render Overtime Services: AS Portuguez (01/29/2025) JA Siguenza & 1 (01/27/2025) C Petilla (01/29/2025) JA Siguenza & 1 (01/29/2025) H Maticinos (01/29/2025) EMS Abila & 5 (01/29/2025) | G10: For Signature
A11: =A10 -> 45687 | B11: =B10+1 -> 5 | C11: Travel Order: OMS-TO143 | F11: VMM | G11: For Signature
A12: =A11 -> 45687 | B12: =B11+1 -> 6 | C12: From Catanduanes: Request for IT Equipment | F12: MCGS
A13: =A12 -> 45687 | B13: =B12+1 -> 7 | C13: From: Sisbro Construction & Supply Letter Request for Final Inspection of San Agustin CIS AL-EGPIPSOL-003-24INF | D13: ENG'G | F13: LFCP
A14: =A13 -> 45687 | B14: =B13+1 -> 8 | C14: From Catanduanes: Variation Order of Manambrag CIS CY 2023 Variance CAT-VAR-001-23INF | D14: ENG'G | G14: To JAS for evaluation
A15: =A14 -> 45687 | B15: =B14+1 -> 9 | C15: Gate Pass Vcls: 165-2025 RIS: 082-2025 | F15: VMM | G15: For Signature
A16: =A15 -> 45687 | B16: =B15+1 -> 10 | C16: Personnel Locator Slip: 01/30/2025, 11:00am, Official, NBN | F16: VMM | G16: For Signature
A17: =A16 -> 45687 | B17: =B16+1 -> 11 | C17: Travel Order : ADM-TO 009 & OMS-TO 144 Gate Pass : 166-2025 RIS : 083-2025 | F17: VMM | G17: For Signature
A18: =A17 -> 45687 | B18: =B17+1 -> 12 | C18: Personnel Locator Slip: 1/30/2025, 1:00PM, RP Bonapos, Personal 01/30/2025, 12:30PM, AM Lopez & AP Francia, Official | F18: VMM | G18: For Signature
A19: =A18 -> 45687 | B19: =B18+1 -> 13 | C19: Cheque & Attachments: Vilma M. Manlangit - Php 33,954.47 Labor at OGSONG RIS for Dec. 1-15, 2024 (Variance 2023) BC Dugan & 9 Others | F19: MCGS | G19: For Signature
A20: =A19 -> 45687 | B20: =B19+1 -> 14 | C20: Cheque & Attachments: Edilberto R. Beo Jr - Php 1,350.00 TEV December 2024 | F20: MCGS | G20: For Signature
A21: =A20 -> 45687 | B21: =B20+1 -> 15 | C21: Cheque & Attachments: Dale Derick L. Detera - Php 4,995.00 TEV July 5-December 11, 2024 | F21: MCGS | G21: For Signature
A22: =A21 -> 45687 | B22: =B21+1 -> 16 | C22: Cheque & Attachments: Rodolfo G. llave Jr. - Php 4,500.00 TEV June-August 2024 | F22: MCGS | G22: For Signature
A23: =A22 -> 45687 | B23: =B22+1 -> 17 | C23: Cheque & Attachments: Ian Feliciano III P. Berdin - Php 3,350.00 TEV June 2024 | F23: MCGS | G23: For Signature
A24: =A23 -> 45687 | B24: =B23+1 -> 18 | C24: Cheque & Attachments: Carlito C. Pongpong - Php 2,000.00 TEV November 5-21, 2024 | F24: MCGS | G24: For Signature
A25: =A24 -> 45687 | B25: =B24+1 -> 19 | C25: Cheque & Attachments: Claire's Resto & Catering - Php 4,275.00 Meals for Convergence Meeting last 10/11/2024 | F25: MCGS | G25: For Signature
A26: =A25 -> 45687 | B26: =B25+1 -> 20 | C26: Cheque & Attachments: Claire's Resto & Catering - Php 21,660.00 Meals/Snacks for Capability Building of Various IA last 10/09/2024 | F26: MCGS | G26: For Signature
... A41: =A40 -> 45687 | B41: =B40+1 -> 35 | C41: To Region: Gender & Development Plan & Budget for CY 2025 & Box 8 1. Cabraran Pequeño CIS 2. Baldaing Awang CIS | F41: MCGS | G41: For Signature
A42: =A41 -> 45687 | B42: =B41+1 -> 36 | C42: From Region: DPWH-NIA Convergence: DPWH's Flood Management Program for FY 2025 GAA | F42: MCGS
A43: =A42 -> 45687 | B43: =B42+1 -> 37 | C43: Cheque & Attachments: Gail Nicole J. Jacob - Php480.00 TEV November 13,14 & 19, 2024 | F43: MCGS | G43: For Signature
A44: =A43 -> 45687 | B44: =B43+1 -> 38 | C44: Payroll: Adelante, Llave Jr (12/16-31/2024) Arcilla (01/01-15/2025) | F44: MCGS | G44: For Signature
A45: =A44 -> 45687 | B45: =B44+1 -> 39 | C45: Gate Pass Mtls: 016-2025 | F45: VMM | G45: For Signature
A46: =A45 -> 45687 | B46: =B45+1 -> 40 | C46: From: WCVC Builders Request for Copy of Acceptance 1. Bugao CIS (CAT-RREIS-2020-01-07INF) 2. Quirino CIS (CAT-RREIS-2020-01-04INF) 3. Sicmil CIS (CAT-RREIS-2020-01-01INF) 4. San Roque CIP (CAT-SIP-2020-01-02INF) | D46: CATNES | G46: endorse to Catanduanes
A47: =A46 -> 45687 | B47: =B46+1 -> 41 | C47: To Catanduanes: Request for Copy of Acceptance 1. Bugao CIS (CAT-RREIS-2020-01-07INF) 2. Quirino CIS (CAT-RREIS-2020-01-04INF) 3. Sicmil CIS (CAT-RREIS-2020-01-01INF) 4. San Roque CIP (CAT-SIP-2020-01-02INF) | D47: CATNES | F47: VMM | G47: For Signature
A48: ***NOTHING FOLLOWS***
A50: Received, Recorded, Tracked, Disseminated & Filed:
A53: COLEEN M. RASTRULLO | D53: ELLA N. RINGAD | G53: JESSICA V. PEÑAFLOR
A54: Engineering Assistant A | D54: Engineering Assistant A | G54: Information Officer C

Sheet 0131
A1: INCOMING DOCUMENTS TO THE OFFICE OF THE IMO MANAGER
A2: 45688
A3: =TEXT(A2,"DDDD") -> Friday
A4: NOTE: | B4: All signatories on Official Business. OIC : RAP
A5: NO. | C5: DOCUMENTS | F5: TO | G5: REMARKS
C6: PARTICULAR | D6: SECTION | E6: TYPE
A7: =A2 -> 45688 | B7: 1 | C7: Gate Pass Vcls : 174, 168, 171, 168, 171, 172, 167, 173, 170-2025 RIS : 087, 084, 085, 086-2025 Transpo Req. : 125, 126, 122,127,128-2025 | G7: For signature
A8: =A7 -> 45688 | B8: =B7+1 -> 2 | C8: Gate Pass Mtrls : 017-2025 | G8: For signature
A9: =A8 -> 45688 | B9: =B8+1 -> 3 | C9: RIS : 088-2025 Gate Pass Vcls: 175-2025
A10: =A9 -> 45688 | B10: =B9+1 -> 4 | C10: Travel Order : ENG-TO 185, OMS-TO 145 | G10: For signature
A11: =A10 -> 45688 | B11: =B10+1 -> 5 | C11: Authority to Render Overtime Services (1/18/2025) 1. JB Completo & 3 | F11: MCGS | G11: For signature
A12: =A11 -> 45688 | B12: =B11+1 -> 6 | C12: Travel Order : ENG-TO186, OMS-TO 146 Gate Pass Mtls : 018-2025 | G12: For signature
A13: =A12 -> 45688 | B13: =B12+1 -> 7 | C13: Authority to Render Overtime Services (1/18/2025) 1. PJC Pante (30/1/2025) | F13: MCGS | G13: For signature
A14: =A13 -> 45688 | B14: =B13+1 -> 8 | C14: Authority to Render Overtime Services (2/1/2025) 1. NB Oraye (2/1/2025) | G14: For signature
A15: =A14 -> 45688 | B15: =B14+1 -> 9 | C15: Gate Pass Mtrls : 019-2025 | G15: For signature
A16: =A15 -> 45688 | B16: =B15+1 -> 10 | C16: APEX Builders Request for In-House Inspection AL-EGPIPSOL-004-24INF | G16: routed to eng'g
A17: =A16 -> 45688 | B17: =B16+1 -> 11 | C17: Personnel Locator Slip : 1/31/2025, WP Eusebio,11:30 am, Official | G17: For signature
A18: =A17 -> 45688 | B18: =B17+1 -> 12 | C18: Travel Order : OMS-TO 147 Authority to Render Overtime Services 1. Raposa & 1 (2/1 & 2/25) | G18: For signature
A19: =A18 -> 45688 | B19: =B18+1 -> 13 | C19: Authority to Render Overtime Services 1. DR Pagal (1/30-31/2025) Travel Order : ADM-TO 010 | G19: For signature
A20: =A19 -> 45688 | B20: =B19+1 -> 14 | C20: Travel Order : ENG-TO 187 | F20: MCGS | G20: For signature
A21: =A20 -> 45688 | B21: =B20+1 -> 15 | C21: Travel Order : ENG-TO 188 | G21: For signature
A22: =A21 -> 45688 | B22: =B21+1 -> 16 | C22: Gate Pass Vcls : 176-2025 RIS : 089, Daily Trip Ticket : 131, 069, 068, 067, 066, 065, 064, 063, 062, 061, 060, 059, 058-2025 | G22: For signature
A23: =A22 -> 45688 | B23: =B22+1 -> 17 | C23: Authority to Render Overtime Services 1. JAR Sarion & 6 (2/1/2025) | G23: For signature
A24: =A23 -> 45688 | B24: =B23+1 -> 18 | C24: Notice of Meeting: Upcoming 1st Quarter Regular Meeting of Protected Area Management board (PAMB) February 4, 2025, 9:00am
A25: =A24 -> 45688 | B25: =B24+1 -> 19 | C25: Itinerary of Travel : ENG-TO 189 to 210 | G25: For signature
A26: ***NOTHING FOLLOWS***
A28: Received, Recorded, Tracked, Disseminated & Filed:
A31: COLEEN M. RASTRULLO | D31: ELLA N. RINGAD | G31: JESSICA V. PEÑAFLOR
A32: Engineering Assistant A | D32: Engineering Assistant A | G32: Information Officer C

Sheet 0203
A1: INCOMING DOCUMENTS TO THE OFFICE OF THE IMO MANAGER
A2: 45691
A3: =TEXT(A2,"DDDD") -> Monday
A4: NOTE: | B4: MCGS present at Afternoon. OIC for AM: BPB
A5: NO. | C5: DOCUMENTS | F5: TO | G5: REMARKS
C6: PARTICULAR | D6: SECTION | E6: TYPE
A7: =A2 -> 45691 | B7: 1 | C7: Travel Order: OMS-TO150 | D7: OMS | F7: BPB | G7: For signature
A8: =A7 -> 45691 | B8: =B7+1 -> 2 | C8: Travel Order: ENG-TO211,212 | D8: ENG'G | F8: BPB | G8: For signature
A9: =A8 -> 45691 | B9: =B8+1 -> 3 | C9: Authority to Render Overtime Services: AM Dela Cruz (01/18/2025) | D9: ENG'G | F9: MCGS | G9: For signature
A10: =A9 -> 45691 | B10: =B9+1 -> 4 | C10: Itinerary: OMS-TO150,151 Travel Order: OMS-TO152,153 | D10: OMS | F10: BPB | G10: For signature
A11: =A10 -> 45691 | B11: =B10+1 -> 5 | C11: Gate Pass Vcls: 177,178,179,180,181-2025 RIS: 090,091,092-2025 Transpo Req: 132,133,134,135,137-2025 | D11: OMS | F11: BPB | G11: For signature
A12: =A11 -> 45691 | B12: =B11+1 -> 6 | C12: RIS ROV - 25-01-060 Delivery Receipt (01/31/2025)- 130bags BB Rice | F12: MCGS | G12: For signature
A13: =A12 -> 45691 | B13: =B12+1 -> 7 | C13: Travel Order: ENG-TO213 | D13: ENG'G | F13: BPB | G13: For signature
A14: =A13 -> 45691 | B14: =B13+1 -> 8 | C14: Itinerary: OMS-TO154,155 | D14: OMS | F14: BPB | G14: For signature
A15: =A14 -> 45691 | B15: =B14+1 -> 9 | C15: Travel Order: OMS-TO156 Gate Pass Vcls: 182-2025 | D15: OMS | F15: BPB | G15: For signature
A16: =A15 -> 45691 | B16: =B15+1 -> 10 | C16: Itinerary: ENG-TO214,215,216,217 | D16: ENG'G | F16: BPB | G16: For signature
A17: =A16 -> 45691 | B17: =B16+1 -> 11 | C17: Personnel Locator Slip: 02/03/2025, 10:40AM, Official, CL Lontac & CL Lontac | D17: OMS | F17: BPB | G17: For signature
A18: =A17 -> 45691 | B18: =B17+1 -> 12 | C18: RIS: 093-2025 | D18: OMS | F18: BPB | G18: For signature
A19: =A18 -> 45691 | B19: =B18+1 -> 13 | C19: Letter to: (02/03/2025) Ligao City Mayor Brgy. Tinampo Barangay Captain re: Invitation for Special meeting on 02/07/2025 at Barangay Hall, Tinampo, Ligao City at 9:00AM | D19: OMS | F19: BPB | G19: For signature
A20: =A19 -> 45691 | B20: =B19+1 -> 14 | C20: Itinerary : OMS-TO157 | D20: OMS | F20: BPB | G20: For signature
A21: =A20 -> 45691 | B21: =B20+1 -> 15 | C21: Itinerary : ENG-TO219 | D21: ENG'G | F21: BPB | G21: For signature
A22: =A21 -> 45691 | B22: =B21+1 -> 16 | C22: Personnel Locator Slip: 02/03/2025, 1:00PM, Official, AM Lopez & AP Francia | D22: OMS | F22: BPB | G22: For signature
A23: =A22 -> 45691 | B23: =B22+1 -> 17 | C23: From Catanduanes: Resubmission of Attachments for 1st Partial Billing Baniaga CIS (CAT-RREIS-005-24INF) Panganiban CIS (CAT-RREIS-008-24INF) Inagasan CIS (CAT-RREIS-004-24INF) | D23: CATNES | G23: TO JAS
A24: =A23 -> 45691 | B24: =B23+1 -> 18 | C24: From Catanduanes: Revised attachments for CY 2025 POW of: 1. Caningag CIS 2. Carangag CIS 3. Oco CIS | D24: CATNES | G24: TO JAS
A25: =A24 -> 45691 | B25: =B24+1 -> 19 | C25: From: West Buyo Irrigator Association of Ilawod Inc. Resolution No. 01 s. 2025 "A Board Resolution requesting NIA ACIMO for immediate repair of dilapedated Lateral A Canal and 10meters damaged at Lateral B Canal" | F25: MCGS
A26: =A25 -> 45691 | B26: =B25+1 -> 20 | C26: Itinerary: OMS-TO159 | D26: OMS | F26: BPB | G26: For signature
A27: =A26 -> 45691 | B27: =B26+1 -> 21 | C27: Itinerary: OMS-TO160 | D27: OMS | F27: BPB | G27: For signature
A28: =A27 -> 45691 | B28: =B27+1 -> 22 | C28: Authority to Render Overtime Services: IC Cullat (01/31/2025) MDO Orogo & 1 (01/18-19/2025) MM Etcobanez & 1 (01/18/2025) RP Bonapos & 1 (01/16/2025) | D28: ADMIN | F28: MCGS | G28: For signature
A29: =A28 -> 45691 | B29: =B28+1 -> 23 | C29: Gate Pass Mtls: 020,021-2025 | D29: ADMIN | F29: BPB | G29: For signature
A30: =A29 -> 45691 | B30: =B29+1 -> 24 | C30: Itinerary: ENG-TO221 | D30: ENG'G | F30: BPB | G30: For signature
A31: =A30 -> 45691 | B31: =B30+1 -> 25 | C31: Travel Order: ENG-TO220 | D31: ENG'G | F31: BPB | G31: For signature
A32: =A31 -> 45691 | B32: =B31+1 -> 26 | C32: To COA: Bank Reconciliation Statement Fund 501 LFP & CARP-IC for December 2024 | D32: FINANCE | F32: MCGS | G32: For signature
A33: =A32 -> 45691 | B33: =B32+1 -> 27 | C33: Transaction Acknowledgement Payroll 12/1-15/2024 F-501 CARP | D33: FINANCE | F33: MCGS | G33: For signature
A34: =A33 -> 45691 | B34: =B33+1 -> 28 | C34: Transaction Acknowledgement Payroll 12/1-15/2024 -Permanent NIA 501 COB | D34: FINANCE | F34: MCGS | G34: For signature
A35: =A34 -> 45691 | B35: =B34+1 -> 29 | C35: Personnel Locator Slip: 02/03/2025, 2:30PM, Official, JV Peñaflor | F35: MCGS | G35: For signature
A36: =A35 -> 45691 | B36: =B35+1 -> 30 | C36: Authority to Render Overtime Services: AP Francia & 2 (02/02/2025) | D36: OMS | F36: MCGS | G36: For signature
A37: =A36 -> 45691 | B37: =B36+1 -> 31 | C37: Itinerary: OMS-TO158,161 | D37: OMS | F37: MCGS | G37: For signature
A38: =A37 -> 45691 | B38: =B37+1 -> 32 | C38: Gate Pass : 183-2025 RIS : 094-2025 Transpo Req. : 140-2025 | D38: OMS | F38: MCGS | G38: For signature
A39: =A38 -> 45691 | B39: =B38+1 -> 33 | C39: Resignation Letter of Patricia Gillyn L. Credo, SAPB | D39: ADMIN | F39: MCGS
A40: =A39 -> 45691 | B40: =B39+1 -> 34 | C40: Itinerary: ENG-TO222 Travel Order: OMS-TO164,165 | F40: MCGS | G40: For signature
A41: =A40 -> 45691 | B41: =B40+1 -> 35 | C41: To COA: Copy of emailed scanned copies of purchase request, purchase order, and inspection & acceptance report dated February 3, 2025 1. IDSCAT-24-12-002 2. IAR-IDS-24-003 3. IAR-IDS-24-11-004 | D41: ADMIN | F41: MCGS | G41: For signature
A42: =A41 -> 45691 | B42: =B41+1 -> 36 | C42: Personnel Locator Slip: 02/03/2025, 4:00PM, Personal, AB Calpe | D42: ADMIN | F42: MCGS | G42: For signature
A43: =A42 -> 45691 | B43: =B42+1 -> 37 | C43: Inspection Report (Completed) 1. 01/10/2025: Desilting at Farm Area of Lower-Talisay CIS, Libon, Albay due to Severe Flooding Caused by Typhoon Kristine 2. 01/21/2025: Removal of Debris Remains Brought by Typhoon Kristine at Cabangan oas-Polangui Irrigation Dam 3. 01/22/2025: Repair of Pulley Assembly of Sluice Gate at CSJ Rubber Dam | D43: OMS | F43: MCGS | G43: For signature
A44: =A43 -> 45691 | B44: =B43+1 -> 38 | C44: Inspection Report (Mobilization) 1. 01/22/2025: Backhoe Mobilization for Desilting at Farm Area of South Quinale RIS, Oas-Libon, Albay due to Severe Flood Caused by the typhoon 2. 12/05/2024: Backhoe Mobilization for Desilting at Farm Area of Prisa Left, oas, Albay due to Severe Flood Casued by the Typhoon Kristine 3. 12/11/2024: Backhoe Mobilization for Desiliting at Farm Area of Lower Talisay, Libon, Albay due to Severe Flood Caused by Typhoon Kristine 4. 01/17/2025: Mobilization of Backhoe for the Removal of Debris Remains Brought by Typhoon Kristine at Cabangan Oas-Polangui Irrigation Dam | D44: OMS | F44: MCGS | G44: For signature
A45: =A44 -> 45691 | B45: =B44+1 -> 39 | C45: Inspection Report (For Excavation) 1. 01/30/2025: Inspection for Backhoe Request at Kamanitohan CIS, Manito, Albay 2. 12/20/2024: Backhoe Request for the Removal of Debris Remains Brought by Typhoon Kristine at Cabangan Oas-Polangui Irrigation Dam 3. 12/04/2024: Backhoe Request for Desilting at Farm Area of Lower Talisay CIS, Libon, albay due to Severe Flood Caused by the Typhoon Kristine 4. 12/04/2024: Backhoe Request for Desilting at Farm Area of Prisa Left Quinale, Oas-Libon, Albay due to Severe Flood Caused by the Typhoon Kristine 5. 12/04/2024: Backhoe Request for Desilting at Farm Area of South Quinale RIS, Oas-Libon, Albay due to Severe Flood Caused by the Typhoon Kristine | D45: OMS | F45: MCGS | G45: For signature
A46: =A45 -> 45691 | B46: =B45+1 -> 40 | C46: Itinerary: OMS-TO162,163,166 Travel Order: OMS-TO167 | D46: OMS | F46: MCGS | G46: For signature
A47: =A46 -> 45691 | B47: =B46+1 -> 41 | C47: CAR Form No.: AC202502:01 West Buyo Irrigator Association of Ilawod Inc. Resolution No. 01 s. 2025 | D47: IMO | F47: MCGS | G47: For signature
A48: =A47 -> 45691 | B48: =B47+1 -> 42 | C48: NIA-IA Functionality Survey-CIS NIA-IA Functionality Survey-NIS Summary of IA Functionality for the Province of Albay CY 2024 | D48: OMS | F48: MCGS | G48: For signature
A49: =A48 -> 45691 | B49: =B48+1 -> 43 | C49: Certification for Realm Construction & Trading with wxisting contract with the NIA as of 01/28/2025 Manambrag CIS (CAT-CARP-001-23INF) issued: 02/03/2025 | D49: FINANCE | F49: MCGS | G49: For signature
A50: =A49 -> 45691 | B50: =B49+1 -> 44 | C50: Gate Pass Vcls: 184,185,186,187,188,189-2025 RIS: 095,096,097-2025 Transpo Req: 142,141,143,144,145-2025 | D50: OMS | F50: MCGS | G50: For signature
A51: ***NOTHING FOLLOWS***
A53: Received, Recorded, Tracked, Disseminated & Filed:
A56: COLEEN M. RASTRULLO | D56: ELLA N. RINGAD | G56: JESSICA V. PEÑAFLOR
A57: Engineering Assistant A | D57: Engineering Assistant A | G57: Information Officer C

Sheet 0204
A1: INCOMING DOCUMENTS TO THE OFFICE OF THE IMO MANAGER
A2: 45692
A3: =TEXT(A2,"DDDD") -> Tuesday
A4: NOTE: | B4: OIC until 9:00AM: BPB.
A5: NO. | C5: DOCUMENTS | F5: TO | G5: REMARKS
C6: PARTICULAR | D6: SECTION | E6: TYPE
A7: =A2 -> 45692 | B7: 1 | C7: Travel Order: OMS-TO160 Gate Pass Mtls: 022-2025 | D7: OMS | F7: BPB | G7: For signature
A8: =A7 -> 45692 | B8: =B7+1 -> 2 | C8: DRAFT: Office Memo: ADM009 s2025 Revised TEV Rates | D8: ADMIN | F8: MCGS
A9: =A8 -> 45692 | B9: =B8+1 -> 3 | C9: For NIA Administrator: Reconstitution of Bids and Awards Committee | D9: BAC | F9: MCGS | G9: For signature
A10: =A9 -> 45692 | B10: =B9+1 -> 4 | C10: PhilHealth Claim Signature Form Jemar B. Peñaflor | D10: OMS | F10: MCGS | G10: For signature
A11: =A10 -> 45692 | B11: =B10+1 -> 5 | C11: Travel Order: OMS-TO130 | D11: OMS | F11: MCGS | G11: For signature
A12: =A11 -> 45692 | B12: =B11+1 -> 6 | C12: RIS: 001,002,003,004,005-P-2024 | D12: OMS | F12: MCGS | G12: For signature
A13: =A12 -> 45692 | B13: =B12+1 -> 7 | C13: To: First OMB Construction & Development Corp re: Lacking Documentary Requirements for Payment Balasbas CIS (ALCARP-REPCIS-018-24INF) | D13: ENG'G | F13: MCGS | G13: For signature
A14: =A13 -> 45692 | B14: =B13+1 -> 8 | C14: Travel Order : ENG-TO 223 | D14: ENG'G | F14: MCGS | G14: For signature
A15: =A14 -> 45692 | B15: =B14+1 -> 9 | C15: Application for Leave: MDS Belgado (02/05/2025) LO Dedase (01/17/2025) (01/13/2025) (11/26/2024) JO Paje (01/4-5/2025) EMS Abila (01/27/2025) CC Pongpong (01/2-3/2025) RG Llave (01/30/2025) IP Adelante Jr (01/21/2025) CTO: DDL Detera (01/24/2025) | D15: ADMIN | F15: MCGS | G15: For signature
A16: =A15 -> 45692 | B16: =B15+1 -> 10 | C16: Gate Pass Mtls:023-2025 | D16: ADMIN | F16: MCGS | G16: For signature
A17: =A16 -> 45692 | B17: =B16+1 -> 11 | C17: Response to Resignation Letter of Ms. Patricia Gillyn Credo | D17: ADMIN | F17: MCGS | G17: For signature
A18: =A17 -> 45692 | B18: =B17+1 -> 12 | C18: Travel Order: OMS-TO169 | D18: OMS | F18: MCGS | G18: For signature
A19: =A18 -> 45692 | B19: =B18+1 -> 13 | C19: Payroll & Attachments Amielle Guarin & 2 (01/16-31/2025) | D19: FINANCE | F19: MCGS | G19: For signature
A20: =A19 -> 45692 | B20: =B19+1 -> 14 | C20: Travel Order: OMS-TO170 Itinerary: OMS-TO171 | D20: OMS | F20: MCGS | G20: For signature
... A43: =A42 -> 45692 | B43: =B42+1 -> 37 | C43: To: Roca Blanca Construction Approved copy of plans for South Quinale RIS (AL-EGPIPSOL-014-24INF) | D43: ENG'G | F43: MCGS | G43: For signature
A44: =A43 -> 45692 | B44: =B43+1 -> 38 | C44: Travel Order: ENG-TO224 FIN-TO001 | F44: MCGS | G44: For signature
A45: =A44 -> 45692 | B45: =B44+1 -> 39 | C45: To Region: Job Order Appointment 1. Credo, PGI & 1 2. Peñaflor, JV & 1 3. Reodique, KCO 4. Amados, JA & 2 5. Olivera, LMB & 1 | D45: ADMIN | F45: MCGS | G45: For signature
A46: =A45 -> 45692 | B46: =B45+1 -> 40 | C46: Gate Pass Vcls: 191,192,193,194,195,196-2025 RIS: 099,101,100-2025 Transpo Req: 148,1563,150,152,151,154,147-2025 Trip Ticket: 070-2025 | D46: OMS | F46: MCGS | G46: For signature
A47: ***NOTHING FOLLOWS***
A49: Received, Recorded, Tracked, Disseminated & Filed:
A52: COLEEN M. RASTRULLO | D52: ELLA N. RINGAD | G52: JESSICA V. PEÑAFLOR
A53: Engineering Assistant A | D53: Engineering Assistant A | G53: Information Officer C

Sheet 0205
A1: INCOMING DOCUMENTS TO THE OFFICE OF THE IMO MANAGER
A2: 45693
A3: =TEXT(A2,"DDDD") -> Wednesday
A4: NOTE: | B4: MCGS & other signatories on official business from 10:45am onwards. OIC: MME
A5: NO. | C5: DOCUMENTS | F5: TO | G5: REMARKS
C6: PARTICULAR | D6: SECTION | E6: TYPE
A7: =A2 -> 45693 | B7: 1 | C7: Personnel Locator Slip: 02/05/2025,8:45AM,Official, AM Lopez | D7: ADMIN | F7: MCGS | G7: For signature
A8: =A7 -> 45693 | B8: =B7+1 -> 2 | C8: Travel Order: ENG-TO225 | D8: ENG'G | F8: MCGS | G8: For signature
A9: =A8 -> 45693 | B9: =B8+1 -> 3 | C9: Travel Order: OMS-TO172 Itinerary: OMS-TO174,173,175,176 | D9: OMS | F9: MCGS | G9: For signature
A10: =A9 -> 45693 | B10: =B9+1 -> 4 | C10: Travel Order: OMS-TO177 | D10: OMS | F10: MCGS | G10: For signature
A11: =A10 -> 45693 | B11: =B10+1 -> 5 | C11: HDMF for KA Almiñana & 2 for September 2024 | D11: FINANCE | F11: MCGS | G11: For signature
A12: =A11 -> 45693 | B12: =B11+1 -> 6 | C12: To Region: Notarized CAN 2024 Affidavit of Undertaking 1. LFCP 2. VEP | D12: ADMIN | F12: MCGS | G12: For signature
A13: =A12 -> 45693 | B13: =B12+1 -> 7 | C13: Travel Order: OMS-TO179 | D13: OMS | F13: MME | G13: For signature
A14: =A13 -> 45693 | B14: =B13+1 -> 8 | C14: From Region: Submission of POW CY 2025 for Operation & Maintenance of NIS & CIS Pump Irrigation System (OMNISPIS) & (OMCISPIS) and Establishment of Pump Irrigation Project - Solar Pump Irrigation Project (EPIP-SPIP) | F14: MCGS
A15: =A14 -> 45693 | B15: =B14+1 -> 9 | C15: From Region: ASA No. 5-501-2025-005 | F15: MCGS
A16: =A15 -> 45693 | B16: =B15+1 -> 10 | C16: From Region: Notice of Meeting & Travel Order on February 5 & 27, 2025 to attenf the IAS Financial Audit Entrance & Exit Conference | F16: MCGS
A17: =A16 -> 45693 | B17: =B16+1 -> 11 | C17: From GSIS: Membership Data and Loan Records December 2024 | F17: MCGS
A18: =A17 -> 45693 | B18: =B17+1 -> 12 | C18: From Landers: Free Membership and Renewal for Credit Card Application | F18: MCGS
A19: =A18 -> 45693 | B19: =B18+1 -> 13 | C19: Overtime Request: RP Bonapos (02/01/2025) RP Bonapos (02/08 & 15/2025) DRP Pagal (02/03/2025 | D19: ADMIN | F19: MCGS | G19: For signature
A20: =A19 -> 45693 | B20: =B19+1 -> 14 | C20: Application for Leave: BP Balingasa (01/30-31/2025) AB Calpe (02/07/2025) MM Etcobanez (01/24/2025) EJ Jacob (12/09/2024) MM Etcobanez (01/17/2025), (12/09 & 23/2024) LO Dedase (01/20/2025) | D20: ADMIN | F20: MCGS | G20: For signature
A21: =A20 -> 45693 | B21: =B20+1 -> 15 | C21: Gate Pass Vcls: 198,199-2025 | D21: OMS | F21: MME | G21: For signature
A22: =A21 -> 45693 | B22: =B21+1 -> 16 | C22: Personnel Locator Slip: 02/05/2025,1:30PM, Official, J Amados | D22: OMS | F22: MME | G22: For signature
A23: =A22 -> 45693 | B23: =B22+1 -> 17 | C23: From COA: AOM No. 2025-01 (2024) ACIMO Delayed Completion fo the Project | D23: CATNES | F23: MCGS
A24: =A23 -> 45693 | B24: =B23+1 -> 18 | C24: From Region: Notice of Meeting TWG Meeting on the Consolidated Targets for the Regional Irrigation Master Plan (RIMP) 2023-2030 | F24: MCGS
A25: =A24 -> 45693 | B25: =B24+1 -> 19 | C25: To Catanduanes: Corrective Action Request Form No. AC202502:02 re: COA AOM No. 2025-01 (2024) ACIMO | D25: CATNES | G25: RUSH: emailed to Catanduanes
A26: =A25 -> 45693 | B26: =B25+1 -> 20 | C26: Travel Order: OMS-TO178 | D26: OMS | F26: MCGS | G26: For signature
A27: =A26 -> 45693 | B27: =B26+1 -> 21 | C27: Report of Accountability for Accountable Forms | D27: FINANCE | F27: MCGS | G27: For signature
A28: =A27 -> 45693 | B28: =B27+1 -> 22 | C28: Cheque & Attachments: 3JA Office and Schools Supplies - 16,467.85 Purchase of Digital Wall Clock | D28: FINANCE | F28: MCGS | G28: For signature
A29: =A28 -> 45693 | B29: =B28+1 -> 23 | C29: Personnel Locator Slip: 02/05/2025, 2:35PM, Official, NB Nash | D29: ENG'G | F29: MME | G29: For signature
A30: =A29 -> 45693 | B30: =B29+1 -> 24 | C30: Personnel Locator Slip: 02/05/2025, 3:00pm, Official, JL Agripa | D30: OMS | F30: MME | G30: For signature
A31: =A30 -> 45693 | B31: =B30+1 -> 25 | C31: Travel Order: ENG-TO226 | D31: ENG'G | F31: MME | G31: For signature
A32: =A31 -> 45693 | B32: =B31+1 -> 26 | C32: To Region: Results of NIA Ushering 2025: "Crafting Horizons" | D32: ADMIN | F32: MCGS | G32: For signature
A33: =A32 -> 45693 | B33: =B32+1 -> 27 | C33: Gate Pass Vcls: 197,200,201,202,203,204,205-2025 RIS: 098,104,103,102-2025 Transpo Req: 139,156,159,160,157,158-2025 | D33: OMS | F33: MME | G33: For signature
A34: =A33 -> 45693 | B34: =B33+1 -> 28 | C34: CTO: MA Robledo (01/29/2025) MB Dacillo (01/20/2025) | D34: ADMIN | F34: MCGS | G34: For signature
A35: =A34 -> 45693 | B35: =B34+1 -> 29 | C35: CY 2025 CSE, PPMP & APP | D35: ADMIN | F35: MCGS | G35: For signature
A36: =A35 -> 45693 | B36: =B35+1 -> 30 | C36: From Central Office: Comments on the Feasibility Study Report of Cabilogan-San Juan River Irrigation System under Modernization Program | D36: ENG'G | F36: MCGS
A37: =A36 -> 45693 | B37: =B36+1 -> 31 | C37: To Ligao City Police Station: To BFP Region V: re: Request for Resource Speakers on the conduct of 1-Day Seminar in Celebration of National Women's Month & Fire Prevention month on March 7, 2025 at NIA ACIMO Covered Court | D37: ADMIN | F37: MCGS | G37: For signature
A38: =A37 -> 45693 | B38: =B37+1 -> 32 | C38: Travel Order: OMS-TO180 | D38: OMS | F38: MME | G38: For signature
A39: =A38 -> 45693 | B39: =B38+1 -> 33 | C39: Travel Order: OMS-TO181 | D39: OMS | F39: MME | G39: For signature
A40: =A39 -> 45693 | B40: =B39+1 -> 34 | C40: Memorandum of Agreement w/ BUPC | D40: ADMIN | F40: MCGS | G40: For signature
A41: =A40 -> 45693 | B41: =B40+1 -> 35 | C41: Paid Wages (Payroll): 1. Paraiso (08/1-15/2024) 2. Dayupay (10/30-31/2024) 3. Aycardo (11/16-30/2024) 4. Guarin & Warde (12/1-18/2024) 5. Almiñana (11/16-31/2024) 6. D, Manlangit (12/1-18/2024) 7. Balingasa & Azutea (10/16-29/2024) 8. Delgado (10/16-31/2024) | D41: ADMIN | F41: MCGS | G41: For signature
A42: ***NOTHING FOLLOWS***
A44: Received, Recorded, Tracked, Disseminated & Filed:
A47: COLEEN M. RASTRULLO | D47: ELLA N. RINGAD | G47: JESSICA V. PEÑAFLOR
A48: Engineering Assistant A | D48: Engineering Assistant A | G48: Information Officer C

Sheet 0206
A1: INCOMING DOCUMENTS TO THE OFFICE OF THE IMO MANAGER
A2: 45694
A3: =TEXT(A2,"DDDD") -> Thursday
A4: NOTE: | B4: MCGS & other signatories on official business from 10:45am onwards. OIC: VMM (8:00 to 9:15 am), MCGS 9:20 am to 5:00pm
A5: NO. | C5: DOCUMENTS | F5: TO | G5: REMARKS
C6: PARTICULAR | D6: SECTION | E6: TYPE
A7: =A2 -> 45694 | B7: 1 | C7: Gate Pass: 206-2025 Requisition and Issue Slip: 105-2025 to 108-2025 | D7: OMS | F7: VMM | G7: For signature
A8: =A7 -> 45694 | B8: =B7+1 -> 2 | C8: Gate Pass: 024-2025 | D8: OMS | F8: VMM | G8: For signature
A9: =A8 -> 45694 | B9: =B8+1 -> 3 | C9: Requisition and Issue Slip: 109-2025 | D9: OMS | F9: VMM | G9: For signature
A10: =A9 -> 45694 | B10: =B9+1 -> 4 | C10: JEV for Fund 501-COB for Oct.1-15,2024 (Letter to M.Aguilar) | D10: FINANCE | F10: MCGS | G10: For signature
A11: =A10 -> 45694 | B11: =B10+1 -> 5 | C11: Regular Parcom Conference on Feb. 20, 2025 9:30AM to 2:00PM at BFD,Bariada, Legazpi City | D11: ENG'G | F11: MCGS | G11: for routing
A12: =A11 -> 45694 | B12: =B11+1 -> 6 | C12: PCR -for Repair/Rehab. Of Diversion and Canals of Bugao CIS (RREIS-CT-052-18) | D12: ENG'G | F12: MCGS | G12: for routing
A13: =A12 -> 45694 | B13: =B12+1 -> 7 | C13: Resubmission of Attachments for CY 2023 Variation Order No.1 of Repai/Restor of Bugao CIS & Obo-Mosbos CIS | D13: ENG'G | F13: MCGS | G13: for routing
A14: =A13 -> 45694 | B14: =B13+1 -> 8 | C14: Records of Leave of Absence Azutea Charlie B. | D14: ADMIN | F14: MCGS | G14: For signature
A15: =A14 -> 45694 | B15: =B14+1 -> 9 | C15: CY 2025 DEPLOYMENT SCHEME FOR INSTITUTIONAL WORKERS | D15: OMS | F15: MCGS | G15: for routing
A16: =A15 -> 45694 | B16: =B15+1 -> 10 | C16: CARP - IC YEAR END REVIEW AND PLANNING/ASSESMENT WORKSHOP ON MARCH 5, 2025 AT NIA RO V | D16: OMS | F16: MCGS | G16: for routing
A17: =A16 -> 45694 | B17: =B16+1 -> 11 | C17: PCR- TANAWAN CIS & 9 OTHERS | D17: OMS | F17: MCGS | G17: for routing
A18: =A17 -> 45694 | B18: =B17+1 -> 12 | C18: SEMINAR PROPOSALFOR WOMENS MONTH CELEBRATION IN CONNECTION WITH GENDER AND DEVELOPMENT | D18: ADMIN | F18: MCGS | G18: For signature
A19: =A18 -> 45694 | B19: =B18+1 -> 13 | C19: REVISED GENDER AND DEVELOPMENT PLAN AND BUDGET FOR CY 2025 | D19: ADMIN | F19: MCGS | G19: For signature
... A27: =A26 -> 45694 | B27: =B26+1 -> 21 | C27: AUTHORITY TO RENDER OVERTIME WORK (FEBRUARY 8, 2025) MYRA M. ETCOBANEZ AMY CALPE RICHARD S. NACARIO | D27: ADMIN | F27: MCGS | G27: For signature
A28: =A27 -> 45694 | B28: =B27+1 -> 22 | C28: NOTICE OF MEETING RE- PRIORITIZATION OF CY 2025 BUDGET FEBRUARY 10, 2025 | D28: ENG'G | G28: for routing
A29: =A28 -> 45694 | B29: =B28+1 -> 23 | C29: COORDINATION MEETING/ INSPECTION OF REGIONAL OFFICE - CONSTRUCTION MANAGEMENT SECTION PERSONNEL AT (IMO;S) | D29: ENG'G | F29: MCGS | G29: for routing
A30: =A29 -> 45694 | B30: =B29+1 -> 24 | C30: FORMAT FOR UNPAID PROJECTS FROM CY 2017 - 2022 | D30: ENG'G | F30: MCGS | G30: for routing
A31: =A30 -> 45694 | B31: =B30+1 -> 25 | C31: SUBMISSION OF STATUS OF FUNDS GAA 2021, 2022, 2023 & 2024 FOR FUND 501-LFP AS OF DEC 31, 2025 | D31: ENG'G | F31: MCGS | G31: for routing
A32: =A31 -> 45694 | B32: =B31+1 -> 26 | C32: OM NO. 010 S 2025 SUBMISSION OF OFFICIAL ENCODERS FOR THE ONLINE PREPARATION OF THE OFFICE AND DIVISION PERFORMANCE COMITMENT REVISED (ODPCR) SYSTEM | D32: ADMIN | F32: MCGS | G32: for routing
A33: =A32 -> 45694 | B33: =B32+1 -> 27 | C33: SUBMNISSION OF A DETAILED CONSTRUCTION SCHEDULE FOR CY 2025 PROGRAMS AND CATCH UP PLANS FOR ALL REMAINING ON GOING PROJECTS | D33: ENG'G | F33: MCGS | G33: for routing
A34: =A33 -> 45694 | B34: =B33+1 -> 28 | C34: 1ST ENDORSEMENT - UNITED ARCHITECTS OF THE PHIL. 50TH NATIONAL CONVENTION ON APRIL 7-12, 2025 | D34: ENG'G | F34: MCGS | G34: for routing
A35: =A34 -> 45694 | B35: =B34+1 -> 29 | C35: NOTICE OF MEETING ONE DAY INTERNAL BUDGET FORUM FOR THE FISCAL YEAR 2026 FEBRUARY 7, 2025 | D35: ENG'G | F35: MCGS | G35: for routing
A36: =A35 -> 45694 | B36: =B35+1 -> 30 | C36: (CAR) CORRECTIVE ACTION SUSAN DELA ROSA TANAWAN, MALINAO, ALBAY | D36: ENG'G | F36: MCGS | G36: for routing
A37: =A36 -> 45694 | B37: =B36+1 -> 31 | C37: Gate Pass Vcls: 208, 209, 210, 211-2025 RIS : 111, 112-2025 Transpo Req: 161,162,164, 165-2025 Travel Order : ADM-012 | D37: OMS | F37: MCGS | G37: For Signature
A38: =A37 -> 45694 | B38: =B37+1 -> 32 | C38: Travel Order : OMS-TO012 | D38: OMS | F38: MCGS | G38: For Signature
A39: =A38 -> 45694 | B39: =B38+1 -> 33 | C39: TO CSC: PLANTILLA OF CASUAL APPOINTMENT OF CLB. Lontac, Driver Mechanic B for the period 09/02/24 to 12/31/24
A40: ***NOTHING FOLLOWS***
A42: Received, Recorded, Tracked, Disseminated & Filed:
A45: COLEEN M. RASTRULLO | D45: ELLA N. RINGAD | G45: JESSICA V. PEÑAFLOR
A46: Engineering Assistant A | D46: Engineering Assistant A | G46: Information Officer C

Sheet 0207
A1: INCOMING DOCUMENTS TO THE OFFICE OF THE IMO MANAGER
A2: 45695
A3: =TEXT(A2,"DDDD") -> Friday
A4: NOTE: | B4: Office - MCGS
A5: NO. | C5: DOCUMENTS | F5: TO | G5: REMARKS
C6: PARTICULAR | D6: SECTION | E6: TYPE
A7: =A2 -> 45695 | B7: 1 | C7: Travel Order : OMS-TO 183 | D7: OMS | F7: MCGS | G7: For signature
A8: =A7 -> 45695 | B8: =B7+1 -> 2 | C8: Gate Pass -Vehicle : 215, 214,213, 212-2025 RIS : 114,113 | D8: OMS | F8: MCGS | G8: For signature
A9: =A8 -> 45695 | B9: =B8+1 -> 3 | C9: Gate Pass -Vehicle :216-2025 | D9: OMS | F9: MCGS | G9: For signature
A10: =A9 -> 45695 | B10: =B9+1 -> 4 | C10: To City of Ligao: re; request for a certification of no funding on Nasisi RIS Dam | D10: OMS | F10: MCGS | G10: For signature
A11: =A10 -> 45695 | B11: =B10+1 -> 5 | C11: RCI-Nov. 16-30, 2024 Report of collection & deposits-January 2025 | D11: FINANCE | F11: MCGS | G11: For signature
A12: =A11 -> 45695 | B12: =B11+1 -> 6 | C12: COA ADM No. 225-01 (2024) ACIMO Delayed completion of the project | D12: ADMIN
A13: =A12 -> 45695 | B13: =B12+1 -> 7 | C13: REPORT OF CHECK ISSUED NIA ALBAY-CATANDUANES IMO OCT. 16-31-2024 | D13: FINANCE | F13: MCGS | G13: For signature
A14: =A13 -> 45695 | B14: =B13+1 -> 8 | C14: 1. ACCOUNTABILITY FOR ACCOUNTABLE FORMS (DEC. 1-31, 2025) 2. RCI LFP/CARP/COB (NOV. 1-15, 2024) 3. RCD LFP/CARP/COB (NOV. 1-15, 2024) 4. JEV & DV HDMF | D14: FINANCE | F14: MCGS | G14: For signature
A15: =A14 -> 45695 | B15: =B14+1 -> 9 | C15: INSPECTION REPORT OF MNOH MAHABA RIS (MAZO IA) PROJECT COST VARIANCE (CY 2023), LIGAO CITY, ALBAY | D15: ENG'G | F15: MCGS | G15: For signature
A16: =A15 -> 45695 | B16: =B15+1 -> 10 | C16: Inspection Report regarding the Typhoon damaged caused by Typhoon Kristine at Kamanitohan CIS, Bgry. Manito, Albay | D16: ENG'G | F16: MCGS | G16: For signature
A17: =A16 -> 45695 | B17: =B16+1 -> 11 | C17: Itinerary : OMS-TO 184 | D17: OMS | F17: MCGS | G17: For signature
A18: =A17 -> 45695 | B18: =B17+1 -> 12 | C18: To COA : Copy of Procurement Monitoring Report as of December 31, 2024 | D18: FINANCE | F18: MCGS | G18: For signature
A19: =A18 -> 45695 | B19: =B18+1 -> 13 | C19: Personnel Locator Slip : 2/7/2025, 10:15AM, Official, CL Lontac | D19: ADMIN | F19: MCGS | G19: For signature
A20: =A19 -> 45695 | B20: =B19+1 -> 14 | C20: Gate Pass Vcls : 217-2025 RIS : 115-2025 Transpo Req. : 167-2025 | D20: OMS | F20: MCGS | G20: For signature
A21: =A20 -> 45695 | B21: =B20+1 -> 15 | C21: From Catanduanes : Response to COA ADM No. 2025-01 (2024) ACIMO Delayed Completion of the Project | D21: ADMIN
A22: =A21 -> 45695 | B22: =B21+1 -> 16 | C22: Travel Order : ENG-TO 228 | D22: ENG'G | F22: MCGS | G22: for siganture
A23: =A22 -> 45695 | B23: =B22+1 -> 17 | C23: Approved Sand and Gravel Permit Application 1. Raul M. Tarin 2. Wilfredo B. Avila 3. Noel A. Faustino 4. Robert B. Vargas 5. Napoleon R. Co | D23: ENG'G | F23: MCGS | G23: for siganture
A24: =A23 -> 45695 | B24: =B23+1 -> 18 | C24: Request for Render Work on February 8, 2025 FRANCISO B. SUAREZ JR. | D24: ENG'G | F24: MCGS | G24: for siganture
A25: =A24 -> 45695 | B25: =B24+1 -> 19 | C25: OFFICE MEMO No. ADM -008 S. 2025 RENDER OVERTIME SERVICE IN PREPARATION FOR IAS AUDIT | D25: ADMIN | F25: MCGS | G25: for siganture
A26: =A25 -> 45695 | B26: =B25+1 -> 20 | C26: PERMIT TO ENTER/ CONSTRUCT AND RIGHT OF WAY WAIVER 1. OLYMPIO S. SEVILLA 2. EFEREN B. MATA | D26: ENG'G | F26: MCGS | G26: for siganture
A27: =A26 -> 45695 | B27: =B26+1 -> 21 | C27: REQUEST FOR ICC SHIRLEY B. RODRIGUEZ | D27: ENG'G | F27: MCGS | G27: for siganture
A28: =A27 -> 45695 | B28: =B27+1 -> 22 | C28: GATE PASS - VEHICLE - 218-2025 Transpo Req. : 099-2025 | D28: OMS | F28: MCGS | G28: for siganture
A29: =A28 -> 45695 | B29: =B28+1 -> 23 | C29: Travel Order : ENG-TO 229,230,231,232 | D29: ENG'G | F29: MCGS | G29: for siganture
A30: =A29 -> 45695 | B30: =B29+1 -> 24 | C30: Proposal: IMT Contract Signing for Selected Gender-Responsive Irrigators Association in the Province of Albay | D30: OMS | F30: MCGS | G30: for siganture
A31: =A30 -> 45695 | B31: =B30+1 -> 25 | C31: AOM No. 2025-02 (2024) NIA.ACIMO February 4, 2025 | D31: ADMIN
A32: =A31 -> 45695 | B32: =B31+1 -> 26 | C32: Memorandum of Agreement (MOA) CARP-IC Quinartilan CIS | D32: OMS | F32: MCGS | G32: for siganture
A33: =A32 -> 45695 | B33: =B32+1 -> 27 | C33: Report of Disbursement ADA-Payroll October 16-31, 2024 LFP LBP Ligao 501 LBP 501 COB 501 CARP | D33: FINANCE | F33: MCGS | G33: for siganture
A34: =A33 -> 45695 | B34: =B33+1 -> 28 | C34: Daily Trip Ticket : 071, 072,073, 074, 075, 076,077,078,079, 080, 081 | D34: OMS | F34: MCGS | G34: for siganture
A35: =A34 -> 45695 | B35: =B34+1 -> 29 | C35: Reply to IA Reso 2403 at Maguranf Ubaliw Basud IA Basud Magurang CIS | D35: ENG'G | F35: MCGS | G35: for siganture
A36: =A35 -> 45695 | B36: =B35+1 -> 30 | C36: TraveL Order : OMS-TO 185 Authority to Render Overtime Services MHS, Nate (2/8/2025) | D36: OMS | F36: MCGS | G36: for siganture
A37: =A36 -> 45695 | B37: =B36+1 -> 31 | C37: Application for Leave : RS Nacario (12/26/202) LO Dedase (11/14/2024) | D37: ADMIN | F37: MCGS | G37: for siganture
A38: =A37 -> 45695 | B38: =B37+1 -> 32 | C38: Report of Dibursement ADA - Payroll (November 1-15, 2024) | D38: FINANCE | F38: MCGS | G38: for siganture
A39: =A38 -> 45695 | B39: =B38+1 -> 33 | C39: 15% Advance Payment Mobilization Tagoytoy CIS (AL-EGPIPSOL-009-24INF) (4 SETS) | D39: FINANCE | F39: MCGS | G39: for siganture
A40: =A39 -> 45695 | B40: =B39+1 -> 34 | C40: Itinerary : ENG-TO 233,234, 235, 236, 238, 240, 241, 239, 242, 237, 243, 247, 246, 244, 245, 248, 249, 250, 251, 252,253 | D40: ENG'G | F40: MCGS | G40: for siganture
A41: ***NOTHING FOLLOWS***
A43: Received, Recorded, Tracked, Disseminated & Filed:
A46: COLEEN M. RASTRULLO | D46: ELLA N. RINGAD | G46: JESSICA V. PEÑAFLOR
A47: Engineering Assistant A | D47: Engineering Assistant A | G47: Information Officer C

Sheet 0210
A1: INCOMING DOCUMENTS TO THE OFFICE OF THE IMO MANAGER
A2: 45698
A3: =TEXT(A2,"DDDD") -> Monday
A4: NOTE: | B4: MCGS & other signatories on official business OIC: VEP
A5: NO. | C5: DOCUMENTS | F5: TO | G5: REMARKS
C6: PARTICULAR | D6: SECTION | E6: TYPE
A7: =A2 -> 45698 | B7: 1 | C7: ITINERARY OF TRAVEL: OMS-TO193 & OMS-TO192 | D7: OMS | F7: VEP | G7: FOR SIGNATURE
A8: =A7 -> 45698 | B8: =B7+1 -> 2 | C8: ITINERARY OF TRAVEL: ENG-TO254 | D8: ENG'G | F8: VEP | G8: FOR SIGNATURE
A9: =A8 -> 45698 | B9: =B8+1 -> 3 | C9: ITINERARY OF TRAVEL: OMS-TO186,187,188,189,190,195, 194, 191 | D9: ENG'G | F9: VEP | G9: FOR SIGNATURE
A10: =A9 -> 45698 | B10: =B9+1 -> 4 | C10: GATE PASS VEHICLE 219-2025 220-2025 221-2025 222-2025 RIS: 116,117-2025 TRANSPO REQUEST-168,169,170,171,172 | D10: OMS | F10: VEP | G10: FOR SIGNATURE
A11: =A10 -> 45698 | B11: =B10+1 -> 5 | C11: RENDER WORK ON FEBRUARY 3-7, 2025 DARLENE MAE C. MAYOR AND 6 | D11: FINANCE | F11: MCGS | G11: FOR SIGNATURE
A12: =A11 -> 45698 | B12: =B11+1 -> 6 | C12: ITINERARY OF TRAVEL: OMS-TO196 | D12: OMS | F12: VEP | G12: FOR SIGNATURE
A13: =A12 -> 45698 | B13: =B12+1 -> 7 | C13: ITINERARY OF TRAVEL: ENG-TO 255, OMS-TO 197 Travel Order : ENG-TO 256 | D13: ENG'G | F13: VEP | G13: FOR SIGNATURE
A14: =A13 -> 45698 | B14: =B13+1 -> 8 | C14: Submission of Data for the Nationwide Planning Workshop and Assessment of the CY 2024 Inventory of Irrigation Systems and Operation Activities | D14: ENG'G
A15: =A14 -> 45698 | B15: =B14+1 -> 9 | C15: NIA- ASAB Meeting on February 11, 2025 | D15: OMS
A16: =A15 -> 45698 | B16: =B15+1 -> 10 | C16: Notice of Meeting on February 11, 2025 Coordination Meeting with the PNR Re: Irrigation Systems along SLH Alignment. | D16: OMS
A17: =A16 -> 45698 | B17: =B16+1 -> 11 | C17: Presentation of Finsl CY 2024 Inventory of Irrigation Systems as of Decemeber 31, 2024 | D17: OMS
A18: =A17 -> 45698 | B18: =B17+1 -> 12 | C18: Post Qualification Evaluation - F Guerrea Construction INC & 4 | D18: BAC
A19: =A18 -> 45698 | B19: =B18+1 -> 13 | C19: Search for the CY 2024 National Level Outstanding IA Performers for NIS and CIS Categories | D19: OMS
A20: =A19 -> 45698 | B20: =B19+1 -> 14 | C20: Gate Pass - Vehicle 223-2025 Travel Order Eng-To-257 Travel Order OMS-TO- 198,200 | D20: OMS | F20: VEP | G20: FOR SIGNATURE
A21: =A20 -> 45698 | B21: =B20+1 -> 15 | C21: Resubmission of attachements for the 1st Partial Progress Billing of Repair/Restoration of: 1. Tinago CIS 2. Panganiban CIS A3. Alibuag CIS | D21: ENG'G | F21: MCGS
A22: =A21 -> 45698 | B22: =B21+1 -> 16 | C22: Justification on Audit Observation In Memorundom (AOM) in MABATO & CIP's No. 2025-01 (2024) | D22: CATNES | F22: MCGS
A23: =A22 -> 45698 | B23: =B22+1 -> 17 | C23: Inspection Report RE: the Proposed Concreting of Brgy. NAPO- SITIO MATAMIS, BRGY. PONSO Farm to Market Road, Brgy. Napo and Brgy. Ponso, Polangui, Albay | D23: ENG'G | F23: MCGS
A24: =A23 -> 45698 | B24: =B23+1 -> 18 | C24: RENDER WORK ON FEBRUARY 8, 2025 DONEL P. VIBAR & 8 | D24: ENG'G | F24: MCGS
A25: =A24 -> 45698 | B25: =B24+1 -> 19 | C25: RENDER WORK ON FEBRUARY 8, 2025 FRANCISCO B. JUAREZ JR. & 1 | D25: ENG'G | F25: MCGS
A26: =A25 -> 45698 | B26: =B25+1 -> 20 | C26: ITINERARY OF TRAVEL: OMS-TO2199 | D26: OMS | F26: VEP | G26: FOR SIGNATURE
A27: =A26 -> 45698 | B27: =B26+1 -> 21 | C27: ITINERARY OF TRAVEL: ENG-TO258, 259 | D27: ENG'G | F27: VEP | G27: FOR SIGNATURE
A28: =A27 -> 45698 | B28: =B27+1 -> 22 | C28: Submission of Names of (IA's) and Farmers Beneficiaries for DOLE- Tupad Works | D28: OMS | F28: BPB
A29: =A28 -> 45698 | B29: =B28+1 -> 23 | C29: MC NO. 03 S 2025 NIA Consultations Performance Evaluation System , Guidelines for Irrigation Project | D29: ENG'G | F29: LFCP
A30: =A29 -> 45698 | B30: =B29+1 -> 24 | C30: ITINERARY OF TRAVEL: ENG-TO260,261 | D30: ENG'G | F30: VEP | G30: FOR SIGNATURE
A31: =A30 -> 45698 | B31: =B30+1 -> 25 | C31: PERSONNEL LOCATOR SLIP CHRISTIAN LEVY LONTAC | D31: ADMIN | F31: VEP | G31: FOR SIGNATURE
A32: =A31 -> 45698 | B32: =B31+1 -> 26 | C32: 3RD AND FINAL BILLING IMPROVEMENT OF NIA ACIMO COMPOUND AL-COB-001-23 | D32: FINANCE | F32: MCGS | G32: FOR SIGNATURE
A33: =A32 -> 45698 | B33: =B32+1 -> 27 | C33: ITINERARY OF TRAVEL: ENG-TO262,263 | D33: ENG'G | F33: VEP | G33: FOR SIGNATURE
A34: =A33 -> 45698 | B34: =B33+1 -> 28 | C34: CY 2025 project certification of no right of way issue | D34: CATNES | F34: MCGS | G34: FOR SIGNATURE
A35: =A34 -> 45698 | B35: =B34+1 -> 29 | C35: REPLY LETTER FOR THE INQUIRY RE: ACTIONS TAKEN FROM THE DAMAGES ON IRRIGATION FACILITIES AND STRUCTURES BY TYPHOON 2024, IN THE MUNICIPALITY OF LIBON, ALBAY | D35: ENG'G | F35: MCGS
A36: =A35 -> 45698 | B36: =B35+1 -> 30 | C36: ITINERARY OF TRAVEL: OMS-TO 201 | D36: OMS | F36: VEP | G36: FOR SIGNATURE
A37: =A36 -> 45698 | B37: =B36+1 -> 31 | C37: SUBMISSION OF LACKING DOCUMENTS ON THE REQUEST FOR ISSUANCE OF IRRIGATION COVERAGE CERTIFICATION FOR LAND TRANSFER | D37: ENG'G | F37: MCGS
A38: =A37 -> 45698 | B38: =B37+1 -> 32 | C38: DPWH 3RD DEO NOTIFICATION ON THE LOCATION OF FY 2025 GAA PROPOSED PROJECT | D38: ENG'G | F38: MCGS
A39: =A38 -> 45698 | B39: =B38+1 -> 33 | C39: INVITATION LETTER FOR JOINT INSPECTION UNDER CARP-IC WITH DEPT. OF AGRARIAN REFORM REGIONAL OFFICE V & LGU MALINAO, ALBAY - (QUINUARTILAN CIS, CAMALIG, TAGOTOY CIS, MALINAO, ALBAY) | D39: ENG'G | F39: MCGS
A40: =A39 -> 45698 | B40: =B39+1 -> 34 | C40: LandBank of the Philippines Ligao Branch Newly Hired Personnel of NIA ACIMO - opening new payroll accounts for the ff: 1. CALABINES, LYLE KENNETH 2. CANUTAL, EVAN MARIE 3. CELLANO, JHEDSON 4. MANLANGIT, GIO DOMINICK 5. MARBELLA, MARK CHRISTIAN 6. NAVARRO, GERALD 7. ROBAS, MARIA BEATRICE | D40: ENG'G | F40: MCGS | G40: FOR SIGNATURE
A41: =A40 -> 45698 | B41: =B40+1 -> 35 | C41: ITINERARY OF TRAVEL: OMS-TO 202,203 | D41: OMS | F41: VEP | G41: FOR SIGNATURE
A42: =A41 -> 45698 | B42: =B41+1 -> 36 | C42: RENDER WORK ON FEBRUARY 9, 2025 CHRISTIAN LEVY B. LONTAC JR. MARC DAVID OROGO | D42: ADMIN | F42: MCGS | G42: FOR SIGNATURE
A43: =A42 -> 45698 | B43: =B42+1 -> 37 | C43: APPLICATION FOR LEAVE ANGELO MARQUEZ ELMERIO TENDENILLA | D43: ADMIN | F43: MCGS | G43: FOR SIGNATURE
A44: =A43 -> 45698 | B44: =B43+1 -> 38 | C44: TIGER SHIELD INDUSTRIAL CORP. | D44: ADMIN | F44: MCGS
A45: =A44 -> 45698 | B45: =B44+1 -> 39 | C45: INVITATION LETTER FOR TRAINING/SEMINAR FROM PAROA | D45: OMS | F45: BPB
A46: =A45 -> 45698 | B46: =B45+1 -> 40 | C46: ACIMO 5-501-2025-025 MOOE (PHP 2,275,000.00) | D46: FINANCE | F46: MCGS
A47: =A46 -> 45698 | B47: =B46+1 -> 41 | C47: RETTERATION ON THE USE OF CORRECTIVE ACTION REQUEST FORM (CARF) IN ALL PERTINENT TRANSACTIONS AND OR ACTIVITIES | D47: ADMIN | F47: MCGS
A48: =A47 -> 45698 | B48: =B47+1 -> 42 | C48: FINANCIAL REPORTS OCT 2024 (CARP) DEC 31 (LFP) DEC 2024 (LFP) ACCOUNTS PAYABLE (CARP-IC)- DEC 31, 2024 DEC 2024 (CARP -IC) | D48: FINANCE | F48: MCGS | G48: FOR SIGNATURE
A49: =A48 -> 45698 | B49: =B48+1 -> 43 | C49: TEV(JEV ONLY) J.S PENAFIEL FOR DECEMBER 2024 | D49: FINANCE | F49: MCGS | G49: FOR SIGNATURE
A50: =A49 -> 45698 | B50: =B49+1 -> 44 | C50: JEV ONLY- LOAN PAYMENT OF NACARIO JB &1 (YEB & CG) | D50: FINANCE | F50: MCGS | G50: FOR SIGNATURE
A51: =A50 -> 45698 | B51: =B50+1 -> 45 | C51: JEV ONLY BIR REMITTANCE FOR TAX WITHHELD OF COB JOB ORDER FOR THE OCTOBER 16-31, 2024- VARIOUS NAMES | D51: FINANCE | F51: MCGS | G51: FOR SIGNATURE
A52: =A51 -> 45698 | B52: =B51+1 -> 46 | C52: TEV- J. DAYUPAY MONTH OF OCTOBER, NOVEMBER, DECEMBER 2024 | D52: FINANCE | F52: MCGS | G52: FOR SIGNATURE
A53: =A52 -> 45698 | B53: =B52+1 -> 47 | C53: CHECK DISBURSEMENT JOURNAL FUND 501-LFP POWERZONE PETROLEUM PRODUCTS CORP FOR FUEL OIL & LUBRICNTS JANUARY - MARCH 2024 | D53: FINANCE | F53: MCGS | G53: FOR SIGNATURE
A54: =A53 -> 45698 | B54: =B53+1 -> 48 | C54: PAYMENT FOR TYRAINING MATERIALS (POLYVINYL CHLORIDE (PVC) PHP 3,407.15 | D54: FINANCE | F54: MCGS | G54: FOR SIGNATURE
A55: =A54 -> 45698 | B55: =B54+1 -> 49 | C55: TEV- JEV ONLY J.B PENAFLOR AUGUST 1-29, 2024 PHP 1,730.00) | D55: FINANCE | F55: MCGS | G55: FOR SIGNATURE
A56: =A55 -> 45698 | B56: =B55+1 -> 50 | C56: MONETIZATION EARNED LEAVES - CARLITO PONGPONG (Php 131,745.73) MB DACILLO (Php 59, 322.56) RG. LLAVE JR. (Php 26,071.19) | D56: FINANCE | F56: MCGS | G56: FOR SIGNATURE
A57: =A56 -> 45698 | B57: =B56+1 -> 51 | C57: MONETIZATION EARNED LEAVES SA PONTILLAS - 100.511 DAYS E. JACOB - 109.773 DAYS | D57: FINANCE | F57: MCGS | G57: FOR SIGNATURE
A58: =A57 -> 45698 | B58: =B57+1 -> 52 | C58: MCGS CELLPHONE ALLOWANCE FOR THE MONTH OF OCTOBER & NOVEMBER 2024 PHP 3,000 | D58: FINANCE | F58: MCGS | G58: FOR SIGNATURE
A59: =A58 -> 45698 | B59: =B58+1 -> 53 | C59: REMITTANCES : NIA 501 LFP (BIR) Php 83,289.39 | D59: FINANCE | F59: MCGS | G59: FOR SIGNATURE
... A64: =A63 -> 45698 | B64: =B63+1 -> 58 | C64: Reimbursement of APF for the month of May to December 2024 Php 9,614.47 | D64: FINANCE | F64: MCGS | G64: FOR SIGNATURE
A65: ***NOTHING FOLLOWS***
A67: Received, Recorded, Tracked, Disseminated & Filed:
A70: COLEEN M. RASTRULLO | D70: ELLA N. RINGAD | G70: JESSICA V. PEÑAFLOR
A71: Engineering Assistant A | D71: Engineering Assistant A | G71: Information Officer C

Sheet 0211
A1: INCOMING DOCUMENTS TO THE OFFICE OF THE IMO MANAGER
A2: 45699
A3: =TEXT(A2,"DDDD") -> Tuesday
A4: NOTE:
A5: NO. | C5: DOCUMENTS | F5: TO | G5: REMARKS
C6: PARTICULAR | D6: SECTION | E6: TYPE
A7: =A2 -> 45699 | B7: 1 | C7: Travel Order : OMS-TO 204 | D7: OMS | F7: MCGS | G7: For signature
A8: =A7 -> 45699 | B8: =B7+1 -> 2 | C8: To COA: Report of Accountability for Accountable Forms for December 2024 & Jnauary 2025 | D8: FINANCE | F8: MCGS | G8: For signature
A9: =A8 -> 45699 | B9: =B8+1 -> 3 | C9: Gate Pass Vcls: 233-2025 Travel Order: OMS-TO205,206 | D9: OMS | F9: MCGS | G9: For signature
A10: =A9 -> 45699 | B10: =B9+1 -> 4 | C10: Cheque & Attachments: Jomer L. Beo - 4,404.00 TEV August 26-29, 2024 | D10: FINANCE | F10: MCGS | G10: For signature
A11: =A10 -> 45699 | B11: =B10+1 -> 5 | C11: Cheque & Attachments: Joshua A. Lumbao - 4,404.00 TEV August 26-29, 2024 | D11: FINANCE | F11: MCGS | G11: For signature
A12: =A11 -> 45699 | B12: =B11+1 -> 6 | C12: Cheque & Attachments: Elizabeth J. Jacob - 1,866.00 TEV November 2024 | D12: FINANCE | F12: MCGS | G12: For signature
A13: =A12 -> 45699 | B13: =B12+1 -> 7 | C13: Cheque & Attachments: Ian Feliciano III P. Berdin - 3,760.00 TEV August 2024 | D13: FINANCE | F13: MCGS | G13: For signature
A14: =A13 -> 45699 | B14: =B13+1 -> 8 | C14: Cheque & Attachments: Onofre B. Gonzales - 80,513.39 Monetization of Earned Leaves -86.864 days | D14: FINANCE | F14: MCGS | G14: For signature
A15: =A14 -> 45699 | B15: =B14+1 -> 9 | C15: Cheque & Attachments: Richard S. Nacario - 15,771.07 Monetization of Earned Leaves -19.528 days | D15: FINANCE | F15: MCGS | G15: For signature
A16: =A15 -> 45699 | B16: =B15+1 -> 10 | C16: Cheque & Attachments: Emeyer Gasoline Station - 47,099.96 Gasoline consumption for February 2024 | D16: FINANCE | F16: MCGS | G16: For signature
A17: =A16 -> 45699 | B17: =B16+1 -> 11 | C17: Authority to Render Overtime Services: 1. RA Paraiso (02/3-9/2025) 2. JA Siguenza (02/3-9/2025) | D17: ENG'G | F17: MCGS | G17: For signature
A18: =A17 -> 45699 | B18: =B17+1 -> 12 | C18: In-House Inspection Report of San Agustin CIS AL-EGPIPSOL-003-24INF | D18: ENG'G | F18: MCGS | G18: For signature
A19: =A18 -> 45699 | B19: =B18+1 -> 13 | C19: Request for ICC 1. Maron B. Borromeo 2. Freddie Pelantic | D19: ENG'G | F19: MCGS | G19: For signature
... A38: =A37 -> 45699 | B38: =B37+1 -> 32 | C38: Payroll & attachments (Nasisi - Bahamas IA) - PAID 1. D. Almares & 9 (November 1-15, 2024) | D38: FINANCE | F38: MCGS | G38: For signature
A39: =A38 -> 45699 | B39: =B38+1 -> 33 | C39: Personnel Locator Slip: 2/11/25, 1:30 pm, personal, JP Roncesvalles | D39: ENG'G | F39: MCGS
A40: =A39 -> 45699 | B40: =B39+1 -> 34 | C40: Travel Order : OMS-TO 207 | D40: OMS | F40: MCGS | G40: For signature
A41: =A40 -> 45699 | B41: =B40+1 -> 35 | C41: DPCR Rating of MCGS (July to December 2024) | D41: ADMIN | F41: MCGS | G41: For signature
A42: =A41 -> 45699 | B42: =B41+1 -> 36 | C42: Certificate of Appearance 1. Katrina A. Ferrer 2. Avelyn U. Nocellado 3. Charmain O. Abiog | D42: ADMIN | F42: MCGS | G42: For signature
A43: =A42 -> 45699 | B43: =B42+1 -> 37 | C43: Cheque & Attachments (Remittances) 1. GSIS (Php 20,473.93) 2. GSIS (Php 3,177.20) 3. GSIS (Php 11,227.31) 4. GSIS (Php 46,121.91) 5. GSIS (Php 89,022.03) 6. GSIS (Php 208,473.93) | D43: FINANCE | F43: MCGS | G43: For signature
A44: =A43 -> 45699 | B44: =B43+1 -> 38 | C44: Travel Order : ENG-TO 265, 266, 267 | D44: ENG'G | F44: MCGS | G44: For signature
A45: =A44 -> 45699 | B45: =B44+1 -> 39 | C45: Letter to : Hon. Sheryl C. Bilo (Municipal Mayor, Malinao) Hon. Carlos Irwin G. Baldo Jr. (Municipal Mayor, Camalig) Rep. Joey Sarte Salceda (Albay 2nd District Representative) | D45: OMS | F45: MCGS | G45: For signature
A46: =A45 -> 45699 | B46: =B45+1 -> 40 | C46: Gate pass Vcls: 234, 235, 236, 237-2025 RIS : 122, 123-2025 Transpo Req. : 181, 186, 185, 184, 183, 182-2025 | D46: OMS | F46: MCGS | G46: For signature
A47: =A46 -> 45699 | B47: =B46+1 -> 41 | C47: Travel Order : OMS-TO 208 | D47: OMS | F47: MCGS | G47: For signature
A48: =A47 -> 45699 | B48: =B47+1 -> 42 | C48: Travel Order : OMS-TO 209 | D48: OMS | F48: MCGS | G48: For signature
A49: =A48 -> 45699 | B49: =B48+1 -> 43 | C49: Payroll & Attachments RG. Aycardo & 5 (January 16-31, 2025) - Php 60,893.94 | D49: ADMIN | F49: MCGS | G49: For signature
A50: =A49 -> 45699 | B50: =B49+1 -> 44 | C50: Payroll & Attachments K.A Almiñana & 8 (January 16-31, 2025) - Php 65, 907.88 | D50: ADMIN | F50: MCGS | G50: For signature
A51: =A50 -> 45699 | B51: =B50+1 -> 45 | C51: Payroll & Attachments GNJ Jacob (January 16-31, 2025) - Php 8,950.03 | D51: ADMIN | F51: MCGS | G51: For signature
... A58: =A57 -> 45699 | B58: =B57+1 -> 52 | C58: 2nd & Final Billing Repair/Restoration of LIBJO CIS CAT-RREIS-009-23INF | D58: ENG'G | F58: MCGS | G58: For signature
A59: ***NOTHING FOLLOWS***
A61: Received, Recorded, Tracked, Disseminated & Filed:
A64: COLEEN M. RASTRULLO | D64: ELLA N. RINGAD | G64: JESSICA V. PEÑAFLOR
A65: Engineering Assistant A | D65: Engineering Assistant A | G65: Information Officer C

Sheet 0212
A1: INCOMING DOCUMENTS TO THE OFFICE OF THE IMO MANAGER
A2: 45700
A3: =TEXT(A2,"DDDD") -> Wednesday
A4: NOTE: | B4: MCGS & other signatories on official business from 10:45am onwards. OIC: LFCP (8:00 to 8:57), MCGS onwards
A5: NO. | C5: DOCUMENTS | F5: TO | G5: REMARKS
C6: PARTICULAR | D6: SECTION | E6: TYPE
A7: =A2 -> 45700 | B7: 1 | C7: TRANSMITTAL TO COA: JEV FOR FUND 501-LFP OCT. 16-31,2024 | D7: FINANCE | F7: LFCP | G7: For signature
A8: =A7 -> 45700 | B8: =B7+1 -> 2 | C8: Itinerary of Travel : OMS-TO 210, ENG-TO 270 | D8: OMS | F8: LFCP | G8: For signature
A9: =A8 -> 45700 | B9: =B8+1 -> 3 | C9: Travel Order : ENG-TO 269 | D9: ENG'G | F9: LFCP | G9: For signature
A10: =A9 -> 45700 | B10: =B9+1 -> 4 | C10: Gate Pass Vcls: 239, 238-2025 RIS : 124-2025 | D10: OMS | F10: LFCP | G10: For signature
A11: =A10 -> 45700 | B11: =B10+1 -> 5 | C11: Seminar Proposal for Women's Month Celebration in connection with Gender & Development "Empowering Women : Understanding the Female Reproductive System and Its Care" | D11: ADMIN | F11: MCGS | G11: For signature
A12: =A11 -> 45700 | B12: =B11+1 -> 6 | C12: Transmittal to COA : Report of Accountability for Accountable Forms for the month of September 2024 | D12: FINANCE | F12: MCGS | G12: For signature
A13: =A12 -> 45700 | B13: =B12+1 -> 7 | C13: Gate Pass - Vcls : 240-2025 RIS : 125-2025 Travel Order : OMS-TO 211 | D13: OMS | F13: MCGS | G13: For signature
A14: =A13 -> 45700 | B14: =B13+1 -> 8 | C14: Sent thru mailing envelope : AIA Philippines Life and General Insurance Company Inc. (received 2/12/25) Government Service Insurance Systems - Legazpi Branch (received 2/12/25) | D14: ADMIN | F14: MCGS | G14: For signature
A15: =A14 -> 45700 | B15: =B14+1 -> 9 | C15: Personnel Locator Slip : 2/12/2025, 9:30 am, Official, JPR Papa | D15: FINANCE | F15: MCGS | G15: For signature
A16: =A15 -> 45700 | B16: =B15+1 -> 10 | C16: Attested appointment of Ms. Conchita Reyes | D16: ADMIN | F16: MCGS | G16: For signature
A17: =A16 -> 45700 | B17: =B16+1 -> 11 | C17: To CSIMO : Engr. Baynas Transmittal Only - for signature of Various Documents | D17: ENG'G | F17: MCGS | G17: For signature
A18: =A17 -> 45700 | B18: =B17+1 -> 12 | C18: Travel Order : OMS-TO 212 | D18: OMS | F18: MCGS | G18: For signature
A19: =A18 -> 45700 | B19: =B18+1 -> 13 | C19: Letter to DPWH 3rd District Engineering Office on request for relocation of FY 2025 Proposed Slope Protection Works | D19: ENG'G | F19: MCGS | G19: For signature
... A29: =A28 -> 45700 | B29: =B28+1 -> 23 | C29: GATE PASS: 214-2025 | D29: OMS | F29: MCGS | G29: For signature
A30: =A29 -> 45700 | B30: =B29+1 -> 24 | C30: Request for Extension/Creation of Job order Positions (1st Semester CY 2025) | D30: ADMIN
A31: =A30 -> 45700 | B31: =B30+1 -> 25 | C31: Received Status of Application of Engr. Lech Fidel C. Pante | D31: ADMIN | F31: MCGS | G31: For signature
A32: =A31 -> 45700 | B32: =B31+1 -> 26 | C32: From COA: Statement of Audit Suspensions, Disallowances and Charges (SASDC) Notice of Settlement of Suspension/Disallowances/Charge (NSSDC) | D32: FINANCE | F32: MCGS | G32: For signature
A33: =A32 -> 45700 | B33: =B32+1 -> 27 | C33: Trasmittal to COA : Journal Entry Vouchers (Adjustments with Supporting Documents) FUND - 501 LFP & COB | D33: FINANCE | F33: MCGS | G33: For signature
A34: =A33 -> 45700 | B34: =B33+1 -> 28 | C34: Personnel Locator Slip : 2/12/2025, 1:00pm, DRP, Pagal | D34: ADMIN | F34: MCGS | G34: For signature
A35: =A34 -> 45700 | B35: =B34+1 -> 29 | C35: CHEQUE with JEV: FAW payroll Dec. 2024 Alamrez & 9 PHP 77,727.10 | D35: FINANCE | F35: MCGS | G35: For signature
A36: =A35 -> 45700 | B36: =B35+1 -> 30 | C36: PERSONNEL LOCATOR SLIP: 2/12/24, 2:00pm, OFFICIAL, VM. MANLANGIT | D36: FINANCE | F36: MCGS | G36: For signature
A37: =A36 -> 45700 | B37: =B36+1 -> 31 | C37: TRAVEL ORDER: OMS-TO0215 & OMS-TO0214 | D37: OMS | F37: MCGS | G37: For signature
A38: =A37 -> 45700 | B38: =B37+1 -> 32 | C38: Gate Pass-Vcls : 242, 243 | D38: OMS | F38: MCGS | G38: For signature
A39: =A38 -> 45700 | B39: =B38+1 -> 33 | C39: Approved Turnover Documents (Albay) 1. San Francisco RIS | D39: ADMIN | F39: MCGS | G39: APPROVED
A40: =A39 -> 45700 | B40: =B39+1 -> 34 | C40: Proposal for the Conduct of Field Investigation for the FSDE of CSJ RIS under Modernization Program | D40: ENG'G | F40: MCGS | G40: For signature
A41: =A40 -> 45700 | B41: =B40+1 -> 35 | C41: Travel Order : ENG-TO 271 | D41: ENG'G | F41: MCGS | G41: VOID
A42: =A41 -> 45700 | B42: =B41+1 -> 36 | C42: Letter to DPWH Regional Office V re: Final List projects under NIA-DPWH Convergence | D42: ENG'G | F42: MCGS | G42: For signature
... A44: =A43 -> 45700 | B44: =B43+1 -> 38 | C44: Cheques & Attachments : 1. Roldolfo G. Llave Jr. (Php 26,071.19 2. Milany B. Dacillo (Php 59,322.56) 3. Elizabeth J. Jacob (Php 121,347.92) 4. Carlito C. Pongpong (Php 131,745.73) 5. Segfrido A. Pontillas (Php 111,129.30) | D44: FINANCE | F44: MCGS | G44: For signature
A45: =A44 -> 45700 | B45: =B44+1 -> 39 | C45: 4th Tracer re: Submission of Pre Construction Conference documents in all projects for CY 2023, CY 2024 and CY 2025 (Generated, Resto, Repair/Rehab, roads) | D45: ENG'G
A46: =A45 -> 45700 | B46: =B45+1 -> 40 | C46: Gate Pass Vcls : 244, 245,246,247, 248-2025 RIS : 126, 127, 128-2025 Transpo Req. : 188, 189, 190, 191, 192, 193-2025, 129-2025 | D46: OMS | F46: MCGS | G46: For signature
A47: =A46 -> 45700 | B47: =B46+1 -> 41 | C47: Travel Order : FIN-TO 004 | D47: FINANCE | F47: MCGS | G47: For signature
A48: =A47 -> 45700 | B48: =B47+1 -> 42 | C48: Resolution No. 1 s. 2025 "A resolution requesting the NIA ACIMO to restore the Siphon which was damaged by Typhoon Kristine to irrigate the 132 hectares of Farmlots of Nagas Maramba Communal Irrigation System" | D48: ENG'G | F48: MCGS
A49: =A48 -> 45700 | B49: =B48+1 -> 43 | C49: Post Qualification Evaluation 1. 24FK0106 - Muntopar Builders Corp. | D49: BAC | F49: MCGS
A50: =A49 -> 45700 | B50: =B49+1 -> 44 | C50: [FORWARDED FROM REGIONAL OFFICE] ARTA Client Satisfaction Survey | D50: ADMIN | F50: MCGS
A51: =A50 -> 45700 | B51: =B50+1 -> 45 | C51: Reiteration for the Submission of Accomplishment reports of Heavy Equipment, Solar Porjects and other Equipment related reports | D51: OMS | F51: MCGS
A52: =A51 -> 45700 | B52: =B51+1 -> 46 | C52: Payroll & Wages : R. Llave Jr. (December 1-15, 2024) - Php 8,062.69 | D52: ADMIN | F52: MCGS | G52: For signature
A53: =A52 -> 45700 | B53: =B52+1 -> 47 | C53: Payroll & Wages : JL Agripa & 9 (November 1-15, 2024) | D53: ADMIN | F53: MCGS | G53: For signature
A54: =A53 -> 45700 | B54: =B53+1 -> 48 | C54: Payroll & Wages : M. Alvares & 4 (January 16-31, 2025) | D54: ADMIN | F54: MCGS | G54: For signature
A55: =A54 -> 45700 | B55: =B54+1 -> 49 | C55: Payroll & Wages : V. Peralta (November 1-15, 2025) | D55: ADMIN | F55: MCGS | G55: For signature
A56: =A55 -> 45700 | B56: =B55+1 -> 50 | C56: Payroll & Wages : MC Azutea & 6 (November 1-15, 2025) | D56: ADMIN | F56: MCGS | G56: For signature
A57: =A56 -> 45700 | B57: =B56+1 -> 51 | C57: Payroll & Wages : JB Dayupay & 12 (November 1-15, 2025) | D57: ADMIN | F57: MCGS | G57: For signature
A58: ***NOTHING FOLLOWS***
A60: Received, Recorded, Tracked, Disseminated & Filed:
A63: COLEEN M. RASTRULLO
A64: Engineering Assistant A

Sheet 0213
A1: INCOMING DOCUMENTS TO THE OFFICE OF THE IMO MANAGER
A2: 45701
A3: =TEXT(A2,"DDDD") -> Thursday
A4: NOTE:
A5: NO. | C5: DOCUMENTS | F5: TO | G5: REMARKS
C6: PARTICULAR | D6: SECTION | E6: TYPE
A7: =A2 -> 45701 | B7: 1 | C7: Authority to render Overtime Service (Job Order ) 1. DMC Mayor & 6 others (February 10-14, 2025) | D7: FINANCE | F7: MCGS | G7: For signature
A8: =A7 -> 45701 | B8: =B7+1 -> 2 | C8: Proposal : 1st Semester System Management Committee Meeting w/ attached Attendance & Minutes | D8: OMS | F8: MCGS | G8: For signature
A9: =A8 -> 45701 | B9: =B8+1 -> 3 | C9: Gate Pass Mtrls : 026-2025 | D9: OMS | F9: MCGS | G9: For signature
A10: =A9 -> 45701 | B10: =B9+1 -> 4 | C10: Gate Pass Vhcls: 249-2025 RIS : 130-2025 | D10: OMS | F10: MCGS | G10: For signature
A11: =A10 -> 45701 | B11: =B10+1 -> 5 | C11: Weekly Accomplishment Report as of February 7, 2025 1. San Agustin CIS (AL-EGPIPSOL-003-24INF) 2. Right Quinale CIS (AL-EGPIPSOL-003-24INF) | D11: ENG'G | F11: MCGS | G11: For signature
A12: =A11 -> 45701 | B12: =B11+1 -> 6 | C12: Travel Order : OMS-TO 215 | D12: OMS | F12: MCGS | G12: For signature
A13: =A12 -> 45701 | B13: =B12+1 -> 7 | C13: Travel Order : ENG-TO 272 | D13: ENG'G | F13: MCGS | G13: For signature
A14: =A13 -> 45701 | B14: =B13+1 -> 8 | C14: To Region : (Transmittal) Final Billing of QRF Projects 2017 NDRRMF-AL-121-17 CPR Construction & Supply. | D14: ENG'G | F14: MCGS | G14: For signature
A15: =A14 -> 45701 | B15: =B14+1 -> 9 | C15: 1. Mobilization of Backhoe for Desilting of Main Canal at South Quinale RIS (Oas & Libon) 2. Mobilization of Backhoe for Cofferdamming and Repair of Rubber Tube at Cabilogan-San Juan RIS (Ligao & Oas) | D15: ENG'G | F15: MCGS | G15: For signature
A16: =A15 -> 45701 | B16: =B15+1 -> 10 | C16: Notice of Meeting : Engineering ( February 14, 2025) Institutional Development Unit (February 14, 2025) | F16: MCGS | G16: For signature, engg & insti
A17: =A16 -> 45701 | B17: =B16+1 -> 11 | C17: Personnel Locator Slip : 2/13/2025, 11:00am, Personal, MB Robas 2/13/2025, 11:00am, Personal, EMF Canutal | D17: FINANCE | F17: MCGS | G17: For signature
A18: =A17 -> 45701 | B18: =B17+1 -> 12 | C18: Travel Order : OMS-TO 216 | D18: OMS | F18: MCGS | G18: For signature
A19: =A18 -> 45701 | B19: =B18+1 -> 13 | C19: Purchase Request : 1. PR No. : 2025-01-005 2. PR. No. : 2025-02-0015 3. PR NO. : 2025-01-0010 | D19: ADMIN | F19: MCGS | G19: For signature
A20: =A19 -> 45701 | B20: =B19+1 -> 14 | C20: To Region : Request for Extension/Creation of Job Order Positions (January to June 2025) | D20: ADMIN | F20: MCGS | G20: For signature
A21: =A20 -> 45701 | B21: =B20+1 -> 15 | C21: Travel Order : ENG-TO 273 | D21: ENG'G | F21: MCGS | G21: For signature
A22: =A21 -> 45701 | B22: =B21+1 -> 16 | C22: Application for Leave : 1. IFP. Berdin ( 2/11/25) 2. MLl, Salem (2/4/25) 3. AP Francia (10/28-29/2025) 4. AP Francia (11/18/2025) | D22: ADMIN | F22: MCGS | G22: For signature
A23: =A22 -> 45701 | B23: =B22+1 -> 17 | C23: Inspection Report for San Francisco Gabon CIS Polangui, Albay | D23: ENG'G | F23: MCGS | G23: For signature
A24: =A23 -> 45701 | B24: =B23+1 -> 18 | C24: To DPWH 1st, 2nd & 3rd Deo : Follow up letter re : Final list of Projects under NIA DPWH Covergence for FY 2025 | D24: ENG'G | F24: MCGS | G24: For signature
A25: =A24 -> 45701 | B25: =B24+1 -> 19 | C25: Authority to render Overtime Service (Job Order ) 1. AMD Balingasa (2/8/25) 2. MA, Robledo (2/8/25) 3. MB Dacillo (2/9/25) Travel Order : OMS TO 217 | D25: OMS | F25: MCGS | G25: For signature
A26: =A25 -> 45701 | B26: =B25+1 -> 20 | C26: Gate Pass Vcls : 250, 251-2025 | D26: OMS | F26: MCGS | G26: For signature
A27: =A26 -> 45701 | B27: =B26+1 -> 21 | C27: Payroll & Wages : GNJ Jacob (Php 6,515.28) - 11/1-15/24 D. Manlangit (Php 64,471.22) - 11/1-15/24 J Bombita & 2 (Php 2,945.40) - 10/16-31/24 R. Mariñas (Php 2,281.79) - 10/16-31/24 V. Peralta (Php 1,874.94) - 10/16-31/24 RC Aydalla (Php 3,021.35) - 12/16-31/24 | D27: ADMIN | F27: MCGS | G27: For signature
A28: =A27 -> 45701 | B28: =B27+1 -> 22 | C28: Gate Pass Vcls : 255-2025 | D28: ADMIN | F28: MCGS | G28: For signature
... A38: =A37 -> 45701 | B38: =B37+1 -> 32 | C38: To Region : Evaluation of Training Effectiveness | D38: ADMIN | F38: MCGS | G38: For signature
A39: =A38 -> 45701 | B39: =B38+1 -> 33 | C39: LGU Polangui: Regular Session on February 17, 2025, 9:00am New SB Session Hall | D39: ADMIN
A40: =A39 -> 45701 | B40: =B39+1 -> 34 | C40: Travel Order : ENG-TO 273 | D40: ENG'G | F40: MCGS | G40: For signature
A41: =A40 -> 45701 | B41: =B40+1 -> 35 | C41: IPCR of Ms. Vida E. Pitallano (Rating July to December 2024) | D41: FINANCE | F41: MCGS | G41: For signature
A42: =A41 -> 45701 | B42: =B41+1 -> 36 | C42: Application for Leave : 1. VE, Pitallano (2/1/2025) | D42: FINANCE | F42: MCGS | G42: For signature
A43: ***NOTHING FOLLOWS***
A45: Received, Recorded, Tracked, Disseminated & Filed:
A48: COLEEN M. RASTRULLO
A49: Engineering Assistant A

Sheet 0214
A1: INCOMING DOCUMENTS TO THE OFFICE OF THE IMO MANAGER
A2: 45702
A3: =TEXT(A2,"DDDD") -> Friday
A4: NOTE:
A5: NO. | C5: DOCUMENTS | F5: TO | G5: REMARKS
C6: PARTICULAR | D6: SECTION | E6: TYPE
A7: =A2 -> 45702 | B7: 1 | C7: Gate Pass Vcls : 256-2025 RIS : 131-2025 Daily Driver's Trip Ticket : 083-2025 | D7: ENG'G | F7: MCGS | G7: for signature
A8: =A7 -> 45702 | B8: =B7+1 -> 2 | C8: Personnel Locator Slip : 2/14/25, 9:00, Official, JPR Papa | D8: OMS | F8: MCGS | G8: for signature
A9: =A8 -> 45702 | B9: =B8+1 -> 3 | C9: Authority to render Overtime services: 1. LMB, Olivera ( 2/6&7/2025) 2. JAD Juarez (2/1/25) 3. C Petilla (2/15/25) 4. JAD Juarez (2/3,5,6/25) 5. JA Dolz (2/8/2025) | D9: ENG'G | F9: MCGS | G9: for signature
A10: =A9 -> 45702 | B10: =B9+1 -> 4 | C10: Cash Advance named to VM Manlangit (FAW payroll) : 1. REALCO & 9 (11/1-15/24) | D10: FINANCE | F10: MCGS | G10: for signature
A11: =A10 -> 45702 | B11: =B10+1 -> 5 | C11: TEV's : (1) 1. RG. Aycardo (Dec. 2024) - Php 2,550.00 2. NB Nash ( July 2024) - Php 1,320.00 3. NB Nash (Aug 2024) - Php 1,260.00 4. JR. Roncesvalles (January to June 2024) - Php 6,540.00 | D11: FINANCE | F11: MCGS | G11: for signature
A12: =A11 -> 45702 | B12: =B11+1 -> 6 | C12: Report of Collection & Deposits August 1-27, 2024 (Duplicate & Triplicate) | D12: FINANCE | F12: MCGS | G12: for signature
A13: =A12 -> 45702 | B13: =B12+1 -> 7 | C13: Report of Collection & Deposits November 28 to December 2024 (Duplicate & Triplicate) | D13: FINANCE | F13: MCGS | G13: for signature
A14: =A13 -> 45702 | B14: =B13+1 -> 8 | C14: Report of Collection & Deposits October 28 to November 27, 2024 (Duplicate & Triplicate) | D14: FINANCE | F14: MCGS | G14: for signature
A15: =A14 -> 45702 | B15: =B14+1 -> 9 | C15: Report of Collection & Deposits August 28 to September 27, 2024 (Duplicate & Triplicate) | D15: FINANCE | F15: MCGS | G15: for signature
A16: =A15 -> 45702 | B16: =B15+1 -> 10 | C16: Cash Advance named to VM Manlangit (FAW payroll) : 1. REALCO & 9 (11/1-15/24) | D16: FINANCE | F16: MCGS | G16: for signature
A17: =A16 -> 45702 | B17: =B16+1 -> 11 | C17: Daily Driver's Trip Ticket : 084, 085, 086, 087, 088, 089, 090, 091, 092, 093, 094, 095-2025 Gate Pass Mtls : 027-2025 | D17: OMS | F17: MCGS | G17: for signature
A18: =A17 -> 45702 | B18: =B17+1 -> 12 | C18: Personnel Locator Slip : 2/14/25, 10:30am, Official, DP Vibar | D18: ENG'G | F18: MCGS | G18: for signature
A19: =A18 -> 45702 | B19: =B18+1 -> 13 | C19: To City Health Office : Request for Resource Speaker for Women's Month Seminar | D19: ADMIN | F19: MCGS | G19: for signature
... A37: =A36 -> 45702 | B37: =B36+1 -> 31 | C37: Report on Flooded/Submerge Farm Lots in Cabilogan-San Juan RIS | D37: ENG'G | F37: MCGS | G37: for signature
A38: =A37 -> 45702 | B38: =B37+1 -> 32 | C38: To Contractor (Hi Tone): Fast Tracking of Rectification Works & Contract Payment | F38: MCGS | G38: for signature
A39: =A38 -> 45702 | B39: =B38+1 -> 33 | C39: Personnel Locator Slip : 2/14/2025, 2:00pm, Official, AB Calpe | D39: ADMIN | F39: MCGS | G39: for signature
A40: =A39 -> 45702 | B40: =B39+1 -> 34 | C40: Application for Leave & CTO : 1. BP, Balingasa (2/10,11,12/25) 2. MB Dacillo (2/13-14/25) 3. SA Pontillas (2/14/25) 4. NS Reodique (11/4/24) 5. VM Manlangit (2/13/25) CTO 1. MDS, Belgado (12/17/24) | D40: ADMIN | F40: MCGS | G40: for signature
A41: =A40 -> 45702 | B41: =B40+1 -> 35 | C41: TEV's : (2) 1. FBJ Juarez (October 1-31, 2024) - Php 2,860.00 2. E. Jacob (October 2024) - Php 2,000.00 3. GN. Jacob (November 2024) - Php 480.00 4. IF Berdin (June 5-28, 2024) -Php 3,350.00 5. IF Berdin (May 2024) Php 2,510.00 6. C. Reyes (July 2024) - Php 3,008.00 7. AV Marquez (Aug. 2024) Php 5,688.00 8. J. Beo (December 5-7, 2025) Php 1,350.00 9. J.S Peñafiel (November 5-29, 2024) Php 1,980.00 10. J. Olaviaga (April-May 2024) Php 3,450.00 11. J. Completo (Aug-December 2024) Php 5,180.00 12. J.B Peñaflor (Sept. 3-19, 2024) Php 1,800.00 13. MB Dacillo (April 2-23, 2024) Php 1,107.00 14. JB. Peñaflor (Feb. December 2024) Php 3,900.00 15. J. Torio (Dec. 5-7, 2024) Php 1,350.00 | D41: FINANCE | F41: MCGS | G41: for signature
A42: =A41 -> 45702 | B42: =B41+1 -> 36 | C42: Electric Consumption : ALECO (Php 26,094.66) | D42: ENG'G | F42: MCGS | G42: for signature
A43: =A42 -> 45702 | B43: =B42+1 -> 37 | C43: To COA : Financial Reports for the month of July 2024 (Fund 501-Corporate Operating Fund (COB) | D43: FINANCE | F43: MCGS | G43: for signature
A44: =A43 -> 45702 | B44: =B43+1 -> 38 | C44: Purchase Order : Payment for GD's Catering Services for Meals - Seminar/Workshop of Balasbas IA Inc. (December 19-20, 2024) Php 16, 000.00 | D44: FINANCE | F44: MCGS | G44: for signature
A45: =A44 -> 45702 | B45: =B44+1 -> 39 | C45: Gate Pass Vcls : 258-2025 RIS : 132-2025 Daily Trip Ticket : 096-2025 | D45: OMS | F45: MCGS | G45: for signature
A46: =A45 -> 45702 | B46: =B45+1 -> 40 | C46: Travel Order : OMS-TO 218 | D46: OMS | F46: MCGS | G46: for signature
A47: =A46 -> 45702 | B47: =B46+1 -> 41 | C47: Accounting Copies (3) : (JEV only for signature) 3rd & Final Billing Repair/Rehabilitation of Gogon CIS 3RB Construction & Supply Php 1,067,496.25 | D47: FINANCE | F47: MCGS | G47: for signature
A48: =A47 -> 45702 | B48: =B47+1 -> 42 | C48: Application for Leave & CTO : 1. DA Rebadajo (2/10-12/25) 2. RA Paraiso ( 1/3/25) | D48: ADMIN | F48: MCGS | G48: for signature
A49: =A48 -> 45702 | B49: =B48+1 -> 43 | C49: Travel order : ENG-TO 277 | D49: ENG'G | F49: MCGS | G49: for signature
A50: =A49 -> 45702 | B50: =B49+1 -> 44 | C50: Gate Pass Vhcls : 259, 260-2025 RIS : 133, 134, 097-2025 Daily Drivers Trip Ticket : 097, 098, 206-2025 | D50: OMS | F50: MCGS | G50: for signature
... A53: =A52 -> 45702 | B53: =B52+1 -> 47 | C53: From Region : Joint Inspection Report of Mabalod-Tandarura CY 2018 SIP-AL-082-18 HI TONE CONST. & DEVT. CORP | D53: ENG'G | F53: MCGS | G53: for signature
A54: ***NOTHING FOLLOWS***
A57: Received, Recorded, Tracked, Disseminated & Filed:
A59: COLEEN M. RASTRULLO
A60: Engineering Assistant A

Sheet 0217
A1: INCOMING DOCUMENTS TO THE OFFICE OF THE IMO MANAGER
A2: 45705
A3: =TEXT(A2,"DDDD") -> Monday
A4: NOTE: | B4: MCGS on official business from 1PM onwards. OIC: BPB
A5: NO. | C5: DOCUMENTS | F5: TO | G5: REMARKS
C6: PARTICULAR | D6: SECTION | E6: TYPE
A7: =A2 -> 45705 | B7: 1 | C7: Travel Order : ENG-TO 299 Gate Pass Vcls : 264-2025 | D7: ENG'G | F7: MCGS | G7: for signature
A8: =A7 -> 45705 | B8: =B7+1 -> 2 | C8: Itinerary of Travel : ENG-TO 298 OMS-TO 220 | D8: ENG'G | F8: MCGS | G8: for signature
A9: =A8 -> 45705 | B9: =B8+1 -> 3 | C9: Travel Order : ENG-TO 300 | D9: ENG'G
A10: =A9 -> 45705 | B10: =B9+1 -> 4 | C10: Itinerary of Travel : OMS-TO 221-226 Travel Order : OMS-TO 228 | D10: OMS | F10: MCGS | G10: for signature
A11: =A10 -> 45705 | B11: =B10+1 -> 5 | C11: Inspection Report of damaged farm to market road in TAPSIA (Lateral D) | D11: OMS | F11: MCGS | G11: for signature
A12: =A11 -> 45705 | B12: =B11+1 -> 6 | C12: Itinerary: ENG-TO 301 | D12: OMS | F12: MCGS | G12: for signature
A13: =A12 -> 45705 | B13: =B12+1 -> 7 | C13: Authority to Render Overtime Services: 1. PJ Rebeta & 3 (2/15/25) 2. MA Robledo & 1 (2/15/25) | D13: ENG'G | F13: MCGS | G13: for signature
A14: =A13 -> 45705 | B14: =B13+1 -> 8 | C14: Itinerary of Travel : ENG-TO 278 - 297, OMS-TO 230 Gate Pass Vcls : 268, 263,265,266,267,262-2025 RIS: 139, 138, 137,135,136-2025 Transpo Req. : 209, 207,210,211, 208-2025 | D14: OMS | F14: MCGS | G14: for signature
A15: =A14 -> 45705 | B15: =B14+1 -> 9 | C15: Travel Order : OMS-TO 219 Authority to render Overtime services with attachments : 1. AMD Balingasa (2/15/25) | D15: OMS | F15: MCGS | G15: for signature
A16: =A15 -> 45705 | B16: =B15+1 -> 10 | C16: Gate Pass Mtrls : 028-2025 | D16: OMS | F16: MCGS | G16: for signature
A17: =A16 -> 45705 | B17: =B16+1 -> 11 | C17: Personnel Locator Slip : 2/17/25, 1:00pm, Official, JA Amados 2/17/25, 1:00pm, Official, JDC Berzuela | D17: OMS | F17: MCGS | G17: for signature
A18: =A17 -> 45705 | B18: =B17+1 -> 12 | C18: Itinerary of Travel : OMS-TO 229, 227 ENG-TO 302 | D18: OMS | F18: MCGS | G18: for signature
A19: =A18 -> 45705 | B19: =B18+1 -> 13 | C19: SALN as of December 31, 2024 1. DMC Mayor & 5 | D19: ADMIN | F19: MCGS | G19: for signature
A20: =A19 -> 45705 | B20: =B19+1 -> 14 | C20: To COA : Various Financial Reports under COB Fund 1. August 2024 2. September 2024 3. October 2024 | D20: FINANCE | F20: MCGS | G20: for signature
A21: =A20 -> 45705 | B21: =B20+1 -> 15 | C21: Resubmission/Revised: Purchased Order from Tracking No. 21425038 | F21: MCGS | G21: for signature
A22: =A21 -> 45705 | B22: =B21+1 -> 16 | C22: Itinerary of Travel ENG-TO 303, 304, 305 | F22: MCGS | G22: for signature
A23: =A22 -> 45705 | B23: =B22+1 -> 17 | C23: To COA :Jornal Entry Vouchers (JEV) 1. August 1-27, 2024 for Fund 501-COB 2. August 28-Sept. 2024 3. September 29 - Oct. 28, 2024 4. Oct. 28 - November 27, 2024 5. November 28 to December 31, 2024 | F23: MCGS | G23: for signature
A24: =A23 -> 45705 | B24: =B23+1 -> 18 | C24: Travel Order: ADM 013 | F24: MCGS | G24: for signature
A25: =A24 -> 45705 | B25: =B24+1 -> 19 | C25: Travel Order : ADM TO 014, 015 | F25: MCGS | G25: for signature
A26: =A25 -> 45705 | B26: =B25+1 -> 20 | C26: 2nd & Final Progress Billing Repair/Restoration of Caningag CIS CAT-RREIS-003-23INF CPR Const. & Supply | F26: MCGS | G26: for signature
A27: =A26 -> 45705 | B27: =B26+1 -> 21 | C27: 10 % Retention Claims BUHI CIS CAT-RREIS-001-23INF Hi Tone Const. & Devt. Corp | F27: MCGS | G27: for signature
A28: =A27 -> 45705 | B28: =B27+1 -> 22 | C28: 10& Retention Claims ALIBUAG CIS CAT-RREIS-002-23INF Hi Tone Const. & Devt. Corp | F28: MCGS | G28: for signature
A29: =A28 -> 45705 | B29: =B28+1 -> 23 | C29: 1st Progress Billing Repair/Restoration of Panganiban CIS CAT-REPCIS-008-24INF JMREO Const. & Services | F29: MCGS | G29: for signature
A30: =A29 -> 45705 | B30: =B29+1 -> 24 | C30: From CARP-Irrigation Component: Arrival Notification of Personnel at Bicol Interational Airport | I30: 45695
A31: =A30 -> 45705 | B31: =B30+1 -> 25 | C31: Resolution 1 s. 2024 Mabini Pinaglabanan IA Inc. | I31: =I30+15 -> 45710
A32: =A31 -> 45705 | B32: =B31+1 -> 26 | C32: From COA : AOM No. 2025-03 (2024) NIA ACIMO Incomplete Attachments in the Disbursement Vouchers
A33: =A32 -> 45705 | B33: =B32+1 -> 27 | C33: Itinerary: ENG-TO306,307 | F33: BPB | G33: for signature
A34: =A33 -> 45705 | B34: =B33+1 -> 28 | C34: Gate Pass Vcls: 269-2025 RIS: 140-2025 | F34: BPB | G34: for signature
A35: =A34 -> 45705 | B35: =B34+1 -> 29 | C35: Travel Order: ENG-TO 307 OMS-TO 232 | F35: BPB | G35: for signature
A36: =A35 -> 45705 | B36: =B35+1 -> 30 | C36: Itinerary of travel : OMS-TO 234, 233 ENG-TO 309 | F36: BPB | G36: for signature
A37: =A36 -> 45705 | B37: =B36+1 -> 31 | C37: Travel Order : OMS-TO 237 | F37: BPB | G37: for signature
A38: =A37 -> 45705 | B38: =B37+1 -> 32 | C38: Authority to Render Overtime Services: 1. GNJ Jacob (2/15/25) | F38: MCGS | G38: for signature
A39: =A38 -> 45705 | B39: =B38+1 -> 33 | C39: Travel Order : OMS-TO 238 | F39: MCGS | G39: for signature
A40: =A39 -> 45705 | B40: =B39+1 -> 34 | C40: Travel Order : OMS-TO 235 ENG-TO 310 | F40: MCGS | G40: for signature
A41: =A40 -> 45705 | B41: =B40+1 -> 35 | C41: Itinerary : OMS-TO 239
A42: =A41 -> 45705 | B42: =B41+1 -> 36 | C42: Gate Pass Vcls: 270, 271, 272,273, 274,275, 276-2025 RIS: 141,142,143-2025 Transpo Req. 204, 215, 213-2025
A43: =A42 -> 45705 | B43: =B42+1 -> 37 | C43: To Region: Job Order Appointment for the Period of January 27, 2025 to June 30, 2025 | F43: BPB | G43: for signature
A44: =A43 -> 45705 | B44: =B43+1 -> 38 | C44: Gate Pass Vcls: 277-2025 RIS: 144-2025 Transpo Req: 212-2025 | F44: BPB | G44: for signature
A45: =A44 -> 45705 | B45: =B44+1 -> 39 | C45: Itinerary: OMS-TO240, 236 | F45: BPB | G45: for signature
A46: ***NOTHING FOLLOWS***
A49: Received, Recorded, Tracked, Disseminated & Filed:
A51: COLEEN M. RASTRULLO
A52: Engineering Assistant A

Sheet 0218
A1: INCOMING DOCUMENTS TO THE OFFICE OF THE IMO MANAGER
A2: 45706
A3: =TEXT(A2,"DDDD") -> Tuesday
A4: NOTE: | B4: MCGS, BPB, LFCP, VEP on official business. OIC : VMM
A5: NO. | C5: DOCUMENTS | F5: TO | G5: REMARKS
C6: PARTICULAR | D6: SECTION | E6: TYPE
A7: =A2 -> 45706 | B7: 1 | C7: Travel Order: OMS-TO241 | F7: VMM | G7: For signature
A8: =A7 -> 45706 | B8: =B7+1 -> 2 | C8: Travel Order: OMS-TO242 ENG-TO311 | F8: VMM | G8: For signature
A9: =A8 -> 45706 | B9: =B8+1 -> 3 | C9: Payroll: Paraiso (7/1-15/2024 & 09/1-15/2024) Mariñas (12/1-18/2024) Dayupay, Guarin & 2 (11/1-15/2024) Dacillo, Peligan S (11/16-30/2024) | F9: MCGS | G9: For signature
A10: =A9 -> 45706 | B10: =B9+1 -> 4 | C10: FIVC: (For Signature) Mintay CIS (CAT-RREIS-012-23INF) February 11, 2025 | F10: MCGS | G10: For signature
A11: =A10 -> 45706 | B11: =B10+1 -> 5 | C11: FIVC: (For Signature) Apud Rawis CIS et. Al (NDRRMF-AL-121-17) February 11, 2025 | F11: MCGS | G11: For signature
A12: =A11 -> 45706 | B12: =B11+1 -> 6 | C12: Travel order: ENG-TO312 | F12: VMM | G12: For signature
A13: =A12 -> 45706 | B13: =B12+1 -> 7 | C13: ACIMO-5-501-2023-762 Repair of CIS P50,132.30 & 1 other | F13: MCGS
A14: =A13 -> 45706 | B14: =B13+1 -> 8 | C14: Post-Qualification Evaluation -Performance Track Record of D'Brothers International Trading Corp. | F14: MCGS
A15: =A14 -> 45706 | B15: =B14+1 -> 9 | C15: Applicant: 1. Diane O. Rayel 2. Rendell Ace Zabala | F15: MCGS
A16: =A15 -> 45706 | B16: =B15+1 -> 10 | C16: TRAVEL ORDER: ENG-TO313 | F16: VMM | G16: For signature
A17: =A16 -> 45706 | B17: =B16+1 -> 11 | C17: Submission of Application for Condonation | F17: MCGS
A18: =A17 -> 45706 | B18: =B17+1 -> 12 | C18: PRLE Cluster Strategic Planning Meeting for FY 2025 | F18: MCGS
A19: =A18 -> 45706 | B19: =B18+1 -> 13 | C19: Requisition and Issue Slip: 145-2025 | F19: VMM | G19: For signature
A20: ***NOTHING FOLLOWS***
A22: Received, Recorded, Tracked, Disseminated & Filed:
A24: COLEEN M. RASTRULLO
A25: Engineering Assistant A

Sheet 0219
A1: INCOMING DOCUMENTS TO THE OFFICE OF THE IMO MANAGER
A2: 45707
A3: =TEXT(A2,"DDDD") -> Wednesday
A4: NOTE:
A5: NO. | C5: DOCUMENTS | F5: TO | G5: REMARKS
C6: PARTICULAR | D6: SECTION | E6: TYPE
A7: =A2 -> 45707 | B7: 1 | C7: TRAVEL ORDER: ENGTO-314 | D7: ENG'G | F7: MCGS | G7: FOR SIGNATURE
A8: =A7 -> 45707 | B8: =B7+1 -> 2 | C8: Gate Pass Vcls : 280, 279,278-2023 RIS : 146, 147, 148-2025 Transpo Req. : 220, 217, 218-2025 Travel Order : OMS-TO 244 | D8: ENG'G | F8: MCGS | G8: FOR SIGNATURE
A9: =A8 -> 45707 | B9: =B8+1 -> 3 | C9: Travel Order : ENG-TO 315 | D9: ENG'G | F9: MCGS | G9: FOR SIGNATURE
A10: =A9 -> 45707 | B10: =B9+1 -> 4 | C10: Transmittal to COA : JEV Fund 501 COB (12/1-15/24) Personnel Locator Slip : 2/19/25, 9:00 am, Official, JP Papa | D10: FINANCE | F10: MCGS | G10: FOR SIGNATURE
A11: =A10 -> 45707 | B11: =B10+1 -> 5 | C11: Transmittal to COA : Financial Reports for the month of November 2024 (FUND-COB) | D11: FINANCE | F11: MCGS | G11: FOR SIGNATURE
A12: =A11 -> 45707 | B12: =B11+1 -> 6 | C12: Gate Pass Vcls : 282,281-2025 | D12: OMS | F12: MCGS | G12: FOR SIGNATURE
A13: =A12 -> 45707 | B13: =B12+1 -> 7 | C13: Itinerary of Travel : OMS-TO 245 | D13: OMS | F13: MCGS | G13: FOR SIGNATURE
A14: =A13 -> 45707 | B14: =B13+1 -> 8 | C14: Personnel Locator Slip : 2/19/25, 9:15am, Personal, DDL Detera | D14: OMS | F14: MCGS | G14: FOR SIGNATURE
A15: =A14 -> 45707 | B15: =B14+1 -> 9 | C15: Certification to Realm Const. & Trading : Repair/Rehab of Manambrag CIS CAT-CARP-001-23INF | D15: FINANCE | F15: MCGS | G15: FOR SIGNATURE
A16: =A15 -> 45707 | B16: =B15+1 -> 10 | C16: Authority to Render Overtime Services : 1. DMC Mayor & 6 (2/17-21/25) | D16: FINANCE | F16: MCGS | G16: FOR SIGNATURE
A17: =A16 -> 45707 | B17: =B16+1 -> 11 | C17: From Landbank : Letter offering for Government Purchase Card & Electronic Salary Loan | D17: ADMIN
A18: =A17 -> 45707 | B18: =B17+1 -> 12 | C18: Resolution No. 1 s. 2025- San Francisco RIS Federation of Irrigators Assoc. Inc. " A resolution requesting the NIA ACIMO, Ligao City for construction of destriyed dam of San francisco RIS located at the main river of Brgy. Bantayan Tabaco City to typhoon Kristine last October 2024" | D18: ADMIN
A19: =A18 -> 45707 | B19: =B18+1 -> 13 | C19: Cheque & Attachments: Mark Cloyd G. So (Php 18,553.50) | D19: FINANCE | F19: MCGS | G19: FOR SIGNATURE
A20: =A19 -> 45707 | B20: =B19+1 -> 14 | C20: Cheque & Attachments: Aldrin P. Francia (Php 9,614.47) | D20: FINANCE | F20: MCGS | G20: FOR SIGNATURE
A21: =A20 -> 45707 | B21: =B20+1 -> 15 | C21: TEV - Cheque with Attachments : Francisco B. Juarez Jr. (Php 3,420.00) | D21: FINANCE | F21: MCGS | G21: FOR SIGNATURE
A22: =A21 -> 45707 | B22: =B21+1 -> 16 | C22: Cheque & Attachments : Vilma M. Manlangit (Php 40,909.00) | D22: FINANCE | F22: MCGS | G22: FOR SIGNATURE
A23: =A22 -> 45707 | B23: =B22+1 -> 17 | C23: From CSPC : Conduct a research study "Kap-Oriented communication strategies of NIA ACIMO towards sustanable irrigation management practices"' | D23: ADMIN | F23: MCGS | G23: FOR SIGNATURE
A24: =A23 -> 45707 | B24: =B23+1 -> 18 | C24: RIS : 149-2025 | D24: OMS | F24: MCGS | G24: FOR SIGNATURE
A25: =A24 -> 45707 | B25: =B24+1 -> 19 | C25: From Catanduanes : CY 2025 POW of Alibuag CIS, San Andres Catanduanes damaged by Typhoon Krisitine under MDRRF Fund of CY 2025 | D25: ADMIN | F25: MCGS | G25: FOR SIGNATURE
A26: =A25 -> 45707 | B26: =B25+1 -> 20 | C26: Travel Order : OMS-TO 246 | D26: OMS | F26: MCGS | G26: FOR SIGNATURE
A27: =A26 -> 45707 | B27: =B26+1 -> 21 | C27: Transmittal to COA : 1. Copy of Inspection and Acceptance Report (IAR-AFS-24-10-003) (IAR-AFS-24-10-005) 2. Received transmittal (various reports) 3. 1st & Final ppmp, CSE, APP 4. Indicative PPMP, CSE, APP 5. Gender & Development Budget for CY 2025 | D27: FINANCE | F27: MCGS | G27: FOR SIGNATURE
A28: =A27 -> 45707 | B28: =B27+1 -> 22 | C28: Audit Observation Memorandum AOM No. 2025-04 (2024) NIA ACIM0 Inconsistent application of rates of expenses and allowances for travel
A29: =A28 -> 45707 | B29: =B28+1 -> 23 | C29: Applicant : Jovelyn De Vera Alcantara (BSABE)
A30: =A29 -> 45707 | B30: =B29+1 -> 24 | C30: From Municipal Agricultural Office Services (MASO) Request available data of all irrigation facilities constructed/rehabilitated in the municipality funded by NIA
A31: =A30 -> 45707 | B31: =B30+1 -> 25 | C31: Personnel Locator Slip : 2/19/25,3:00, Official, JLAgripa | D31: OMS | F31: MCGS | G31: FOR SIGNATURE
A32: =A31 -> 45707 | B32: =B31+1 -> 26 | C32: From DPWH : FY 2025 General Appropriations Act (GAA) NIA-DPWH Convergence Program
A33: =A32 -> 45707 | B33: =B32+1 -> 27 | C33: Application for Leave & CTO: 1. GS Arabaca & 3 | D33: ADMIN | F33: MCGS | G33: FOR SIGNATURE
A34: =A33 -> 45707 | B34: =B33+1 -> 28 | C34: To : Albay 3rd District Engineering Office Inquiry if there are any proposed or ongoing road and slope protection works along the highlighted areas in Brgy. San Agustin, Libon, Albay | D34: ENG'G | F34: MCGS | G34: FOR SIGNATURE
A35: =A34 -> 45707 | B35: =B34+1 -> 29 | C35: Replenishment of Petty Cash named to VM Manlangit (Php 17,112.00) | D35: FINANCE | F35: MCGS | G35: FOR SIGNATURE
A36: =A35 -> 45707 | B36: =B35+1 -> 30 | C36: Payment to Bureau of Treasury for Bondo Premium of Bonded Officials (Additional) for the period of 10/30/24 - 10/29/25 Php 113,736.98 | D36: FINANCE | F36: MCGS | G36: FOR SIGNATURE
A37: =A36 -> 45707 | B37: =B36+1 -> 31 | C37: Division Performance Commitment and Review (DPCR) Rating (July 1, 2024 to December 31, 2024 | D37: ADMIN | F37: MCGS | G37: FOR SIGNATURE
A38: =A37 -> 45707 | B38: =B37+1 -> 32 | C38: Purchase Request : 1. PR No. 2025-02-0019 2. PR No. 2025-02-0018 | D38: ADMIN | F38: MCGS | G38: FOR SIGNATURE
A39: =A38 -> 45707 | B39: =B38+1 -> 33 | C39: Sworn Statement of Assets, Liabilities, and Net Worth (SALN) for CY 2024 | D39: ADMIN | F39: MCGS | G39: FOR SIGNATURE
A40: =A39 -> 45707 | B40: =B39+1 -> 34 | C40: Program of Work (POW) CY 2024 for Equipment | D40: OMS | F40: MCGS | G40: FOR SIGNATURE
A41: =A40 -> 45707 | B41: =B40+1 -> 35 | C41: Preventive Maintenance Schedule Monthly Summary Report on Operations & Maintenance and Repair Cost of Selected Equipment | D41: OMS | F41: MCGS | G41: FOR SIGNATURE
A42: =A41 -> 45707 | B42: =B41+1 -> 36 | C42: Travel Order : ENG-TO 316 Gate Pass Vcls : 283-2025 | D42: ENG'G | F42: MCGS | G42: FOR SIGNATURE
A43: ***NOTHING FOLLOWS***
A45: Received, Recorded, Tracked, Disseminated & Filed:
A47: COLEEN M. RASTRULLO
A48: Engineering Assistant A

Sheet 0220
A1: INCOMING DOCUMENTS TO THE OFFICE OF THE IMO MANAGER
A2: 45708
A3: =TEXT(A2,"DDDD") -> Thursday
A4: NOTE: | B4: MCGS & other signatories on official business from 10:45am onwards. OIC: LFCP
A5: NO. | C5: DOCUMENTS | F5: TO | G5: REMARKS
C6: PARTICULAR | D6: SECTION | E6: TYPE
A7: =A2 -> 45708 | B7: 1 | C7: Gate Pass Vcls : 289, 287,288, 286-2025 RIS : 151, 150-2025 Transpo Req. : 224, 222,223, 221-2025 | D7: OMS | F7: MCGS | G7: for signature
A8: =A7 -> 45708 | B8: =B7+1 -> 2 | C8: Gate Pass: 290-2025 RIS : 152-2025 | D8: OMS | F8: LFCP | G8: for signature
A9: =A8 -> 45708 | B9: =B8+1 -> 3 | C9: TRAVEL ORDER: ENG-TO317 | D9: ENG'G | F9: LFCP | G9: for signature
A10: =A9 -> 45708 | B10: =B9+1 -> 4 | C10: AUTHORITY TO RENDER OVERTIME SERVICES: PG. CREDO & 1 (02/19/25) JV. Penaflor (02/16/25) | D10: IMO | F10: MCGS | G10: for signature
A11: =A10 -> 45708 | B11: =B10+1 -> 5 | C11: RIS: 153-2025 | D11: OMS | F11: MCGS | G11: for signature
A12: =A11 -> 45708 | B12: =B11+1 -> 6 | C12: Gate pass: 283, 284-2023 Itinerary of travel: OMS-TO247 | D12: OMS | F12: MCGS | G12: for signature
A13: =A12 -> 45708 | B13: =B12+1 -> 7 | C13: Authority to Render Overtime Serices : VM Manlangit (2/1/25) | D13: ADMIN | F13: MCGS | G13: for signature
A14: =A13 -> 45708 | B14: =B13+1 -> 8 | C14: From Region : (Sent from GC- Advance copy) Evaluation of the SMD-Monitored Projects as of December 2024 | D14: ADMIN | F14: MCGS
A15: =A14 -> 45708 | B15: =B14+1 -> 9 | C15: From Catanduanes : Proposal for 1st Quarter strategic management review and planning 2025 | D15: CATNES | F15: MCGS
A16: =A15 -> 45708 | B16: =B15+1 -> 10 | C16: To Catanduanes : NIA Certification for Sand and Gravel permit application | D16: CATNES | F16: MCGS
A17: =A16 -> 45708 | B17: =B16+1 -> 11 | C17: To Region : Endorsement of Tuliw Pawa Irrigators Association Inc. as Outstanding IA under Communal Irrigation System (CIS) category | D17: OMS | F17: MCGS
A18: =A17 -> 45708 | B18: =B17+1 -> 12 | C18: Travel Order : OMS-TO 248 | D18: OMS | F18: MCGS | G18: for signature
A19: =A18 -> 45708 | B19: =B18+1 -> 13 | C19: From Region : 1st Endorsement Submission of Program of Works (POW) CY 2025 for Operations & Maintenance of NIS and CIP Pump PIS (OMNISPIS) & OMCIMPIS & Establishment of Pump IP- Solar Pump IP (EPIP-SPIP) | D19: ADMIN
A20: =A19 -> 45708 | B20: =B19+1 -> 14 | C20: From PSABE : 74th PSABE Annual Convention Invitation April 20-25, 2025 | D20: ADMIN
A21: =A20 -> 45708 | B21: =B20+1 -> 15 | C21: From Catanduanes : Submission of certification of No Defects & NIA Certification from IA for Repair/Restoration of Gigmoto CIS, Catanduanes | D21: ENG'G | G21: for signature
A22: =A21 -> 45708 | B22: =B21+1 -> 16 | C22: From Catanduanes : Resubmission of attachments for Variation No. 1 of Repair/Restoration of Bugao & Obo Mosbos CAT-RREIS-006-23INF | D22: ENG'G
A23: =A22 -> 45708 | B23: =B22+1 -> 17 | C23: 2nd Revised Annual Procurement Plan - Common Supplies & Equipment (APP-CSE) 2024 form | D23: ENG'G | F23: MCGS | G23: for signature
A24: =A23 -> 45708 | B24: =B23+1 -> 18 | C24: To region : Request for the issuance of Irrigation Coverage Certification for Land Conversion | D24: ENG'G
A25: =A24 -> 45708 | B25: =B24+1 -> 19 | C25: Personnel Locator Slip : 2/20/25, 1:30, Official, VM Manlangit | D25: ADMIN | F25: MCGS | G25: for signature
A26: =A25 -> 45708 | B26: =B25+1 -> 20 | C26: Cheques & attachments : Bureau of Treasury (Php 113,736.98) | D26: FINANCE | F26: MCGS | G26: for signature
A27: =A26 -> 45708 | B27: =B26+1 -> 21 | C27: Cheques & attachments (TEVs) : 1. Milany B. Dacillo (Php 1,801.00) 2. Milany B. Dacillo (Php 1,107.00) 3. Milany B. Dacillo (Php 1,952.00) 4. Milany B. Dacillo (Php 2,000.00) 5. Milany B. Dacillo (Php 2,000.00) 6. Raymond Gil C. Aycardo (Php 2,550.00) 7. Francisco B. Juarez Jr. (Php 2,550.00) 8. Marilou A. Robledo (Php 2,378.00) | D27: FINANCE | F27: MCGS | G27: for signature
A28: =A27 -> 45708 | B28: =B27+1 -> 22 | C28: Cheque & Attachments: Replenishment for Petty Cash of VM Manlangit (Php 17,112.00) | D28: FINANCE | F28: MCGS | G28: for signature
A29: =A28 -> 45708 | B29: =B28+1 -> 23 | C29: Payment for Bac Honorarium : BP Balingasa & 12 (October-December 2024) Php 269,693.01 | D29: FINANCE | F29: MCGS | G29: for signature
A30: =A29 -> 45708 | B30: =B29+1 -> 24 | C30: Travel Order : OMS-TO 249 | D30: OMS | F30: MCGS | G30: for signature
A31: =A30 -> 45708 | B31: =B30+1 -> 25 | C31: Remittances : 1. BIR NIA 501 LFP for Sept-November 2024 (Php 703,940.18) 2. BIR NIA 501 LFP for Sept-November 2024 (Php 493,225.47) 3. SSS for Beo & 3 R. Nacario, Banga & 14 - December 2024 (Php 10,830.00) 4. HDMF of JL Agripa et. Al - Nov. 2024 (Php 12,600) 5. HDMF of JL Agripa et. Al - Nov. 2024 (Php 12,400) 6. GSIS of EMS Abila & 39 - Dec. 2024 (Php 278,728.52) 7. SSS of K. Almiñana & 1, A, Calpe & 11 - December 2024 (Php 9,660.00) 8. SSS of Beo & 3, Banga & 14 - Nov. 2024 (Php 11,320.00) 9. HDMF for Pag-Ibig Contri. of V. Manlangit & 1 - Dec. 2024 (Php 800.00) 10. HDMFfor Pag Ibig Contri of M. Dacillo - Dec. 2024 (Php 3900.00) | D31: FINANCE | F31: MCGS | G31: for signature
A32: =A31 -> 45708 | B32: =B31+1 -> 26 | C32: Salary Differential : Rosana Rebadajo (Php 7,592.05) LCWD : 12/3/24 - 1/06/25 (Php 5,660.08) Bureau of Treasury for LD Dec. 2024 (Php 4,488.42) FICELCO : 11/23 - 12/23/24 (Php 6,394.25) | D32: FINANCE | F32: MCGS | G32: for signature
A33: =A32 -> 45708 | B33: =B32+1 -> 27 | C33: Payment for 10& Retention Claims of : Omega Const. & Supply CASANRA CIP AL-SIP-2020-01-15INF | D33: FINANCE | F33: MCGS | G33: for signature
